Workbook

Sheet 1. Assumptions & Goals
A1: TIMELINE
A2: Year | B2: 2025 | C2: 2026 | D2: 2027 | E2: 2028 | F2: 2029 | G2: 2030 | H2: 2031 | I2: 2032 | J2: 2033 | K2: 2034 | L2: 2035 | M2: 2036 | N2: 2037 | O2: 2038 | P2: 2039 | Q2: 2040 | R2: 2041 | S2: 2042 | T2: 2043 | U2: 2044 | V2: 2045 | W2: 2046 | X2: 2047 | Y2: 2048 | Z2: 2049 | AA2: 2050 | AB2: 2051 | AC2: 2052 | AD2: 2053 | AE2: 2054 | AF2: 2055 | AG2: 2056 | AH2: 2057 | AI2: 2058 | AJ2: 2059 | AK2: 2060 | AL2: 2061 | AM2: 2062 | AN2: 2063 | AO2: 2064 | AP2: 2065 | AQ2: 2066 | AR2: 2067 | AS2: 2068 | AT2: 2069 | AU2: 2070 | AV2: 2071 | AW2: 2072 | AX2: 2073 | AY2: 2074 | AZ2: 2075 | BA2: 2076 | BB2: 2077 | BC2: 2078 | BD2: 2079 | BE2: 2080 | BF2: 2081 | BG2: 2082 | BH2: 2083 | BI2: 2084 | BJ2: 2085 | BK2: 2086 | BL2: 2087 | BM2: 2088
A3: Age | B3: 22 | C3: 23 | D3: 24 | E3: 25 | F3: 26 | G3: 27 | H3: 28 | I3: 29 | J3: 30 | K3: 31 | L3: 32 | M3: 33 | N3: 34 | O3: 35 | P3: 36 | Q3: 37 | R3: 38 | S3: 39 | T3: 40 | U3: 41 | V3: 42 | W3: 43 | X3: 44 | Y3: 45 | Z3: 46 | AA3: 47 | AB3: 48 | AC3: 49 | AD3: 50 | AE3: 51 | AF3: 52 | AG3: 53 | AH3: 54 | AI3: 55 | AJ3: 56 | AK3: 57 | AL3: 58 | AM3: 59 | AN3: 60 | AO3: 61 | AP3: 62 | AQ3: 63 | AR3: 64 | AS3: 65 | AT3: 66 | AU3: 67 | AV3: 68 | AW3: 69 | AX3: 70 | AY3: 71 | AZ3: 72 | BA3: 73 | BB3: 74 | BC3: 75 | BD3: 76 | BE3: 77 | BF3: 78 | BG3: 79 | BH3: 80 | BI3: 81 | BJ3: 82 | BK3: 83 | BL3: 84 | BM3: 85
A4: Event | H4: Buy car | J4: Nhi's 6 months of maternity leave Buy apartment | K4: Child is born | AC4: Child goes to university | AF4: Child is independent (when year ends) | AN4: Nhi retires (when year ends) | AP4: Husband retires (when year ends) | AY4: Trash car Go travel around the world | BM4: Nhi and Husband die (when year ends)
A6: CUSTOMER PROFILE | F6: FINANCIAL GOALS
B7: Nhi | C7: Husband | F7: Period | G7: Age | H7: Goals
A8: Age | B8: 22 | C8: 22 | F8: Establishing the Foundation for Family | G8: 28 | H8: Buy car around 500 million
A9: Occupation | B9: Financial Analyst | C9: Developer | G9: 30 | H9: Buy an apartment around 4 billion on installments Prepare medical and living expenses for pregnancy
A10: Accommodation | B10: Renting a one-bedroom apartment | F10: Growing the Family and Preparing for the Future | G10: 31 | H10: Give birth to a child, prepare childbirth and initial care costs
A11: Source of income | B11: Salary from employment | G11: 32-52 | H11: Financial support for the child from childhood to independence
A12: Career Timline | B12: Planning to work until retirement | G12: 53 | H12: Prepare marriage cost for the child
A13: Life expectancy | B13: 85 years | F13: Enjoying Life After Retirement | G13: 60 | H13: Nhi retires, enjoy a secure, worry-free retirement
G14: 62 | H14: Husband retires, enjoy a secure, worry-free retirement
A15: ASSUMPTIONS | G15: 71 | H15: Trash car Prepare for travelling around the world, around 5.5 billion for Nhi and Husband
A16: NUMBER | B16: ASSUMPTIONS | C16: BACK-UP REASONS (IF ANY)
A17: 0 | B17: Applicable law used in the model and insurance policy will not change.
A18: Family
A19: 1 | B19: Nhi and Husband are of the same age, marry at 22, get pregnant at 30, live till 85 without any significant health problems.
A20: 2 | B20: Nhi and Husband's parents pay for their marriage, but their parents also take the profit from the wedding gift money. | C20: Marriage Preparation
A21: 3 | B21: After marriage, Nhi and Husband move into the one-room apartment Nhi rents.
A22: 4 | B22: Nhi and Husband have their own phones, laptops, motorbikes and savings account before marriage but decide to combine them as family's assets for easier control.
A23: 5 | B23: Nhi and Husband do not plan to change motorbikes or car. As they carefully maintain, the vehicles are still usable until they die. | C23: Vehicles Longevity
A24: 6 | B24: When Nhi and Husband travel around the world, they ask their child to take care of the home, but still pay for apartment service and other necessary expenses.
A25: Work
A26: 7 | B26: Risk premium with occupational income volatility for Nhi and Husband is 3%.
A27: 8 | B27: Nhi (started as a junior financial analyst) and Husband (started as a junior developer) work for average companies with average abilities, so they receive average salaries for their professions.
A28: 9 | B28: Nhi and Husband's salaries are the salaries after their companies pay for social security and other compulsory obligations for laborers, except taxes. | C28: After-Tax Income
A29: 10 | B29: Nhi and Husband's salaries and expenses increase as inflation rate.
A30: 11 | B30: When Nhi has her maternity leave, Nhi loses her yearly bonus (thirteen-month salary) for that year. | C30: Maternity Leave
A31: Spending
A32: 12 | B32: Fuel and Vehicle Upkeep Expenses already include all compulsory obligations regarding the vehicles (compulsory insurances...).
A33: 13 | B33: Inflation, refinancing rate and other factors (economic, political,...) impacting mortgage rate is fairly stable, it is the same as 2025 when they buy the apartment. Nhi and Husband decide to have an installment of 20 years for the apartment to reduce financial pressure. | C33: 20-year mortgage
A34: 14 | B34: Nhi and Husband have an average spending style, so they spend an average amount compared to the general raising their child. They raise the child until he finishes college, give him money for his marriage and even the wedding gift money.
A35: Saving and Investment
A36: 15 | B36: The Emergency Fund is three times the monthly expenses. | C36: Emergency Fund
A37: Insurance
A38: 16 | B38: Because a 4-seat car can carry up to 5 people (NhaxeHoangDung, n.d.), they buy insurance for 5 people in the car in case they carry people other than their family (friends, colleagues...). | C38: Maximum Carriage
A39: 17 | B39: Inflation, business operation and other factors (economic, political...) impacting the insurance rate and dividend are fairly stable, it is the same as 2025 when they buy life insurance.
A40: 18 | B40: In life insurance calculation, the one who dies has joint properties (apartment, car, bond, stock...) in their name as the worst-case scenario. They also write a will for the surviving spouse to inherit all the joint properties.

Sheet 1. Drivers
A1: ANNUAL TAX INCOME | F1: TAX DEDUCTIONS | J1: DISCOUNT RATE FOR HUMAN CAPITAL AND PENSION VALUE
A2: Tax grade | B2: Taxable income/year (VND million) | C2: Tax rate | D2: Income Tax | F2: Type of deductions | G2: Deduction/month | H2: Tax Deductions | K2: Rate | L2: Risk Free Rate
A3: 1 | B3: Up to 60 | C3: 0.05 | F3: Personal | G3: 11000000 | J3: Risk Free Rate (Vietnam 20-Year Government Bond) | K3: 0.03474
A4: 2 | B4: Between over 60 and 120 | C4: 0.1 | F4: Dependents | G4: 4400000 | J4: Risk premium with occupational income volatility | K4: 0.03
A5: 3 | B5: Between over 120 and 216 | C5: 0.15
A6: 4 | B6: Between over 216 and 384 | C6: 0.2 | F6: AGE OF RETIREMENT
A7: 5 | B7: Between over 384 and 624 | C7: 0.25 | F7: Gender | G7: Age | H7: Retirement
A8: 6 | B8: Between over 624 and 960 | C8: 0.3 | F8: Male | G8: 62
A9: 7 | B9: Over 960 | C9: 0.35 | F9: Female | G9: 60
A11: INFLATION | E11: SAVINGS ACCOUNT INTEREST RATE (2025) | J11: ANNUAL SAVINGS ACCOUNT INTEREST RATE | N11: STOCK MARKET ANNUAL RETURN | R11: BOND INVESTMENT FUND (DCBF) ANNUAL RETURN
A12: Year | B12: Rate | C12: Inflation | E12: Number | F12: Bank | G12: Interest Rate | H12: Interest Rate | J12: Period | K12: Rate | L12: Annual Interest Rate | N12: Year | O12: Return | P12: Stock Return | R12: Date | S12: Price | T12: Return | U12: Bond Return
A13: 2021 | B13: 0.0184 | E13: 1 | F13: BIDV | G13: 0.047 | J13: 2008-2011 | K13: =AVERAGE(9%,14%) -> 0.115 | N13: 2008 | O13: -0.6595 | R13: 44000 | S13: 20036
A14: =A13+1 -> 2022 | B14: 0.0316 | E14: =E13+1 -> 2 | F14: Vietcombank | G14: 0.046 | J14: 2012-2015 | K14: =AVERAGE(6.5%,9%) -> 0.0775 | N14: 2009 | O14: 0.5676 | R14: 44196 | S14: 20756 | T14: =(S14-S13)/S13 -> 0.035935316
A15: =A14+1 -> 2023 | B15: 0.0325 | E15: =E14+1 -> 3 | F15: Agribank | G15: 0.048 | J15: 2016-2019 | K15: =AVERAGE(6%,7%) -> 0.065 | N15: 2010 | O15: -0.0204 | R15: 44350 | S15: 21388 | T15: =(S15-S14)/S14 -> 0.030449027
A16: =A15+1 -> 2024 | B16: 0.0362 | E16: =E15+1 -> 4 | F16: Vietinbank | G16: 0.047 | J16: 2020-2023 | K16: =AVERAGE(4%,6%) -> 0.05 | N16: 2011 | O16: -0.2746 | R16: 44560 | S16: 22270 | T16: =(S16-S15)/S15 -> 0.041238077
A17: 2025 | B17: 0.0295 | E17: =E16+1 -> 5 | F17: VIB | G17: 0.049 | J17: 2024 | K17: =AVERAGE(1.7%,6%) -> 0.0385 | N17: 2012 | O17: 0.1769 | R17: 44714 | S17: 22971 | T17: =(S17-S16)/S16 -> 0.031477324
A18: 2026 | B18: 0.0249 | E18: =E17+1 -> 6 | F18: Techcombank | G18: 0.0475 | J18: 2025 | K18: =G26 -> 0.050346154 | N18: 2013 | O18: 0.2197 | R18: 44923 | S18: 23257 | T18: =(S18-S17)/S17 -> 0.012450481
A19: 2027 | B19: 0.028 | E19: =E18+1 -> 7 | F19: VPBank | G19: 0.053 | J19: Mean | K19: =AVERAGE(K13:K18) -> 0.066057692 | N19: 2014 | O19: 0.0812 | R19: 45084 | S19: 24073 | T19: =(S19-S18)/S18 -> 0.035086211
A20: 2028 | B20: 0.029 | E20: =E19+1 -> 8 | F20: TPBank | G20: 0.052 | J20: Standard Deviation | K20: =STDEV(K13:K18) -> 0.027537331 | N20: 2015 | O20: 0.0612 | R20: 45291 | S20: 25390 | T20: =(S20-S19)/S19 -> 0.054708595
A21: 2029 | B21: 0.029 | E21: =E20+1 -> 9 | F21: ACB | G21: 0.049 | N21: 2016 | O21: 0.1482 | R21: 45449 | S21: 26153 | T21: =(S21-S20)/S20 -> 0.030051201
A22: 2030 | B22: 0.029 | E22: =E21+1 -> 10 | F22: Sacombank | G22: 0.054 | N22: 2017 | O22: 0.4803 | R22: 45610 | S22: 26863 | T22: =(S22-S21)/S21 -> 0.027147937
A23: 2030 Afterwards | B23: =AVERAGE(B13:B22) -> 0.02881 | E23: =E22+1 -> 11 | F23: MSB | G23: 0.056 | N23: 2018 | O23: -0.0932 | R23: Mean | T23: =AVERAGE(T14:T22)*2 -> 0.066343149
E24: =E23+1 -> 12 | F24: HDBank | G24: 0.056 | N24: 2019 | O24: 0.0767 | R24: Standard Deviation | T24: =STDEV(T14:T22)*SQRT(2) -> 0.016014706
E25: =E24+1 -> 13 | F25: MBBank | G25: 0.05 | N25: 2020 | O25: 0.1487
E26: Mean | G26: =AVERAGE(G13:G25) -> 0.050346154 | N26: 2021 | O26: 0.3573
N27: 2022 | O27: -0.3278
N28: 2023 | O28: 0.122
N29: 2024 | O29: 0.1211
N30: Mean | O30: =AVERAGE(O13:O29) -> 0.069729412
N31: Standard Deviation | O31: =STDEV(O13:O29) -> 0.29518767

Sheet 2. Balance Sheet & Cashflow Sta
A1: TRADITIONAL BALANCE SHEET (2025)
A2: ASSETS | B2: AMOUNT | C2: % | F2: LIABILITIES AND NET WORTH | G2: AMOUNT | H2: %
A3: Liquid Assets | F3: Liabilities
A4: Cash | B4: ='3. Funding Allocation'!L5 -> 41955535 | C4: =B4/$B$17 -> 0.17010733 | F4: Short-term Liabilities | G4: 0 | H4: =G4/$G$9 -> 0
A5: Saving Account | B5: 60000000 | C5: =B5/$B$17 -> 0.24326802 | F5: Long-term liabilities | G5: 0 | H5: =G5/$G$9 -> 0
A6: Total Liquid Assets | B6: =SUM(B4:B5) -> 1.0195553e+08 | C6: =B6/$B$17 -> 0.41337535 | F6: Other Liabilities | G6: 0 | H6: =G6/$G$9 -> 0
F7: TOTAL LIABILITIES | G7: =SUM(G4:G6) -> 0 | H7: =G7/$G$9 -> 0
A8: Tangible Assets | F8: NET WORTH | G8: =G9-G7 -> 2.4664154e+08 | H8: =G8/$G$9 -> 1
A9: Samsung Galaxy S23 | B9: 8790000 | C9: =B9/$B$17 -> 0.035638765 | D9: Samsung S23 | F9: TOTAL LIABILITIES AND NET WORTH | G9: =B17 -> 2.4664154e+08 | H9: =G9/$G$9 -> 1
A10: Samsung Galaxy S24 | B10: 11090000 | C10: =B10/$B$17 -> 0.044964039 | D10: Samsung S24
A11: Laptop Dell Inspiron 15 | B11: 11990000 | C11: =B11/$B$17 -> 0.048613059 | D11: Dell Inspiron | F11: RATIO | G11: CALCULATION
A12: Laptop Dell Precision 5550 | B12: 14490000 | C12: =B12/$B$17 -> 0.058749227 | D12: Dell Precision | F12: Solvency Ratio | G12: =G8/B17 -> 1
A13: Honda Vision 2025 (Standard version) | B13: 34735509 | C13: =B13/$B$17 -> 0.14083397 | D13: Vision
A14: Honda Airblade 160 (Standard version) | B14: 63590500 | C14: =B14/$B$17 -> 0.25782558 | D14: Airblade
A15: Total Tangible Assets | B15: =SUM(B9:B14) -> 144686009 | C15: =B15/$B$17 -> 0.58662465
A17: TOTAL ASSETS | B17: =SUM(B6,B15) -> 2.4664154e+08 | C17: =B17/$B$17 -> 1
A19: ECONOMIC (HOLISTIC) BALANCE SHEET (2025)
A20: ASSETS | B20: AMOUNT | C20: % | F20: LIABILITIES AND NET WORTH | G20: AMOUNT | H20: %
A21: Financial Capital | F21: Liabilities
A22: Liquid Assets | B22: =B6 -> 1.0195553e+08 | C22: =B22/$B$36 -> 0.0040010591 | F22: Short-term Liabilities | G22: 0 | H22: =G22/$G$26 -> 0
A23: Tangible Assets | B23: =B15 -> 144686009 | C23: =B23/$B$36 -> 0.0056779387 | F23: Long-term liabilities | G23: 0 | H23: =G23/$G$26 -> 0
A24: Total Financial Capital | B24: =B17 -> 2.4664154e+08 | C24: =B24/$B$36 -> 0.0096789978 | F24: Other Liabilities | G24: 0 | H24: =G24/$G$26 -> 0
F25: Lifetime consumption needs | G25: ='2. Consumption Needs'!B22 -> 2.7200707e+10 | H25: =G25/$G$26 -> 1
A26: Human Capital | F26: TOTAL LIABILITIES | G26: =SUM(G22:G25) -> 2.7200707e+10 | H26: =G26/$G$26 -> 1
A27: Nhi's Human Capital | B27: ='2. Human Capital & Pension Valu'!B19 -> 8.9051492e+09 | C27: =B27/$B$36 -> 0.34946635
A28: Husband's Human Capital | B28: ='2. Human Capital & Pension Valu'!B33 -> 1.0511668e+10 | C28: =B28/$B$36 -> 0.41251126 | F28: ECONOMIC NET WORTH | G28: =B36-G26 -> -1.7185704e+09
A29: Total Human Capital | B29: ='2. Human Capital & Pension Valu'!B35 -> 1.9416817e+10 | C29: =B29/$B$36 -> 0.7619776
A31: Pension Value
A32: Nhi's Pension Value | B32: ='2. Human Capital & Pension Valu'!B48 -> 2.9992074e+09 | C32: =B32/$B$36 -> 0.11769843
A33: Husband's Pension Value | B33: ='2. Human Capital & Pension Valu'!B54 -> 2.8194703e+09 | C33: =B33/$B$36 -> 0.11064497
A34: Total Pension Value | B34: ='2. Human Capital & Pension Valu'!B56 -> 5.8186776e+09 | C34: =B34/$B$36 -> 0.2283434
A36: TOTAL ASSETS | B36: =SUM(B24,B29,B34) -> 2.5482136e+10 | C36: =B36/$B$36 -> 1
A38: CASHFLOW STATEMENT
B39: AMOUNT | C39: %
A40: Income
A41: Nhi's After-tax Income | B41: ='2. Human Capital & Pension Valu'!B17 -> 160975000 | C41: =B41/$B$44 -> 0.43456977
A42: Husband's After-tax Income | B42: ='2. Human Capital & Pension Valu'!B31 -> 203400000 | C42: =B42/$B$44 -> 0.54910074
A43: Interest from Saving Account | B43: ='3. Monte Carlo'!Q2 -> 6048829.3 | C43: =B43/$B$44 -> 0.016329482
A44: Total Income | B44: =SUM(B41:B43) -> 3.7042383e+08 | C44: =B44/$B$44 -> 1
A46: Expenses
A47: Living Expense | B47: ='2. Consumption Needs'!B16 -> 3.2846829e+08 | C47: =B47/$B$48 -> 1
A48: Total Living Expense | B48: =B47 -> 3.2846829e+08 | C48: =B48/$B$48 -> 1
A50: CASH SURPLUS (DEFICIT) | B50: =B44-B48 -> 41955535

Sheet 2. Human Capital & Pension Valu
A1: TIMELINE
A2: Year | B2: 2025 | C2: 2026 | D2: 2027 | E2: 2028 | F2: 2029 | G2: 2030 | H2: 2031 | I2: 2032 | J2: 2033 | K2: 2034 | L2: 2035 | M2: 2036 | N2: 2037 | O2: 2038 | P2: 2039 | Q2: 2040 | R2: 2041 | S2: 2042 | T2: 2043 | U2: 2044 | V2: 2045 | W2: 2046 | X2: 2047 | Y2: 2048 | Z2: 2049 | AA2: 2050 | AB2: 2051 | AC2: 2052 | AD2: 2053 | AE2: 2054 | AF2: 2055 | AG2: 2056 | AH2: 2057 | AI2: 2058 | AJ2: 2059 | AK2: 2060 | AL2: 2061 | AM2: 2062 | AN2: 2063 | AO2: 2064 | AP2: 2065 | AQ2: 2066 | AR2: 2067 | AS2: 2068 | AT2: 2069 | AU2: 2070 | AV2: 2071 | AW2: 2072 | AX2: 2073 | AY2: 2074 | AZ2: 2075 | BA2: 2076 | BB2: 2077 | BC2: 2078 | BD2: 2079 | BE2: 2080 | BF2: 2081 | BG2: 2082 | BH2: 2083 | BI2: 2084 | BJ2: 2085 | BK2: 2086 | BL2: 2087 | BM2: 2088
A3: Age | B3: 22 | C3: 23 | D3: 24 | E3: 25 | F3: 26 | G3: 27 | H3: 28 | I3: 29 | J3: 30 | K3: 31 | L3: 32 | M3: 33 | N3: 34 | O3: 35 | P3: 36 | Q3: 37 | R3: 38 | S3: 39 | T3: 40 | U3: 41 | V3: 42 | W3: 43 | X3: 44 | Y3: 45 | Z3: 46 | AA3: 47 | AB3: 48 | AC3: 49 | AD3: 50 | AE3: 51 | AF3: 52 | AG3: 53 | AH3: 54 | AI3: 55 | AJ3: 56 | AK3: 57 | AL3: 58 | AM3: 59 | AN3: 60 | AO3: 61 | AP3: 62 | AQ3: 63 | AR3: 64 | AS3: 65 | AT3: 66 | AU3: 67 | AV3: 68 | AW3: 69 | AX3: 70 | AY3: 71 | AZ3: 72 | BA3: 73 | BB3: 74 | BC3: 75 | BD3: 76 | BE3: 77 | BF3: 78 | BG3: 79 | BH3: 80 | BI3: 81 | BJ3: 82 | BK3: 83 | BL3: 84 | BM3: 85
A4: Event | H4: Buy car | J4: Nhi's 6 months of maternity leave Buy apartment | K4: Child is born | AC4: Child goes to university | AF4: Child is independent (when year ends) | AN4: Nhi retires (when year ends) | AP4: Husband retires (when year ends) | AY4: Trash car Go travel around the world | BM4: Nhi and Husband die (when year ends)
A5: Inflation Rate | B5: ='1. Drivers'!B17 -> 0.0295 | C5: ='1. Drivers'!B18 -> 0.0249 | D5: ='1. Drivers'!B19 -> 0.028 | E5: ='1. Drivers'!B20 -> 0.029 | F5: ='1. Drivers'!B21 -> 0.029 | G5: ='1. Drivers'!B22 -> 0.029 | H5: ='1. Drivers'!$B$23 -> 0.02881 | I5: ='1. Drivers'!$B$23 -> 0.02881 | J5: ='1. Drivers'!$B$23 -> 0.02881 | K5: ='1. Drivers'!$B$23 -> 0.02881 | L5: ='1. Drivers'!$B$23 -> 0.02881 | M5: ='1. Drivers'!$B$23 -> 0.02881 | N5: ='1. Drivers'!$B$23 -> 0.02881 | O5: ='1. Drivers'!$B$23 -> 0.02881 | ... BM5: ='1. Drivers'!$B$23 -> 0.02881
A7: Monthly Salary | B7: Yearly Bonus | C7: Maternity Leave | D7: Surviving Probability
A8: NHI'S HUMAN CAPITAL
A9: Position | B9: Junior Financial Analyst | D9: Senior Financial Analyst | G9: Lead Financial Analyst | O9: Financial Manager | Y9: Financial Director
A10: Monthly Salary | B10: =AVERAGE(10000000,15000000) -> 12500000 | C10: =B10*(1+C5) -> 12811250 | D10: =AVERAGE(15000000,25000000)*(1+C5)*(1+D5) -> 21071944 | E10: =D10*(1+E5) -> 21683030 | F10: =E10*(1+F5) -> 22311838 | G10: =AVERAGE(25000000,40000000)*(1+C5)*(1+D5)*(1+E5)*(1+F5)*(1+G5) -> 37308183 | H10: =G10*(1+H5) -> 38383031 | I10: =H10*(1+I5) -> 39488846 | J10: =I10*(1+J5) -> 40626520 | K10: =J10*(1+K5) -> 41796970 | L10: =K10*(1+L5) -> 43001141 | M10: =L10*(1+M5) -> 44240004 | N10: =M10*(1+N5) -> 45514558 | O10: =AVERAGE(35000000,50000000)*(1+C5)*(1+D5)*(1+E5)*(1+F5)*(1+G5)*(1+H5)^(O2-H2+1) -> 61233781 | P10: =O10*(1+P5) -> 62997926 | Q10: =P10*(1+Q5) -> 64812897 | R10: =Q10*(1+R5) -> 66680156 | S10: =R10*(1+S5) -> 68601211 | T10: =S10*(1+T5) -> 70577612 | U10: =T10*(1+U5) -> 72610953 | V10: =U10*(1+V5) -> 74702875 | W10: =V10*(1+W5) -> 76855065 | X10: =W10*(1+X5) -> 79069259 | Y10: =AVERAGE(50000000,80000000)*(1+C5)*(1+D5)*(1+E5)*(1+F5)*(1+G5)*(1+H5)^(Y2-H2+1) -> 1.2441343e+08 | Z10: =Y10*(1+Z5) -> 1.2799778e+08 | AA10: =Z10*(1+AA5) -> 1.316854e+08 | AB10: =AA10*(1+AB5) -> 1.3547926e+08 | AC10: =AB10*(1+AC5) -> 1.3938241e+08 | AD10: =AC10*(1+AD5) -> 1.4339802e+08 | AE10: =AD10*(1+AE5) -> 1.4752932e+08 | AF10: =AE10*(1+AF5) -> 1.5177964e+08 | AG10: =AF10*(1+AG5) -> 1.5615241e+08 | ... AN10: =AM10*(1+AN5) -> 1.9049998e+08
A11: Yearly Bonus | B11: =B10 -> 12500000 | C11: =C10 -> 12811250 | D11: =D10 -> 21071944 | E11: =E10 -> 21683030 | F11: =F10 -> 22311838 | G11: =G10 -> 37308183 | H11: =H10 -> 38383031 | I11: =I10 -> 39488846 | J11: 0 | K11: =K10 -> 41796970 | L11: =L10 -> 43001141 | M11: =M10 -> 44240004 | N11: =N10 -> 45514558 | O11: =O10 -> 61233781 | P11: =P10 -> 62997926 | Q11: =Q10 -> 64812897 | R11: =R10 -> 66680156 | ... AN11: =AN10 -> 1.9049998e+08
A12: Pretax Annual Salary | B12: =B10*12+B11 -> 162500000 | C12: =C10*12+C11 -> 1.6654625e+08 | D12: =D10*12+D11 -> 273935272 | E12: =E10*12+E11 -> 2.8187939e+08 | F12: =F10*12+F11 -> 2.900539e+08 | G12: =G10*12+G11 -> 4.8500637e+08 | H12: =H10*12+H11 -> 4.9897941e+08 | I12: =I10*12+I11 -> 5.13355e+08 | J12: =J10*6+J11 -> 2.4375912e+08 | K12: =K10*12+K11 -> 5.4336061e+08 | L12: =L10*12+L11 -> 5.5901483e+08 | M12: =M10*12+M11 -> 5.7512005e+08 | N12: =N10*12+N11 -> 5.9168926e+08 | O12: =O10*12+O11 -> 7.9603915e+08 | P12: =P10*12+P11 -> 8.1897304e+08 | Q12: =Q10*12+Q11 -> 8.4256766e+08 | R12: =R10*12+R11 -> 8.6684203e+08 | ... AN12: =AN10*12+AN11 -> 2.4764997e+09
A13: Deductions | B13: =11000000*12 -> 132000000 | C13: =11000000*12 -> 132000000 | D13: =11000000*12 -> 132000000 | E13: =11000000*12 -> 132000000 | F13: =11000000*12 -> 132000000 | G13: =11000000*12 -> 132000000 | H13: =11000000*12 -> 132000000 | I13: =11000000*12 -> 132000000 | ... AN13: =11000000*12 -> 132000000
A14: Assessable Income | B14: =B12-B13 -> 30500000 | C14: =C12-C13 -> 34546250 | D14: =D12-D13 -> 141935272 | E14: =E12-E13 -> 1.4987939e+08 | F14: =F12-F13 -> 1.580539e+08 | G14: =G12-G13 -> 3.5300637e+08 | H14: =H12-H13 -> 3.6697941e+08 | I14: =I12-I13 -> 3.81355e+08 | ... AN14: =AN12-AN13 -> 2.3444997e+09
A15: Income Tax | B15: =IF(B14<=60000000,B14*0.05,IF(B14<=120000000,60000000*0.05+(B14-60000000)*0.1,IF(B14<=216000000,60000000*0.05+60000000*0.1+(B14-120000000)*0.15,IF(B14<=384000000,60000000*0.05+60000000*0.1+96000000*0.15+(B14-216000000)*0.2,IF(B14<=624000000,60000000*0.05+60000000*0.1+96000000*0.15+168000000*0.2+(B14-384000000)*0.25,IF(B14<=960000000,60000000*0.05+60000000*0.1+96000000*0.15+168000000*0.2+240000000*0.25+(B14-624000000)*0.3,60000000*0.05+60000000*0.1+96000000*0.15+168000000*0.2+240000000*0.25+336000000*0.3+(B14-960000000)*0.35)))))) -> 1525000 | C15: =IF(C14<=60000000,C14*0.05,IF(C14<=120000000,60000000*0.05+(C14-60000000)*0.1,IF(C14<=216000000,60000000*0.05+60000000*0.1+(C14-120000000)*0.15,IF(C14<=384000000,60000000*0.05+60000000*0.1+96000000*0.15+(C14-216000000)*0.2,IF(C14<=624000000,60000000*0.05+60000000*0.1+96000000*0.15+168000000*0.2+(C14-384000000)*0.25,IF(C14<=960000000,60000000*0.05+60000000*0.1+96000000*0.15+168000000*0.2+240000000*0.25+(C14-624000000)*0.3,60000000*0.05+60000000*0.1+96000000*0.15+168000000*0.2+240000000*0.25+336000000*0.3+(C14-960000000)*0.35)))))) -> 1727312.5 | D15: =IF(D14<=60000000,D14*0.05,IF(D14<=120000000,60000000*0.05+(D14-60000000)*0.1,IF(D14<=216000000,60000000*0.05+60000000*0.1+(D14-120000000)*0.15,IF(D14<=384000000,60000000*0.05+60000000*0.1+96000000*0.15+(D14-216000000)*0.2,IF(D14<=624000000,60000000*0.05+60000000*0.1+96000000*0.15+168000000*0.2+(D14-384000000)*0.25,IF(D14<=960000000,60000000*0.05+60000000*0.1+96000000*0.15+168000000*0.2+240000000*0.25+(D14-624000000)*0.3,60000000*0.05+60000000*0.1+96000000*0.15+168000000*0.2+240000000*0.25+336000000*0.3+(D14-960000000)*0.35)))))) -> 12290291 | E15: =IF(E14<=60000000,E14*0.05,IF(E14<=120000000,60000000*0.05+(E14-60000000)*0.1,IF(E14<=216000000,60000000*0.05+60000000*0.1+(E14-120000000)*0.15,IF(E14<=384000000,60000000*0.05+60000000*0.1+96000000*0.15+(E14-216000000)*0.2,IF(E14<=624000000,60000000*0.05+60000000*0.1+96000000*0.15+168000000*0.2+(E14-384000000)*0.25,IF(E14<=960000000,60000000*0.05+60000000*0.1+96000000*0.15+168000000*0.2+240000000*0.25+(E14-624000000)*0.3,60000000*0.05+60000000*0.1+96000000*0.15+168000000*0.2+240000000*0.25+336000000*0.3+(E14-960000000)*0.35)))))) -> 13481909 | F15: =IF(F14<=60000000,F14*0.05,IF(F14<=120000000,60000000*0.05+(F14-60000000)*0.1,IF(F14<=216000000,60000000*0.05+60000000*0.1+(F14-120000000)*0.15,IF(F14<=384000000,60000000*0.05+60000000*0.1+96000000*0.15+(F14-216000000)*0.2,IF(F14<=624000000,60000000*0.05+60000000*0.1+96000000*0.15+168000000*0.2+(F14-384000000)*0.25,IF(F14<=960000000,60000000*0.05+60000000*0.1+96000000*0.15+168000000*0.2+240000000*0.25+(F14-624000000)*0.3,60000000*0.05+60000000*0.1+96000000*0.15+168000000*0.2+240000000*0.25+336000000*0.3+(F14-960000000)*0.35)))))) -> 14708085 | G15: =IF(G14<=60000000,G14*0.05,IF(G14<=120000000,60000000*0.05+(G14-60000000)*0.1,IF(G14<=216000000,60000000*0.05+60000000*0.1+(G14-120000000)*0.15,IF(G14<=384000000,60000000*0.05+60000000*0.1+96000000*0.15+(G14-216000000)*0.2,IF(G14<=624000000,60000000*0.05+60000000*0.1+96000000*0.15+168000000*0.2+(G14-384000000)*0.25,IF(G14<=960000000,60000000*0.05+60000000*0.1+96000000*0.15+168000000*0.2+240000000*0.25+(G14-624000000)*0.3,60000000*0.05+60000000*0.1+96000000*0.15+168000000*0.2+240000000*0.25+336000000*0.3+(G14-960000000)*0.35)))))) -> 50801275 | H15: =IF(H14<=60000000,H14*0.05,IF(H14<=120000000,60000000*0.05+(H14-60000000)*0.1,IF(H14<=216000000,60000000*0.05+60000000*0.1+(H14-120000000)*0.15,IF(H14<=384000000,60000000*0.05+60000000*0.1+96000000*0.15+(H14-216000000)*0.2,IF(H14<=624000000,60000000*0.05+60000000*0.1+96000000*0.15+168000000*0.2+(H14-384000000)*0.25,IF(H14<=960000000,60000000*0.05+60000000*0.1+96000000*0.15+168000000*0.2+240000000*0.25+(H14-624000000)*0.3,60000000*0.05+60000000*0.1+96000000*0.15+168000000*0.2+240000000*0.25+336000000*0.3+(H14-960000000)*0.35)))))) -> 53595881 | I15: =IF(I14<=60000000,I14*0.05,IF(I14<=120000000,60000000*0.05+(I14-60000000)*0.1,IF(I14<=216000000,60000000*0.05+60000000*0.1+(I14-120000000)*0.15,IF(I14<=384000000,60000000*0.05+60000000*0.1+96000000*0.15+(I14-216000000)*0.2,IF(I14<=624000000,60000000*0.05+60000000*0.1+96000000*0.15+168000000*0.2+(I14-384000000)*0.25,IF(I14<=960000000,60000000*0.05+60000000*0.1+96000000*0.15+168000000*0.2+240000000*0.25+(I14-624000000)*0.3,60000000*0.05+60000000*0.1+96000000*0.15+168000000*0.2+240000000*0.25+336000000*0.3+(I14-960000000)*0.35)))))) -> 56471001 | ... AN15: =IF(AN14<=60000000,AN14*0.05,IF(AN14<=120000000,60000000*0.05+(AN14-60000000)*0.1,IF(AN14<=216000000,60000000*0.05+60000000*0.1+(AN14-120000000)*0.15,IF(AN14<=384000000,60000000*0.05+60000000*0.1+96000000*0.15+(AN14-216000000)*0.2,IF(AN14<=624000000,60000000*0.05+60000000*0.1+96000000*0.15+168000000*0.2+(AN14-384000000)*0.25,IF(AN14<=960000000,60000000*0.05+60000000*0.1+96000000*0.15+168000000*0.2+240000000*0.25+(AN14-624000000)*0.3,60000000*0.05+60000000*0.1+96000000*0.15+168000000*0.2+240000000*0.25+336000000*0.3+(AN14-960000000)*0.35)))))) -> 7.0237489e+08
A16: After-tax Income | B16: =B12-B15 -> 160975000 | C16: =C12-C15 -> 1.6481894e+08 | D16: =D12-D15 -> 2.6164498e+08 | E16: =E12-E15 -> 2.6839749e+08 | F16: =F12-F15 -> 2.7534581e+08 | G16: =G12-G15 -> 4.342051e+08 | H16: =H12-H15 -> 4.4538353e+08 | I16: =I12-I15 -> 4.56884e+08 | ... AN16: =AN12-AN15 -> 1.7741248e+09
A17: Present Value of Future Income | B17: =B16/(1+'1. Drivers'!$K$3+'1. Drivers'!$K$4)^(B2-2025) -> 160975000 | C17: =C16/(1+'1. Drivers'!$K$3+'1. Drivers'!$K$4)^(C2-2025) -> 1.5479736e+08 | D17: =D16/(1+'1. Drivers'!$K$3+'1. Drivers'!$K$4)^(D2-2025) -> 2.307944e+08 | E17: =E16/(1+'1. Drivers'!$K$3+'1. Drivers'!$K$4)^(E2-2025) -> 2.2235543e+08 | F17: =F16/(1+'1. Drivers'!$K$3+'1. Drivers'!$K$4)^(F2-2025) -> 2.1424179e+08 | G17: =G16/(1+'1. Drivers'!$K$3+'1. Drivers'!$K$4)^(G2-2025) -> 3.1730511e+08 | H17: =H16/(1+'1. Drivers'!$K$3+'1. Drivers'!$K$4)^(H2-2025) -> 3.0568402e+08 | I17: =I16/(1+'1. Drivers'!$K$3+'1. Drivers'!$K$4)^(I2-2025) -> 2.9451062e+08 | ... AN17: =AN16/(1+'1. Drivers'!$K$3+'1. Drivers'!$K$4)^(AN2-2025) -> 1.6357936e+08
A18: Surviving Probability | B18: =1-0.000416227 -> 0.99958377 | C18: =1-0.000416227 -> 0.99958377 | D18: =1-0.000416227 -> 0.99958377 | E18: =1- 0.000472252 -> 0.99952775 | F18: =1- 0.000472252 -> 0.99952775 | G18: =1- 0.000472252 -> 0.99952775 | H18: =1- 0.000472252 -> 0.99952775 | I18: =1- 0.000472252 -> 0.99952775 | J18: =1-0.000615292 -> 0.99938471 | K18: =1-0.000615292 -> 0.99938471 | L18: =1-0.000615292 -> 0.99938471 | M18: =1-0.000615292 -> 0.99938471 | N18: =1-0.000615292 -> 0.99938471 | O18: =1-0.000912829 -> 0.99908717 | P18: =1-0.000912829 -> 0.99908717 | Q18: =1-0.000912829 -> 0.99908717 | R18: =1-0.000912829 -> 0.99908717 | S18: =1-0.000912829 -> 0.99908717 | T18: =1-0.001452051 -> 0.99854795 | U18: =1-0.001452051 -> 0.99854795 | V18: =1-0.001452051 -> 0.99854795 | W18: =1-0.001452051 -> 0.99854795 | X18: =1-0.001452051 -> 0.99854795 | Y18: =1-0.002280473 -> 0.99771953 | Z18: =1-0.002280473 -> 0.99771953 | AA18: =1-0.002280473 -> 0.99771953 | AB18: =1-0.002280473 -> 0.99771953 | AC18: =1-0.002280473 -> 0.99771953 | AD18: =1-0.003585945 -> 0.99641406 | AE18: =1-0.003585945 -> 0.99641406 | AF18: =1-0.003585945 -> 0.99641406 | AG18: =1-0.003585945 -> 0.99641406 | AH18: =1-0.003585945 -> 0.99641406 | AI18: =1-0.005487598 -> 0.9945124 | AJ18: =1-0.005487598 -> 0.9945124 | AK18: =1-0.005487598 -> 0.9945124 | AL18: =1-0.005487598 -> 0.9945124 | AM18: =1-0.005487598 -> 0.9945124 | AN18: =1-0.008891343 -> 0.99110866
A19: HUMAN CAPITAL | B19: =SUMPRODUCT(C17:AN17,C18:AN18) -> 8.9051492e+09
A21: Monthly Salary
A22: HUSBAND'S HUMAN CAPITAL
A23: Position | B23: Junior Developer | E23: Senior Developer | J23: Lead Developer | Q23: Developer Manager | AA23: Developer Director
A24: Monthly Salary | B24: =AVERAGE(8000000,24000000) -> 16000000 | C24: =B24*(1+C5) -> 16398400 | D24: =C24*(1+D5) -> 16857555 | E24: =AVERAGE(20000000,52000000)*(1+C5)*(1+D5)*(1+E5) -> 39029455 | F24: =E24*(1+F5) -> 40161309 | G24: =F24*(1+G5) -> 41325987 | H24: =G24*(1+H5) -> 42516588 | I24: =H24*(1+I5) -> 43741491 | J24: =AVERAGE(36000000,48000000)*(1+C5)*(1+D5)*(1+E5)*(1+F5)*(1+G5)*(1+H5)^(J2-H2+1) -> 52501964 | K24: =J24*(1+K5) -> 54014546 | L24: =K24*(1+L5) -> 55570705 | M24: =L24*(1+M5) -> 57171697 | N24: =M24*(1+N5) -> 58818814 | O24: =N24*(1+O5) -> 60513384 | P24: =O24*(1+P5) -> 62256774 | Q24: =AVERAGE(48000000,72000000)*(1+C5)*(1+D5)*(1+E5)*(1+F5)*(1+G5)*(1+H5)^(Q2-H2+1) -> 91500560 | R24: =Q24*(1+R5) -> 94136691 | S24: =R24*(1+S5) -> 96848769 | T24: =S24*(1+T5) -> 99638982 | U24: =T24*(1+U5) -> 1.0250958e+08 | V24: =U24*(1+V5) -> 1.0546288e+08 | W24: =V24*(1+W5) -> 1.0850127e+08 | X24: =W24*(1+X5) -> 1.1162719e+08 | Y24: =X24*(1+Y5) -> 1.1484317e+08 | ... AP24: =AO24*(1+AP5) -> 1.8612434e+08
A25: Yearly Bonus | B25: =B24 -> 16000000 | C25: =C24 -> 16398400 | D25: =D24 -> 16857555 | E25: =E24 -> 39029455 | F25: =F24 -> 40161309 | G25: =G24 -> 41325987 | H25: =H24 -> 42516588 | I25: =I24 -> 43741491 | ... AP25: =AP24 -> 1.8612434e+08
A26: Pretax Annual Salary | B26: =B24*12+B25 -> 208000000 | C26: =C24*12+C25 -> 2.131792e+08 | D26: =D24*12+D25 -> 2.1914822e+08 | E26: =E24*12+E25 -> 5.0738291e+08 | F26: =F24*12+F25 -> 5.2209702e+08 | G26: =G24*12+G25 -> 5.3723783e+08 | H26: =H24*12+H25 -> 5.5271565e+08 | I26: =I24*12+I25 -> 5.6863939e+08 | ... AP26: =AP24*12+AP25 -> 2.4196164e+09
A27: Deductions | B27: =11000000*12 -> 132000000 | C27: =11000000*12 -> 132000000 | D27: =11000000*12 -> 132000000 | E27: =11000000*12 -> 132000000 | F27: =11000000*12 -> 132000000 | G27: =11000000*12 -> 132000000 | H27: =11000000*12 -> 132000000 | I27: =11000000*12 -> 132000000 | J27: =11000000*12 -> 132000000 | K27: =(11000000+4400000)*12 -> 184800000 | L27: =(11000000+4400000)*12 -> 184800000 | M27: =(11000000+4400000)*12 -> 184800000 | N27: =(11000000+4400000)*12 -> 184800000 | O27: =(11000000+4400000)*12 -> 184800000 | P27: =(11000000+4400000)*12 -> 184800000 | Q27: =(11000000+4400000)*12 -> 184800000 | R27: =(11000000+4400000)*12 -> 184800000 | ... AB27: =(11000000+4400000)*12 -> 184800000 | AC27: =11000000*12 -> 132000000 | AD27: =11000000*12 -> 132000000 | AE27: =11000000*12 -> 132000000 | AF27: =11000000*12 -> 132000000 | AG27: =11000000*12 -> 132000000 | AH27: =11000000*12 -> 132000000 | AI27: =11000000*12 -> 132000000 | AJ27: =11000000*12 -> 132000000 | ... AP27: =11000000*12 -> 132000000
A28: Assessable Income | B28: =B26-B27 -> 76000000 | C28: =C26-C27 -> 81179200 | D28: =D26-D27 -> 87148218 | E28: =E26-E27 -> 3.7538291e+08 | F28: =F26-F27 -> 3.9009702e+08 | G28: =G26-G27 -> 4.0523783e+08 | H28: =H26-H27 -> 4.2071565e+08 | I28: =I26-I27 -> 4.3663939e+08 | ... AP28: =AP26-AP27 -> 2.2876164e+09
A29: Income Tax | B29: =IF(B28<=60000000,B28*0.05,IF(B28<=120000000,60000000*0.05+(B28-60000000)*0.1,IF(B28<=216000000,60000000*0.05+60000000*0.1+(B28-120000000)*0.15,IF(B28<=384000000,60000000*0.05+60000000*0.1+96000000*0.15+(B28-216000000)*0.2,IF(B28<=624000000,60000000*0.05+60000000*0.1+96000000*0.15+168000000*0.2+(B28-384000000)*0.25,IF(B28<=960000000,60000000*0.05+60000000*0.1+96000000*0.15+168000000*0.2+240000000*0.25+(B28-624000000)*0.3,60000000*0.05+60000000*0.1+96000000*0.15+168000000*0.2+240000000*0.25+336000000*0.3+(B28-960000000)*0.35)))))) -> 4600000 | C29: =IF(C28<=60000000,C28*0.05,IF(C28<=120000000,60000000*0.05+(C28-60000000)*0.1,IF(C28<=216000000,60000000*0.05+60000000*0.1+(C28-120000000)*0.15,IF(C28<=384000000,60000000*0.05+60000000*0.1+96000000*0.15+(C28-216000000)*0.2,IF(C28<=624000000,60000000*0.05+60000000*0.1+96000000*0.15+168000000*0.2+(C28-384000000)*0.25,IF(C28<=960000000,60000000*0.05+60000000*0.1+96000000*0.15+168000000*0.2+240000000*0.25+(C28-624000000)*0.3,60000000*0.05+60000000*0.1+96000000*0.15+168000000*0.2+240000000*0.25+336000000*0.3+(C28-960000000)*0.35)))))) -> 5117920 | D29: =IF(D28<=60000000,D28*0.05,IF(D28<=120000000,60000000*0.05+(D28-60000000)*0.1,IF(D28<=216000000,60000000*0.05+60000000*0.1+(D28-120000000)*0.15,IF(D28<=384000000,60000000*0.05+60000000*0.1+96000000*0.15+(D28-216000000)*0.2,IF(D28<=624000000,60000000*0.05+60000000*0.1+96000000*0.15+168000000*0.2+(D28-384000000)*0.25,IF(D28<=960000000,60000000*0.05+60000000*0.1+96000000*0.15+168000000*0.2+240000000*0.25+(D28-624000000)*0.3,60000000*0.05+60000000*0.1+96000000*0.15+168000000*0.2+240000000*0.25+336000000*0.3+(D28-960000000)*0.35)))))) -> 5714821.8 | E29: =IF(E28<=60000000,E28*0.05,IF(E28<=120000000,60000000*0.05+(E28-60000000)*0.1,IF(E28<=216000000,60000000*0.05+60000000*0.1+(E28-120000000)*0.15,IF(E28<=384000000,60000000*0.05+60000000*0.1+96000000*0.15+(E28-216000000)*0.2,IF(E28<=624000000,60000000*0.05+60000000*0.1+96000000*0.15+168000000*0.2+(E28-384000000)*0.25,IF(E28<=960000000,60000000*0.05+60000000*0.1+96000000*0.15+168000000*0.2+240000000*0.25+(E28-624000000)*0.3,60000000*0.05+60000000*0.1+96000000*0.15+168000000*0.2+240000000*0.25+336000000*0.3+(E28-960000000)*0.35)))))) -> 55276582 | F29: =IF(F28<=60000000,F28*0.05,IF(F28<=120000000,60000000*0.05+(F28-60000000)*0.1,IF(F28<=216000000,60000000*0.05+60000000*0.1+(F28-120000000)*0.15,IF(F28<=384000000,60000000*0.05+60000000*0.1+96000000*0.15+(F28-216000000)*0.2,IF(F28<=624000000,60000000*0.05+60000000*0.1+96000000*0.15+168000000*0.2+(F28-384000000)*0.25,IF(F28<=960000000,60000000*0.05+60000000*0.1+96000000*0.15+168000000*0.2+240000000*0.25+(F28-624000000)*0.3,60000000*0.05+60000000*0.1+96000000*0.15+168000000*0.2+240000000*0.25+336000000*0.3+(F28-960000000)*0.35)))))) -> 58524254 | G29: =IF(G28<=60000000,G28*0.05,IF(G28<=120000000,60000000*0.05+(G28-60000000)*0.1,IF(G28<=216000000,60000000*0.05+60000000*0.1+(G28-120000000)*0.15,IF(G28<=384000000,60000000*0.05+60000000*0.1+96000000*0.15+(G28-216000000)*0.2,IF(G28<=624000000,60000000*0.05+60000000*0.1+96000000*0.15+168000000*0.2+(G28-384000000)*0.25,IF(G28<=960000000,60000000*0.05+60000000*0.1+96000000*0.15+168000000*0.2+240000000*0.25+(G28-624000000)*0.3,60000000*0.05+60000000*0.1+96000000*0.15+168000000*0.2+240000000*0.25+336000000*0.3+(G28-960000000)*0.35)))))) -> 62309457 | H29: =IF(H28<=60000000,H28*0.05,IF(H28<=120000000,60000000*0.05+(H28-60000000)*0.1,IF(H28<=216000000,60000000*0.05+60000000*0.1+(H28-120000000)*0.15,IF(H28<=384000000,60000000*0.05+60000000*0.1+96000000*0.15+(H28-216000000)*0.2,IF(H28<=624000000,60000000*0.05+60000000*0.1+96000000*0.15+168000000*0.2+(H28-384000000)*0.25,IF(H28<=960000000,60000000*0.05+60000000*0.1+96000000*0.15+168000000*0.2+240000000*0.25+(H28-624000000)*0.3,60000000*0.05+60000000*0.1+96000000*0.15+168000000*0.2+240000000*0.25+336000000*0.3+(H28-960000000)*0.35)))))) -> 66178913 | I29: =IF(I28<=60000000,I28*0.05,IF(I28<=120000000,60000000*0.05+(I28-60000000)*0.1,IF(I28<=216000000,60000000*0.05+60000000*0.1+(I28-120000000)*0.15,IF(I28<=384000000,60000000*0.05+60000000*0.1+96000000*0.15+(I28-216000000)*0.2,IF(I28<=624000000,60000000*0.05+60000000*0.1+96000000*0.15+168000000*0.2+(I28-384000000)*0.25,IF(I28<=960000000,60000000*0.05+60000000*0.1+96000000*0.15+168000000*0.2+240000000*0.25+(I28-624000000)*0.3,60000000*0.05+60000000*0.1+96000000*0.15+168000000*0.2+240000000*0.25+336000000*0.3+(I28-960000000)*0.35)))))) -> 70159847 | ... AP29: =IF(AP28<=60000000,AP28*0.05,IF(AP28<=120000000,60000000*0.05+(AP28-60000000)*0.1,IF(AP28<=216000000,60000000*0.05+60000000*0.1+(AP28-120000000)*0.15,IF(AP28<=384000000,60000000*0.05+60000000*0.1+96000000*0.15+(AP28-216000000)*0.2,IF(AP28<=624000000,60000000*0.05+60000000*0.1+96000000*0.15+168000000*0.2+(AP28-384000000)*0.25,IF(AP28<=960000000,60000000*0.05+60000000*0.1+96000000*0.15+168000000*0.2+240000000*0.25+(AP28-624000000)*0.3,60000000*0.05+60000000*0.1+96000000*0.15+168000000*0.2+240000000*0.25+336000000*0.3+(AP28-960000000)*0.35)))))) -> 6.8246576e+08
A30: After-tax Income | B30: =B26-B29 -> 203400000 | C30: =C26-C29 -> 2.0806128e+08 | D30: =D26-D29 -> 2.134334e+08 | E30: =E26-E29 -> 4.5210633e+08 | F30: =F26-F29 -> 4.6357276e+08 | G30: =G26-G29 -> 4.7492837e+08 | H30: =H26-H29 -> 4.8653674e+08 | I30: =I26-I29 -> 4.9847954e+08 | ... AP30: =AP26-AP29 -> 1.7371507e+09
A31: Present Value of Future Income | B31: =B30/(1+'1. Drivers'!$K$3+'1. Drivers'!$K$4)^(B2-2025) -> 203400000 | C31: =C30/(1+'1. Drivers'!$K$3+'1. Drivers'!$K$4)^(C2-2025) -> 1.9541041e+08 | D31: =D30/(1+'1. Drivers'!$K$3+'1. Drivers'!$K$4)^(D2-2025) -> 1.8826745e+08 | E31: =E30/(1+'1. Drivers'!$K$3+'1. Drivers'!$K$4)^(E2-2025) -> 3.7455006e+08 | F31: =F30/(1+'1. Drivers'!$K$3+'1. Drivers'!$K$4)^(F2-2025) -> 3.6069791e+08 | G31: =G30/(1+'1. Drivers'!$K$3+'1. Drivers'!$K$4)^(G2-2025) -> 3.4706456e+08 | H31: =H30/(1+'1. Drivers'!$K$3+'1. Drivers'!$K$4)^(H2-2025) -> 3.3392906e+08 | I31: =I30/(1+'1. Drivers'!$K$3+'1. Drivers'!$K$4)^(I2-2025) -> 3.213234e+08 | ... AP31: =AP30/(1+'1. Drivers'!$K$3+'1. Drivers'!$K$4)^(AP2-2025) -> 1.4128456e+08
A32: Surviving Probability | B32: =1-0.00148833 -> 0.99851167 | C32: =1-0.00148833 -> 0.99851167 | D32: =1-0.00148833 -> 0.99851167 | E32: =1-0.001467648 -> 0.99853235 | F32: =1-0.001467648 -> 0.99853235 | G32: =1-0.001467648 -> 0.99853235 | H32: =1-0.001467648 -> 0.99853235 | I32: =1-0.001467648 -> 0.99853235 | J32: =1-0.001691763 -> 0.99830824 | K32: =1-0.001691763 -> 0.99830824 | L32: =1-0.001691763 -> 0.99830824 | M32: =1-0.001691763 -> 0.99830824 | N32: =1-0.001691763 -> 0.99830824 | O32: =1-0.002338274 -> 0.99766173 | P32: =1-0.002338274 -> 0.99766173 | Q32: =1-0.002338274 -> 0.99766173 | R32: =1-0.002338274 -> 0.99766173 | S32: =1-0.002338274 -> 0.99766173 | T32: =1-0.003645446 -> 0.99635455 | U32: =1-0.003645446 -> 0.99635455 | V32: =1-0.003645446 -> 0.99635455 | W32: =1-0.003645446 -> 0.99635455 | X32: =1-0.003645446 -> 0.99635455 | Y32: =1- 0.005916506 -> 0.99408349 | Z32: =1- 0.005916506 -> 0.99408349 | AA32: =1- 0.005916506 -> 0.99408349 | AB32: =1- 0.005916506 -> 0.99408349 | AC32: =1- 0.005916506 -> 0.99408349 | AD32: =1-0.00947506 -> 0.99052494 | AE32: =1-0.00947506 -> 0.99052494 | AF32: =1-0.00947506 -> 0.99052494 | AG32: =1-0.00947506 -> 0.99052494 | AH32: =1-0.00947506 -> 0.99052494 | AI32: =1-0.014665436 -> 0.98533456 | AJ32: =1-0.014665436 -> 0.98533456 | AK32: =1-0.014665436 -> 0.98533456 | AL32: =1-0.014665436 -> 0.98533456 | AM32: =1-0.014665436 -> 0.98533456 | AN32: =1-0.022502985 -> 0.97749701 | AO32: =1-0.022502985 -> 0.97749701 | AP32: =1-0.022502985 -> 0.97749701
A33: HUMAN CAPITAL | B33: =SUMPRODUCT(C31:AP31,C32:AP32) -> 1.0511668e+10
A35: TOTAL HUMAN CAPITAL | B35: =SUM(B19,B33) -> 1.9416817e+10
A38: GENERAL INFORMATION REGARDING PENSION VALUE
B39: Nhi | C39: Husband | D39: Social Security
A40: Year starting Social Security | B40: 45658 | C40: 45658
A41: Average Income | B41: =AVERAGE(B16:AN16) -> 9.171176e+08 | C41: =AVERAGE(B30:AP30) -> 1.0076613e+09
A42: Pension | B42: =75%*B41 -> 6.878382e+08 | C42: =75%*C41 -> 7.5574597e+08
A44: NHI PENSION VALUE
A45: Pension | AO45: =$B$42 -> 6.878382e+08 | AP45: =$B$42 -> 6.878382e+08 | AQ45: =$B$42 -> 6.878382e+08 | AR45: =$B$42 -> 6.878382e+08 | AS45: =$B$42 -> 6.878382e+08 | AT45: =$B$42 -> 6.878382e+08 | AU45: =$B$42 -> 6.878382e+08 | AV45: =$B$42 -> 6.878382e+08 | ... BM45: =$B$42 -> 6.878382e+08
A46: Pension Present Value | AO46: =AO45/(1+'1. Drivers'!$K$3)^(AO2-2025) -> 1.8158e+08 | AP46: =AP45/(1+'1. Drivers'!$K$3)^(AP2-2025) -> 1.754837e+08 | AQ46: =AQ45/(1+'1. Drivers'!$K$3)^(AQ2-2025) -> 1.6959207e+08 | AR46: =AR45/(1+'1. Drivers'!$K$3)^(AR2-2025) -> 1.6389824e+08 | AS46: =AS45/(1+'1. Drivers'!$K$3)^(AS2-2025) -> 1.5839558e+08 | AT46: =AT45/(1+'1. Drivers'!$K$3)^(AT2-2025) -> 1.5307766e+08 | AU46: =AU45/(1+'1. Drivers'!$K$3)^(AU2-2025) -> 1.4793829e+08 | AV46: =AV45/(1+'1. Drivers'!$K$3)^(AV2-2025) -> 1.4297146e+08 | ... BM46: =BM45/(1+'1. Drivers'!$K$3)^(BM2-2025) -> 80005216
A47: Surviving Probability | B47: =1-0.000416227 -> 0.99958377 | C47: =1-0.000416227 -> 0.99958377 | D47: =1-0.000416227 -> 0.99958377 | E47: =1- 0.000472252 -> 0.99952775 | F47: =1- 0.000472252 -> 0.99952775 | G47: =1- 0.000472252 -> 0.99952775 | H47: =1- 0.000472252 -> 0.99952775 | I47: =1- 0.000472252 -> 0.99952775 | J47: =1-0.000615292 -> 0.99938471 | K47: =1-0.000615292 -> 0.99938471 | L47: =1-0.000615292 -> 0.99938471 | M47: =1-0.000615292 -> 0.99938471 | N47: =1-0.000615292 -> 0.99938471 | O47: =1-0.000912829 -> 0.99908717 | P47: =1-0.000912829 -> 0.99908717 | Q47: =1-0.000912829 -> 0.99908717 | R47: =1-0.000912829 -> 0.99908717 | S47: =1-0.000912829 -> 0.99908717 | T47: =1-0.001452051 -> 0.99854795 | U47: =1-0.001452051 -> 0.99854795 | V47: =1-0.001452051 -> 0.99854795 | W47: =1-0.001452051 -> 0.99854795 | X47: =1-0.001452051 -> 0.99854795 | Y47: =1-0.002280473 -> 0.99771953 | Z47: =1-0.002280473 -> 0.99771953 | AA47: =1-0.002280473 -> 0.99771953 | AB47: =1-0.002280473 -> 0.99771953 | AC47: =1-0.002280473 -> 0.99771953 | AD47: =1-0.003585945 -> 0.99641406 | AE47: =1-0.003585945 -> 0.99641406 | AF47: =1-0.003585945 -> 0.99641406 | AG47: =1-0.003585945 -> 0.99641406 | AH47: =1-0.003585945 -> 0.99641406 | AI47: =1-0.005487598 -> 0.9945124 | AJ47: =1-0.005487598 -> 0.9945124 | AK47: =1-0.005487598 -> 0.9945124 | AL47: =1-0.005487598 -> 0.9945124 | AM47: =1-0.005487598 -> 0.9945124 | AN47: =1-0.008891343 -> 0.99110866 | AO47: =1-0.008891343 -> 0.99110866 | AP47: =1-0.008891343 -> 0.99110866 | AQ47: =1-0.008891343 -> 0.99110866 | AR47: =1-0.008891343 -> 0.99110866 | AS47: =1-0.014746672 -> 0.98525333 | AT47: =1-0.014746672 -> 0.98525333 | AU47: =1-0.014746672 -> 0.98525333 | AV47: =1-0.014746672 -> 0.98525333 | AW47: =1-0.014746672 -> 0.98525333 | AX47: =1-0.025760369 -> 0.97423963 | AY47: =1-0.025760369 -> 0.97423963 | AZ47: =1-0.025760369 -> 0.97423963 | BA47: =1-0.025760369 -> 0.97423963 | BB47: =1-0.025760369 -> 0.97423963 | BC47: =1-0.044856567 -> 0.95514343 | BD47: =1-0.044856567 -> 0.95514343 | BE47: =1-0.044856567 -> 0.95514343 | BF47: =1-0.044856567 -> 0.95514343 | BG47: =1-0.044856567 -> 0.95514343 | BH47: =1-0.080907942 -> 0.91909206 | BI47: =1-0.080907942 -> 0.91909206 | BJ47: =1-0.080907942 -> 0.91909206 | BK47: =1-0.080907942 -> 0.91909206 | BL47: =1-0.080907942 -> 0.91909206 | BM47: =1-0.169725066 -> 0.83027493
A48: PENSION VALUE | B48: =SUMPRODUCT(AO46:BM46,AO47:BM47) -> 2.9992074e+09
A50: HUSBAND PENSION VALUE
A51: Pension | AQ51: =$C$42 -> 7.5574597e+08 | AR51: =$C$42 -> 7.5574597e+08 | AS51: =$C$42 -> 7.5574597e+08 | AT51: =$C$42 -> 7.5574597e+08 | AU51: =$C$42 -> 7.5574597e+08 | AV51: =$C$42 -> 7.5574597e+08 | AW51: =$C$42 -> 7.5574597e+08 | AX51: =$C$42 -> 7.5574597e+08 | ... BM51: =$C$42 -> 7.5574597e+08
A52: Pension Present Value | AQ52: =AQ51/(1+'1. Drivers'!$K$3)^(AQ2-2025) -> 1.8633528e+08 | AR52: =AR51/(1+'1. Drivers'!$K$3)^(AR2-2025) -> 1.8007932e+08 | AS52: =AS51/(1+'1. Drivers'!$K$3)^(AS2-2025) -> 1.740334e+08 | AT52: =AT51/(1+'1. Drivers'!$K$3)^(AT2-2025) -> 1.6819046e+08 | AU52: =AU51/(1+'1. Drivers'!$K$3)^(AU2-2025) -> 1.625437e+08 | AV52: =AV51/(1+'1. Drivers'!$K$3)^(AV2-2025) -> 1.5708651e+08 | AW52: =AW51/(1+'1. Drivers'!$K$3)^(AW2-2025) -> 1.5181254e+08 | AX52: =AX51/(1+'1. Drivers'!$K$3)^(AX2-2025) -> 1.4671564e+08 | ... BM52: =BM51/(1+'1. Drivers'!$K$3)^(BM2-2025) -> 87903840
A53: Surviving Probability | B53: =1-0.00148833 -> 0.99851167 | C53: =1-0.00148833 -> 0.99851167 | D53: =1-0.00148833 -> 0.99851167 | E53: =1-0.001467648 -> 0.99853235 | F53: =1-0.001467648 -> 0.99853235 | G53: =1-0.001467648 -> 0.99853235 | H53: =1-0.001467648 -> 0.99853235 | I53: =1-0.001467648 -> 0.99853235 | J53: =1-0.001691763 -> 0.99830824 | K53: =1-0.001691763 -> 0.99830824 | L53: =1-0.001691763 -> 0.99830824 | M53: =1-0.001691763 -> 0.99830824 | N53: =1-0.001691763 -> 0.99830824 | O53: =1-0.002338274 -> 0.99766173 | P53: =1-0.002338274 -> 0.99766173 | Q53: =1-0.002338274 -> 0.99766173 | R53: =1-0.002338274 -> 0.99766173 | S53: =1-0.002338274 -> 0.99766173 | T53: =1-0.003645446 -> 0.99635455 | U53: =1-0.003645446 -> 0.99635455 | V53: =1-0.003645446 -> 0.99635455 | W53: =1-0.003645446 -> 0.99635455 | X53: =1-0.003645446 -> 0.99635455 | Y53: =1- 0.005916506 -> 0.99408349 | Z53: =1- 0.005916506 -> 0.99408349 | AA53: =1- 0.005916506 -> 0.99408349 | AB53: =1- 0.005916506 -> 0.99408349 | AC53: =1- 0.005916506 -> 0.99408349 | AD53: =1-0.00947506 -> 0.99052494 | AE53: =1-0.00947506 -> 0.99052494 | AF53: =1-0.00947506 -> 0.99052494 | AG53: =1-0.00947506 -> 0.99052494 | AH53: =1-0.00947506 -> 0.99052494 | AI53: =1-0.014665436 -> 0.98533456 | AJ53: =1-0.014665436 -> 0.98533456 | AK53: =1-0.014665436 -> 0.98533456 | AL53: =1-0.014665436 -> 0.98533456 | AM53: =1-0.014665436 -> 0.98533456 | AN53: =1-0.022502985 -> 0.97749701 | AO53: =1-0.022502985 -> 0.97749701 | AP53: =1-0.022502985 -> 0.97749701 | AQ53: =1-0.022502985 -> 0.97749701 | AR53: =1-0.022502985 -> 0.97749701 | AS53: =1-0.034346082 -> 0.96565392 | AT53: =1-0.034346082 -> 0.96565392 | AU53: =1-0.034346082 -> 0.96565392 | AV53: =1-0.034346082 -> 0.96565392 | AW53: =1-0.034346082 -> 0.96565392 | AX53: =1-0.053464327 -> 0.94653567 | AY53: =1-0.053464327 -> 0.94653567 | AZ53: =1-0.053464327 -> 0.94653567 | BA53: =1-0.053464327 -> 0.94653567 | BB53: =1-0.053464327 -> 0.94653567 | BC53: =1-0.081470516 -> 0.91852948 | BD53: =1-0.081470516 -> 0.91852948 | BE53: =1-0.081470516 -> 0.91852948 | BF53: =1-0.081470516 -> 0.91852948 | BG53: =1-0.081470516 -> 0.91852948 | BH53: =1-0.125631472 -> 0.87436853 | BI53: =1-0.125631472 -> 0.87436853 | BJ53: =1-0.125631472 -> 0.87436853 | BK53: =1-0.125631472 -> 0.87436853 | BL53: =1-0.125631472 -> 0.87436853 | BM53: =1-0.216329625 -> 0.78367038
A54: PENSION VALUE | B54: =SUMPRODUCT(AQ52:BM52,AQ53:BM53) -> 2.8194703e+09
A56: TOTAL PENSION VALUE | B56: =SUM(B48,B54) -> 5.8186776e+09

Sheet 2. Consumption Needs
A1: TIMELINE
A2: Year | B2: 2025 | C2: 2026 | D2: 2027 | E2: 2028 | F2: 2029 | G2: 2030 | H2: 2031 | I2: 2032 | J2: 2033 | K2: 2034 | L2: 2035 | M2: 2036 | N2: 2037 | O2: 2038 | P2: 2039 | Q2: 2040 | R2: 2041 | S2: 2042 | T2: 2043 | U2: 2044 | V2: 2045 | W2: 2046 | X2: 2047 | Y2: 2048 | Z2: 2049 | AA2: 2050 | AB2: 2051 | AC2: 2052 | AD2: 2053 | AE2: 2054 | AF2: 2055 | AG2: 2056 | AH2: 2057 | AI2: 2058 | AJ2: 2059 | AK2: 2060 | AL2: 2061 | AM2: 2062 | AN2: 2063 | AO2: 2064 | AP2: 2065 | AQ2: 2066 | AR2: 2067 | AS2: 2068 | AT2: 2069 | AU2: 2070 | AV2: 2071 | AW2: 2072 | AX2: 2073 | AY2: 2074 | AZ2: 2075 | BA2: 2076 | BB2: 2077 | BC2: 2078 | BD2: 2079 | BE2: 2080 | BF2: 2081 | BG2: 2082 | BH2: 2083 | BI2: 2084 | BJ2: 2085 | BK2: 2086 | BL2: 2087 | BM2: 2088
A3: Age | B3: 22 | C3: 23 | D3: 24 | E3: 25 | F3: 26 | G3: 27 | H3: 28 | I3: 29 | J3: 30 | K3: 31 | L3: 32 | M3: 33 | N3: 34 | O3: 35 | P3: 36 | Q3: 37 | R3: 38 | S3: 39 | T3: 40 | U3: 41 | V3: 42 | W3: 43 | X3: 44 | Y3: 45 | Z3: 46 | AA3: 47 | AB3: 48 | AC3: 49 | AD3: 50 | AE3: 51 | AF3: 52 | AG3: 53 | AH3: 54 | AI3: 55 | AJ3: 56 | AK3: 57 | AL3: 58 | AM3: 59 | AN3: 60 | AO3: 61 | AP3: 62 | AQ3: 63 | AR3: 64 | AS3: 65 | AT3: 66 | AU3: 67 | AV3: 68 | AW3: 69 | AX3: 70 | AY3: 71 | AZ3: 72 | BA3: 73 | BB3: 74 | BC3: 75 | BD3: 76 | BE3: 77 | BF3: 78 | BG3: 79 | BH3: 80 | BI3: 81 | BJ3: 82 | BK3: 83 | BL3: 84 | BM3: 85
A4: Event | H4: Buy car | J4: Nhi's 6 months of maternity leave Buy apartment | K4: Child is born | AC4: Child goes to university | AF4: Child is independent (when year ends) | AN4: Nhi retires (when year ends) | AP4: Husband retires (when year ends) | AY4: Trash car Go travel around the world | BM4: Nhi and Husband die (when year ends)
A5: Inflation Rate | B5: ='1. Drivers'!B17 -> 0.0295 | C5: ='1. Drivers'!B18 -> 0.0249 | D5: ='1. Drivers'!B19 -> 0.028 | E5: ='1. Drivers'!B20 -> 0.029 | F5: ='1. Drivers'!B21 -> 0.029 | G5: ='1. Drivers'!B22 -> 0.029 | H5: ='1. Drivers'!$B$23 -> 0.02881 | I5: ='1. Drivers'!$B$23 -> 0.02881 | J5: ='1. Drivers'!$B$23 -> 0.02881 | K5: ='1. Drivers'!$B$23 -> 0.02881 | L5: ='1. Drivers'!$B$23 -> 0.02881 | M5: ='1. Drivers'!$B$23 -> 0.02881 | N5: ='1. Drivers'!$B$23 -> 0.02881 | O5: ='1. Drivers'!$B$23 -> 0.02881 | ... BM5: ='1. Drivers'!$B$23 -> 0.02881
A7: CONSUMPTION NEED (BEFORE LIFE INSURANCE)
A8: Living Expenses | B8: =B59 -> 3.2545954e+08 | C8: =B8*(1+C5) -> 3.3356349e+08 | D8: =C8*(1+D5) -> 3.4290326e+08 | E8: =D8*(1+E5) -> 3.5284746e+08 | F8: =E8*(1+F5) -> 3.6308004e+08 | G8: =F8*(1+G5) -> 3.7360936e+08 | H8: =G8*(1+H5) -> 3.8437304e+08 | I8: =H8*(1+I5) -> 3.9544683e+08 | J8: =I8*(1+J5) -> 4.0683965e+08 | K8: =(G57+K43)*(1+C5)*(1+D5)*(1+E5)*(1+F5)*(1+G5)*(1+H5)^(K2-H2+1) -> 5.0583863e+08 | L8: =G57*(1+C5)*(1+D5)*(1+E5)*(1+F5)*(1+G5)*(1+H5)^(L2-H2+1) -> 3.6302767e+08 | M8: =L8*(1+M5) -> 3.734865e+08 | N8: =M8*(1+N5) -> 3.8424664e+08 | O8: =N8*(1+O5) -> 3.9531679e+08 | P8: =O8*(1+P5) -> 4.0670587e+08 | Q8: =P8*(1+Q5) -> 4.1842306e+08 | R8: =Q8*(1+R5) -> 4.3047783e+08 | S8: =R8*(1+S5) -> 4.428799e+08 | T8: =S8*(1+T5) -> 4.5563927e+08 | ... AX8: =AW8*(1+AX5) -> 1.0682587e+09 | AY8: =0 -> 0 | AZ8: =AX8*(1+AY5)*(1+AZ5) -> 1.1306985e+09 | BA8: =AZ8*(1+BA5) -> 1.1632739e+09 | BB8: =BA8*(1+BB5) -> 1.1967878e+09 | BC8: =BB8*(1+BC5) -> 1.2312673e+09 | BD8: =BC8*(1+BD5) -> 1.2667401e+09 | BE8: =BD8*(1+BE5) -> 1.3032349e+09 | BF8: =BE8*(1+BF5) -> 1.3407811e+09 | BG8: =BF8*(1+BG5) -> 1.379409e+09 | BH8: =BG8*(1+BH5) -> 1.4191497e+09 | ... BM8: =BL8*(1+BM5) -> 1.6357017e+09
A9: Prenancy and Child Rearing Expenses | J9: =K28*(1+C5)*(1+D5)*(1+E5)*(1+F5)*(1+G5)*(1+H5)^(J2-H2+1) -> 41251543 | K9: =K29*(1+C5)*(1+D5)*(1+E5)*(1+F5)*(1+G5)*(1+H5)^4 -> 60444849 | L9: =K30*(1+C5)*(1+D5)*(1+E5)*(1+F5)*(1+G5)*(1+H5)^5 -> 91294730 | M9: =K30*(1+C5)*(1+D5)*(1+E5)*(1+F5)*(1+G5)*(1+H5)^6 -> 93924931 | N9: =K31*(1+C5)*(1+D5)*(1+E5)*(1+F5)*(1+G5)*(1+H5)^7 -> 70022397 | O9: =K31*(1+C5)*(1+D5)*(1+E5)*(1+F5)*(1+G5)*(1+H5)^8 -> 72039743 | P9: =K31*(1+C5)*(1+D5)*(1+E5)*(1+F5)*(1+G5)*(1+H5)^9 -> 74115207 | Q9: =$K$32*(1+$C$5)*(1+$D$5)*(1+$E$5)*(1+$F$5)*(1+$G$5)*(1+$H$5)^10 -> 37057727 | R9: =$K$32*(1+$C$5)*(1+$D$5)*(1+$E$5)*(1+$F$5)*(1+$G$5)*(1+$H$5)^11 -> 38125360 | S9: =$K$32*(1+$C$5)*(1+$D$5)*(1+$E$5)*(1+$F$5)*(1+$G$5)*(1+$H$5)^12 -> 39223752 | T9: =$K$32*(1+$C$5)*(1+$D$5)*(1+$E$5)*(1+$F$5)*(1+$G$5)*(1+$H$5)^13 -> 40353788 | U9: =$K$32*(1+$C$5)*(1+$D$5)*(1+$E$5)*(1+$F$5)*(1+$G$5)*(1+$H$5)^14 -> 41516380 | V9: =$K$33*(1+$C$5)*(1+$D$5)*(1+$E$5)*(1+$F$5)*(1+$G$5)*(1+$H$5)^15 -> 73384589 | W9: =$K$33*(1+$C$5)*(1+$D$5)*(1+$E$5)*(1+$F$5)*(1+$G$5)*(1+$H$5)^16 -> 75498799 | X9: =$K$33*(1+$C$5)*(1+$D$5)*(1+$E$5)*(1+$F$5)*(1+$G$5)*(1+$H$5)^17 -> 77673919 | Y9: =$K$33*(1+$C$5)*(1+$D$5)*(1+$E$5)*(1+$F$5)*(1+$G$5)*(1+$H$5)^18 -> 79911705 | Z9: =$K$34*(1+$C$5)*(1+$D$5)*(1+$E$5)*(1+$F$5)*(1+$G$5)*(1+$H$5)^19 -> 97147036 | AA9: =$K$34*(1+$C$5)*(1+$D$5)*(1+$E$5)*(1+$F$5)*(1+$G$5)*(1+$H$5)^20 -> 99945842 | AB9: =$K$34*(1+$C$5)*(1+$D$5)*(1+$E$5)*(1+$F$5)*(1+$G$5)*(1+$H$5)^21 -> 1.0282528e+08 | AC9: =($K$35+K36)*(1+$C$5)*(1+$D$5)*(1+$E$5)*(1+$F$5)*(1+$G$5)*(1+$H$5)^22 -> 3.641966e+08 | AD9: =$K$35*(1+$C$5)*(1+$D$5)*(1+$E$5)*(1+$F$5)*(1+$G$5)*(1+$H$5)^23 -> 2.3440061e+08 | AE9: =$K$35*(1+$C$5)*(1+$D$5)*(1+$E$5)*(1+$F$5)*(1+$G$5)*(1+$H$5)^24 -> 2.4115369e+08 | AF9: =$K$35*(1+$C$5)*(1+$D$5)*(1+$E$5)*(1+$F$5)*(1+$G$5)*(1+$H$5)^25 -> 2.4810133e+08 | AG9: =K37*(1+$C$5)*(1+$D$5)*(1+$E$5)*(1+$F$5)*(1+$G$5)*(1+$H$5)^26 -> 3.9182243e+08
A10: Car Expenses | H10: =K50*(1+C5)*(1+D5)*(1+E5)*(1+F5)*(1+G5)*(1+H5) -> 5.6238817e+08 | I10: =(K48+K49)*(1+C5)*(1+D5)*(1+E5)*(1+F5)*(1+G5)*(1+H5)^2 -> 45187391 | J10: =I10*(1+J5) -> 46489239 | K10: =J10*(1+K5) -> 47828594 | L10: =K10*(1+L5) -> 49206536 | M10: =L10*(1+M5) -> 50624177 | N10: =M10*(1+N5) -> 52082659 | O10: =N10*(1+O5) -> 53583160 | P10: =O10*(1+P5) -> 55126891 | Q10: =P10*(1+Q5) -> 56715097 | ... AX10: =AW10*(1+AX5) -> 1.4479698e+08
A11: Apartment (Down Payment and Mortgage Payment) | J11: ='2. Mortgage'!B2-'2. Mortgage'!B4 -> 1.1652075e+09 | K11: ='2. Mortgage'!K2 -> 2.8113427e+08 | L11: ='2. Mortgage'!K14 -> 2.7368177e+08 | M11: ='2. Mortgage'!K26 -> 2.6622927e+08 | N11: ='2. Mortgage'!K38 -> 3.2601865e+08 | O11: ='2. Mortgage'!K50 -> 3.1450115e+08 | P11: ='2. Mortgage'!K62 -> 3.0298365e+08 | Q11: ='2. Mortgage'!K74 -> 2.9146615e+08 | R11: ='2. Mortgage'!K86 -> 2.7994865e+08 | S11: ='2. Mortgage'!K98 -> 2.6843115e+08 | T11: ='2. Mortgage'!K110 -> 2.5691365e+08 | U11: ='2. Mortgage'!K122 -> 2.4539615e+08 | V11: ='2. Mortgage'!K134 -> 2.3387865e+08 | W11: ='2. Mortgage'!K146 -> 2.2236115e+08 | X11: ='2. Mortgage'!K158 -> 2.1084365e+08 | Y11: ='2. Mortgage'!K170 -> 1.9932615e+08 | Z11: ='2. Mortgage'!K182 -> 1.8780865e+08 | AA11: ='2. Mortgage'!K194 -> 1.7629115e+08 | AB11: ='2. Mortgage'!K206 -> 1.6477365e+08 | AC11: ='2. Mortgage'!K218 -> 1.5325615e+08 | AD11: ='2. Mortgage'!K230 -> 1.4173865e+08
A12: Car Insurance | H12: ='4. Health and Car Insurance'!H38 -> 9414583 | I12: ='4. Health and Car Insurance'!I38 -> 9685817.1 | J12: ='4. Health and Car Insurance'!J38 -> 9012148.2 | K12: ='4. Health and Car Insurance'!K38 -> 9271788.2 | L12: ='4. Health and Car Insurance'!L38 -> 9538908.5 | M12: ='4. Health and Car Insurance'!M38 -> 8839786.4 | N12: ='4. Health and Car Insurance'!N38 -> 9094460.7 | O12: ='4. Health and Car Insurance'!O38 -> 9356472.1 | ... AX12: ='4. Health and Car Insurance'!AX38 -> 22962448
A13: Health Insurance | B13: ='4. Health and Car Insurance'!B33 -> 3008750 | C13: ='4. Health and Car Insurance'!C33 -> 3083667.9 | D13: ='4. Health and Car Insurance'!D33 -> 3170010.6 | E13: ='4. Health and Car Insurance'!E33 -> 3261940.9 | F13: ='4. Health and Car Insurance'!F33 -> 3356537.2 | G13: ='4. Health and Car Insurance'!G33 -> 3453876.7 | H13: ='4. Health and Car Insurance'!H33 -> 3553382.9 | I13: ='4. Health and Car Insurance'!I33 -> 3655755.9 | ... AN13: ='4. Health and Car Insurance'!AN33 -> 10581541
A14: Travel Expenses | AY14: =K56*(1+$C$5)*(1+$D$5)*(1+$E$5)*(1+$F$5)*(1+$G$5)*(1+$H$5)^(AY2-H2+1) -> 5.5117493e+09
A15: Total Expenses | B15: =SUM(B8:B14) -> 3.2846829e+08 | C15: =SUM(C8:C14) -> 3.3664715e+08 | D15: =SUM(D8:D14) -> 3.4607328e+08 | E15: =SUM(E8:E14) -> 3.561094e+08 | F15: =SUM(F8:F14) -> 3.6643657e+08 | G15: =SUM(G8:G14) -> 3.7706323e+08 | H15: =SUM(H8:H14) -> 9.5972918e+08 | I15: =SUM(I8:I14) -> 4.5397579e+08 | ... BM15: =SUM(BM8:BM14) -> 1.6357017e+09
A16: Present value of Total Expenses | B16: =B15 -> 3.2846829e+08 | C16: =C15/(1+C5) -> 3.2846829e+08 | D16: =D15/((1+C5)*(1+D5)) -> 3.2846829e+08 | E16: =E15/((1+C5)*(1+D5)*(1+E5)) -> 3.2846829e+08 | F16: =F15/((1+C5)*(1+D5)*(1+E5)*(1+F5)) -> 3.2846829e+08 | G16: =G15/((1+C5)*(1+D5)*(1+E5)*(1+F5)*(1+G5)) -> 3.2846829e+08 | H16: =H15/((1+$C$5)*(1+$D$5)*(1+$E$5)*(1+$F$5)*(1+$G$5)*(1+$H$5)^(H2-$H$2+1)) -> 8.1262989e+08 | I16: =I15/((1+$C$5)*(1+$D$5)*(1+$E$5)*(1+$F$5)*(1+$G$5)*(1+$H$5)^(I2-$H$2+1)) -> 3.7362989e+08 | J16: =J15/((1+$C$5)*(1+$D$5)*(1+$E$5)*(1+$F$5)*(1+$G$5)*(1+$H$5)^(J2-$H$2+1)) -> 1.3379989e+09 | K16: =K15/((1+$C$5)*(1+$D$5)*(1+$E$5)*(1+$F$5)*(1+$G$5)*(1+$H$5)^(K2-$H$2+1)) -> 7.0934215e+08 | L16: =L15/((1+$C$5)*(1+$D$5)*(1+$E$5)*(1+$F$5)*(1+$G$5)*(1+$H$5)^(L2-$H$2+1)) -> 6.0063806e+08 | M16: =M15/((1+$C$5)*(1+$D$5)*(1+$E$5)*(1+$F$5)*(1+$G$5)*(1+$H$5)^(M2-$H$2+1)) -> 5.8865537e+08 | N16: =N15/((1+$C$5)*(1+$D$5)*(1+$E$5)*(1+$F$5)*(1+$G$5)*(1+$H$5)^(N2-$H$2+1)) -> 6.0566804e+08 | O16: =O15/((1+$C$5)*(1+$D$5)*(1+$E$5)*(1+$F$5)*(1+$G$5)*(1+$H$5)^(O2-$H$2+1)) -> 5.9115515e+08 | ... BM16: =BM15/((1+$C$5)*(1+$D$5)*(1+$E$5)*(1+$F$5)*(1+$G$5)*(1+$H$5)^(BM2-$H$2+1)) -> 2.743741e+08
A18: CONSUMPTION NEED (AFTER LIFE INSURANCE)
A19: Life Insurance | L19: ='4. Life Insurance'!B61 -> 8733259.2 | M19: =$L$19 -> 8733259.2 | N19: =$L$19 -> 8733259.2 | O19: =$L$19 -> 8733259.2 | P19: =$L$19 -> 8733259.2 | Q19: =$L$19 -> 8733259.2 | R19: =$L$19 -> 8733259.2 | S19: =$L$19 -> 8733259.2 | T19: =$L$19 -> 8733259.2 | ... AJ19: =$L$19 -> 8733259.2
A20: Total Expenses | B20: =SUM(B8:B14,B19) -> 3.2846829e+08 | C20: =SUM(C8:C14,C19) -> 3.3664715e+08 | D20: =SUM(D8:D14,D19) -> 3.4607328e+08 | E20: =SUM(E8:E14,E19) -> 3.561094e+08 | F20: =SUM(F8:F14,F19) -> 3.6643657e+08 | G20: =SUM(G8:G14,G19) -> 3.7706323e+08 | H20: =SUM(H8:H14,H19) -> 9.5972918e+08 | I20: =SUM(I8:I14,I19) -> 4.5397579e+08 | ... BM20: =SUM(BM8:BM14,BM19) -> 1.6357017e+09
A21: Present value of Total Expenses | B21: =B20 -> 3.2846829e+08 | C21: =C20/(1+C5) -> 3.2846829e+08 | D21: =D20/((1+C5)*(1+D5)) -> 3.2846829e+08 | E21: =E20/((1+C5)*(1+D5)*(1+E5)) -> 3.2846829e+08 | F21: =F20/((1+C5)*(1+D5)*(1+E5)*(1+F5)) -> 3.2846829e+08 | G21: =G20/((1+C5)*(1+D5)*(1+E5)*(1+F5)*(1+G5)) -> 3.2846829e+08 | H21: =H20/((1+$C$5)*(1+$D$5)*(1+$E$5)*(1+$F$5)*(1+$G$5)*(1+$H$5)^(H2-$H$2+1)) -> 8.1262989e+08 | I21: =I20/((1+$C$5)*(1+$D$5)*(1+$E$5)*(1+$F$5)*(1+$G$5)*(1+$H$5)^(I2-$H$2+1)) -> 3.7362989e+08 | J21: =J20/((1+$C$5)*(1+$D$5)*(1+$E$5)*(1+$F$5)*(1+$G$5)*(1+$H$5)^(J2-$H$2+1)) -> 1.3379989e+09 | K21: =K20/((1+$C$5)*(1+$D$5)*(1+$E$5)*(1+$F$5)*(1+$G$5)*(1+$H$5)^(K2-$H$2+1)) -> 7.0934215e+08 | L21: =L20/((1+$C$5)*(1+$D$5)*(1+$E$5)*(1+$F$5)*(1+$G$5)*(1+$H$5)^(L2-$H$2+1)) -> 6.0723861e+08 | M21: =M20/((1+$C$5)*(1+$D$5)*(1+$E$5)*(1+$F$5)*(1+$G$5)*(1+$H$5)^(M2-$H$2+1)) -> 5.9507108e+08 | N21: =N20/((1+$C$5)*(1+$D$5)*(1+$E$5)*(1+$F$5)*(1+$G$5)*(1+$H$5)^(N2-$H$2+1)) -> 6.1190409e+08 | O21: =O20/((1+$C$5)*(1+$D$5)*(1+$E$5)*(1+$F$5)*(1+$G$5)*(1+$H$5)^(O2-$H$2+1)) -> 5.9721657e+08 | ... BM21: =BM20/((1+$C$5)*(1+$D$5)*(1+$E$5)*(1+$F$5)*(1+$G$5)*(1+$H$5)^(BM2-$H$2+1)) -> 2.743741e+08
A22: LIFETIME CONSUMPTION NEEDS | B22: =SUM(B21:BM21) -> 2.7200707e+10
A24: ANNUAL LIVING EXPENSES
A26: BEFORE BUYING HOME | F26: AFTER BUYING HOME | J26: PRENANCY AND CHILD REARING
A27: EXPENSES | B27: AMOUNT/YEAR | C27: % | F27: EXPENSES | G27: AMOUNT/YEAR | H27: % | J27: EXPENSES | K27: AMOUNT/YEAR | L27: %
A28: Rent | B28: =8000000*12 -> 96000000 | C28: =B28/$B$59 -> 0.29496754 | D28: Rent | F28: Utilities | J28: Pregnancy and Childbirth | K28: 33000000 | L28: =K28/$K$38 -> 0.050979121 | M28: Pregnancy
F29: Apartment Service | G29: =AVERAGE(10000,20000)*83*12 -> 14940000 | J29: Aged 0-1 | K29: =AVERAGE(36000000,58000000) -> 47000000 | L29: =K29/$K$38 -> 0.072606627 | M29: Child Rearing
A30: Utilities | F30: Basic (Electricity, Heating, Cooling, Water, Garbage) | G30: =2218015.87*83/85*12 -> 25989927 | H30: =G30/$B$59 -> 0.079856091 | J30: Aged 1-3 | K30: =AVERAGE(116000000,160000000)/2 -> 69000000 | L30: =K30/$K$38 -> 0.10659271
A31: Apartment Service | B31: =AVERAGE(10000,20000)*56*12 -> 10080000 | C31: =B31/$B$59 -> 0.030971591 | D31: Service | F31: Mobile Phone with Calls and 10GB+ Data Monthly | G31: =152500*2*12 -> 3660000 | H31: =G31/$B$59 -> 0.011245637 | J31: Kintergarden (Aged 3-6) | K31: =AVERAGE(126000000,174000000)/3 -> 50000000 | L31: =K31/$K$38 -> 0.077241092
A32: Basic (Electricity, Heating, Cooling, Water, Garbage) | B32: =2218015.87*56/85*12 -> 17535373 | C32: =B32/$B$59 -> 0.053878809 | D32: Utilities | F32: Internet (60 Mbps or More, Unlimited Data, Cable/ADSL) | G32: =246500*12 -> 2958000 | H32: =G32/$B$59 -> 0.0090886872 | J32: Elementary School (Aged 6-11) | K32: =AVERAGE(108000000,135000000)/5 -> 24300000 | L32: =K32/$K$38 -> 0.037539171
A33: Mobile Phone with Calls and 10GB+ Data Monthly | B33: =152500*2*12 -> 3660000 | C33: =B33/$B$59 -> 0.011245637 | F33: Total Utilities | G33: =SUM(G29:G32) -> 47547927 | H33: =G33/$B$59 -> 0.14609474 | J33: Secondary School (Aged 11-15) | K33: =AVERAGE(154000000,180000000)/4 -> 41750000 | L33: =K33/$K$38 -> 0.064496312
A34: Internet (60 Mbps or More, Unlimited Data, Cable/ADSL) | B34: =246500*12 -> 2958000 | C34: =B34/$B$59 -> 0.0090886872 | J34: High School (Aged 15-18) | K34: =AVERAGE(134000000,162000000)/3 -> 49333333 | L34: =K34/$K$38 -> 0.076211211
A35: Total Utilities | B35: =SUM(B31:B34) -> 34233373 | C35: =B35/$B$59 -> 0.10518472 | F35: Foods and Goceries | J35: College (Aged 18-22) | K35: =AVERAGE(350000000,500000000)/4 -> 106250000 | L35: =K35/$K$38 -> 0.16413732
F36: Dine in | G36: =3381090.49*2*12 -> 81146172 | H36: =G36/$B$59 -> 0.24932798 | J36: Honda Airblade 160 (Standard version) | K36: 63590500 | L36: =K36/$K$38 -> 0.098235994
A37: Foods and Goceries | D37: Food | F37: Dine out | G37: =1000000*12 -> 12000000 | H37: =G37/$B$59 -> 0.036870942 | J37: Marriage Support | K37: =7000000+28200000+34200000+(141000000+7400000+39000000)/2 -> 163100000 | L37: =K37/$K$38 -> 0.25196044 | M37: Marriage
A38: Dine in | B38: =3381090.49*2*12 -> 81146172 | C38: =B38/$B$59 -> 0.24932798 | F38: Snacks and Drinks | G38: =500000*12 -> 6000000 | H38: =G38/$B$59 -> 0.018435471 | J38: TOTAL EXPENSES | K38: =SUM(K28:K37) -> 6.4732383e+08 | L38: =K38/$K$38 -> 1
A39: Dine out | B39: =800000*12 -> 9600000 | C39: =B39/$B$59 -> 0.029496754 | F39: Total Foods and Goceries | G39: =SUM(G36:G38) -> 99146172 | H39: =G39/$B$59 -> 0.3046344
A40: Snacks and Drinks | B40: =300000*12 -> 3600000 | C40: =B40/$B$59 -> 0.011061283 | J40: FUNITURE EXPENSE WHEN BUYING HOME
A41: Total Foods and Goceries | B41: =SUM(B38:B40) -> 94346172 | C41: =B41/$B$59 -> 0.28988602 | F41: Transportation | J41: EXPENSES | K41: AMOUNT/YEAR | L41: %
F42: Fuel and Vehicle Upkeep (include Insurance) | G42: =(435000+555000)*12 -> 11880000 | H42: =G42/$B$59 -> 0.036502233 | J42: Interior design & construction | K42: 118950000 | L42: =K42/$K$43 -> 1 | M42: Furnitures
A43: Transportation | F43: Parking Expenses | G43: =AVERAGE(50000,100000)*2*12 -> 1800000 | H43: =G43/$B$59 -> 0.0055306413 | J43: TOTAL EXPENSES | K43: =K42 -> 118950000 | L43: =K43/$K$43 -> 1
A44: Fuel and Vehicle Upkeep | B44: =(435000+555000)*12 -> 11880000 | C44: =B44/$B$59 -> 0.036502233 | D44: Motorbike | F44: Public transport and Taxi | G44: =100000*2*12 -> 2400000 | H44: =G44/$B$59 -> 0.0073741884
A45: Parking Expenses | B45: =AVERAGE(50000,100000)*2*12 -> 1800000 | C45: =B45/$B$59 -> 0.0055306413 | D45: Parking | F45: Total Transportation | G45: =SUM(G42:G44) -> 16080000 | H45: =G45/$B$59 -> 0.049407062 | J45: CAR EXPENSES
A46: Public transport and Taxi | B46: =100000*2*12 -> 2400000 | C46: =B46/$B$59 -> 0.0073741884 | J46: EXPENSES | K46: AMOUNT/YEAR | L46: %
A47: Total Transportation | B47: =SUM(B44:B46) -> 16080000 | C47: =B47/$B$59 -> 0.049407062 | F47: Medicines and other health care services (Health Insurance not cover) | G47: =100000*2*12 -> 2400000 | H47: =G47/$B$59 -> 0.0073741884 | J47: Price (Down Payment) | K47: =439000000 -> 439000000 | L47: =K47/$K$50 -> 0.92190092 | M47: Car
J48: Fuel and Vehicle Upkeep | K48: =35840000 -> 35840000 | L48: =K48/$K$50 -> 0.075264075 | M48: Upkeep
A49: Medicines and other health care services (Health Insurance not cover) | B49: =100000*2*12 -> 2400000 | C49: =B49/$B$59 -> 0.0073741884 | F49: Entertainment and Others | J49: Parking Expenses | K49: =AVERAGE(700000,2000000) -> 1350000 | L49: =K49/$K$50 -> 0.0028350028 | M49: Parking
F50: Sport and Entertainment | G50: =1000000*2*12 -> 24000000 | H50: =G50/$B$59 -> 0.073741884 | J50: TOTAL EXPENSES | K50: =SUM(K47:K49) -> 476190000 | L50: =K50/$K$50 -> 1
A51: Entertainment and Others | F51: Shopping (Clothes, Cosmetic products,...) | G51: =1000000*2*12 -> 24000000 | H51: =G51/$B$59 -> 0.073741884
A52: Sport and Entertainment | B52: =800000*2*12 -> 19200000 | C52: =B52/$B$59 -> 0.058993507 | D52: Entertainment | F52: Socialize (Gifts for Parents and Relatives, Wedding, Funeral...) | G52: =10000000*2 -> 20000000 | H52: =G52/G57 -> 0.072893178 | J52: TRAVEL EXPENSES
A53: Shopping (Clothes, Cosmetic products,...) | B53: =800000*2*12 -> 19200000 | C53: =B53/$B$59 -> 0.058993507 | F53: Travelling Expenses | G53: =5000000*2 -> 10000000 | H53: =G53/G57 -> 0.036446589 | J53: EXPENSES | K53: AMOUNT/YEAR | L53: %
A54: Socialize (Gifts for Parents and Relatives, Wedding, Funeral...) | B54: =7000000*2 -> 14000000 | C54: =B54/B59 -> 0.043016099 | F54: Other Personal Allowances | G54: =1300000*2*12 -> 31200000 | H54: =G54/$B$59 -> 0.095864449 | J54: Travel around the world | K54: =651350000*2 -> 1302700000 | L54: =K54/$K$56 -> 0.9467242 | M54: Travel
A55: Travelling Expenses | B55: =3000000*2 -> 6000000 | C55: =B55/B59 -> 0.018435471 | D55: Travelling | F55: Total Entertainment and Others | G55: =SUM(G50:G54) -> 109200000 | H55: =G55/$B$59 -> 0.33552557 | J55: Apartment and Other Expenses | K55: =G33+G42-(285000+375000)*12+G43+G52 -> 73307927 | L55: =K55/$K$56 -> 0.053275803
A56: Other Personal Allowances | B56: =1000000*2*12 -> 24000000 | C56: =B56/$B$59 -> 0.073741884 | J56: TOTAL EXPENSES | K56: =SUM(K54:K55) -> 1.3760079e+09 | L56: =K56/$K$56 -> 1
A57: Total Entertainment and Others | B57: =SUM(B52:B56) -> 82400000 | C57: =B57/$B$59 -> 0.25318047 | F57: TOTAL EXPENSES | G57: =SUM(G33,G39,G45,G47,G55) -> 2.743741e+08 | H57: =G57/$B$59 -> 0.84303596
A59: TOTAL EXPENSES | B59: =SUM(B28,B35,B41,B47,B49,B57) -> 3.2545954e+08 | C59: =B59/$B$59 -> 1

Sheet 2. Mortgage
A1: Mortgage (BIDV) | E1: Year | F1: Month | G1: Principal payment | H1: Remaining principal | I1: Interest payment | J1: Monthly Total payment | K1: Annually Total payment
A2: Apartment Price | B2: =37350000*83*(1+'1. Drivers'!B18)*(1+'1. Drivers'!B19)*(1+'1. Drivers'!B20)*(1+'1. Drivers'!B21)*(1+'1. Drivers'!B22)*(1+'1. Drivers'!B23)^3 -> 3.8752075e+09 | C2: Home | E2: 2034 | F2: January | G2: =$B$4/(20*12) -> 11291667 | H2: =B4-G2 -> 2.6987083e+09 | I2: =B4*B5/12 -> 12420833 | J2: =SUM(G2,I2) -> 23712500 | K2: =SUM(J2:J13) -> 2.8113427e+08
A3: Max Value can Borrow | B3: =B2*70% -> 2.7126452e+09 | C3: Interest | F3: February | G3: =$B$4/(20*12) -> 11291667 | H3: =H2-G3 -> 2.6874167e+09 | I3: =H2*$B$5/12 -> 12369080 | J3: =SUM(G3,I3) -> 23660747
A4: Principal | B4: =ROUNDDOWN(B3,-7) -> 2710000000 | F4: March | G4: =$B$4/(20*12) -> 11291667 | H4: =H3-G4 -> 2.676125e+09 | I4: =H3*$B$5/12 -> 12317326 | J4: =SUM(G4,I4) -> 23608993
A5: First 3-year | B5: 0.055 | F5: April | G5: =$B$4/(20*12) -> 11291667 | H5: =H4-G5 -> 2.6648333e+09 | I5: =H4*$B$5/12 -> 12265573 | J5: =SUM(G5,I5) -> 23557240
A6: More than 3 years | B6: =B5+3% -> 0.085 | F6: May | G6: =$B$4/(20*12) -> 11291667 | H6: =H5-G6 -> 2.6535417e+09 | I6: =H5*$B$5/12 -> 12213819 | J6: =SUM(G6,I6) -> 23505486
A7: Period | B7: 20 years | F7: June | G7: =$B$4/(20*12) -> 11291667 | H7: =H6-G7 -> 2.64225e+09 | I7: =H6*$B$5/12 -> 12162066 | J7: =SUM(G7,I7) -> 23453733
F8: July | G8: =$B$4/(20*12) -> 11291667 | H8: =H7-G8 -> 2.6309583e+09 | I8: =H7*$B$5/12 -> 12110313 | J8: =SUM(G8,I8) -> 23401979
F9: August | G9: =$B$4/(20*12) -> 11291667 | H9: =H8-G9 -> 2.6196667e+09 | I9: =H8*$B$5/12 -> 12058559 | J9: =SUM(G9,I9) -> 23350226
F10: September | G10: =$B$4/(20*12) -> 11291667 | H10: =H9-G10 -> 2.608375e+09 | I10: =H9*$B$5/12 -> 12006806 | J10: =SUM(G10,I10) -> 23298472
F11: October | G11: =$B$4/(20*12) -> 11291667 | H11: =H10-G11 -> 2.5970833e+09 | I11: =H10*$B$5/12 -> 11955052 | J11: =SUM(G11,I11) -> 23246719
F12: November | G12: =$B$4/(20*12) -> 11291667 | H12: =H11-G12 -> 2.5857917e+09 | I12: =H11*$B$5/12 -> 11903299 | J12: =SUM(G12,I12) -> 23194965
F13: December | G13: =$B$4/(20*12) -> 11291667 | H13: =H12-G13 -> 2.5745e+09 | I13: =H12*$B$5/12 -> 11851545 | J13: =SUM(G13,I13) -> 23143212
E14: 2035 | F14: January | G14: =$B$4/(20*12) -> 11291667 | H14: =H13-G14 -> 2.5632083e+09 | I14: =H13*$B$5/12 -> 11799792 | J14: =SUM(G14,I14) -> 23091458 | K14: =SUM(J14:J25) -> 2.7368177e+08
F15: February | G15: =$B$4/(20*12) -> 11291667 | H15: =H14-G15 -> 2.5519167e+09 | I15: =H14*$B$5/12 -> 11748038 | J15: =SUM(G15,I15) -> 23039705
F16: March | G16: =$B$4/(20*12) -> 11291667 | H16: =H15-G16 -> 2.540625e+09 | I16: =H15*$B$5/12 -> 11696285 | J16: =SUM(G16,I16) -> 22987951
F17: April | G17: =$B$4/(20*12) -> 11291667 | H17: =H16-G17 -> 2.5293333e+09 | I17: =H16*$B$5/12 -> 11644531 | J17: =SUM(G17,I17) -> 22936198
F18: May | G18: =$B$4/(20*12) -> 11291667 | H18: =H17-G18 -> 2.5180417e+09 | I18: =H17*$B$5/12 -> 11592778 | J18: =SUM(G18,I18) -> 22884444
F19: June | G19: =$B$4/(20*12) -> 11291667 | H19: =H18-G19 -> 2.50675e+09 | I19: =H18*$B$5/12 -> 11541024 | J19: =SUM(G19,I19) -> 22832691
F20: July | G20: =$B$4/(20*12) -> 11291667 | H20: =H19-G20 -> 2.4954583e+09 | I20: =H19*$B$5/12 -> 11489271 | J20: =SUM(G20,I20) -> 22780938
F21: August | G21: =$B$4/(20*12) -> 11291667 | H21: =H20-G21 -> 2.4841667e+09 | I21: =H20*$B$5/12 -> 11437517 | J21: =SUM(G21,I21) -> 22729184
F22: September | G22: =$B$4/(20*12) -> 11291667 | H22: =H21-G22 -> 2.472875e+09 | I22: =H21*$B$5/12 -> 11385764 | J22: =SUM(G22,I22) -> 22677431
F23: October | G23: =$B$4/(20*12) -> 11291667 | H23: =H22-G23 -> 2.4615833e+09 | I23: =H22*$B$5/12 -> 11334010 | J23: =SUM(G23,I23) -> 22625677
F24: November | G24: =$B$4/(20*12) -> 11291667 | H24: =H23-G24 -> 2.4502917e+09 | I24: =H23*$B$5/12 -> 11282257 | J24: =SUM(G24,I24) -> 22573924
F25: December | G25: =$B$4/(20*12) -> 11291667 | H25: =H24-G25 -> 2.439e+09 | I25: =H24*$B$5/12 -> 11230503 | J25: =SUM(G25,I25) -> 22522170
E26: 2036 | F26: January | G26: =$B$4/(20*12) -> 11291667 | H26: =H25-G26 -> 2.4277083e+09 | I26: =H25*$B$5/12 -> 11178750 | J26: =SUM(G26,I26) -> 22470417 | K26: =SUM(J26:J37) -> 2.6622927e+08
F27: February | G27: =$B$4/(20*12) -> 11291667 | H27: =H26-G27 -> 2.4164167e+09 | I27: =H26*$B$5/12 -> 11126997 | J27: =SUM(G27,I27) -> 22418663
F28: March | G28: =$B$4/(20*12) -> 11291667 | H28: =H27-G28 -> 2.405125e+09 | I28: =H27*$B$5/12 -> 11075243 | J28: =SUM(G28,I28) -> 22366910
F29: April | G29: =$B$4/(20*12) -> 11291667 | H29: =H28-G29 -> 2.3938333e+09 | I29: =H28*$B$5/12 -> 11023490 | J29: =SUM(G29,I29) -> 22315156
F30: May | G30: =$B$4/(20*12) -> 11291667 | H30: =H29-G30 -> 2.3825417e+09 | I30: =H29*$B$5/12 -> 10971736 | J30: =SUM(G30,I30) -> 22263403
F31: June | G31: =$B$4/(20*12) -> 11291667 | H31: =H30-G31 -> 2.37125e+09 | I31: =H30*$B$5/12 -> 10919983 | J31: =SUM(G31,I31) -> 22211649
F32: July | G32: =$B$4/(20*12) -> 11291667 | H32: =H31-G32 -> 2.3599583e+09 | I32: =H31*$B$5/12 -> 10868229 | J32: =SUM(G32,I32) -> 22159896
F33: August | G33: =$B$4/(20*12) -> 11291667 | H33: =H32-G33 -> 2.3486667e+09 | I33: =H32*$B$5/12 -> 10816476 | J33: =SUM(G33,I33) -> 22108142
F34: September | G34: =$B$4/(20*12) -> 11291667 | H34: =H33-G34 -> 2.337375e+09 | I34: =H33*$B$5/12 -> 10764722 | J34: =SUM(G34,I34) -> 22056389
F35: October | G35: =$B$4/(20*12) -> 11291667 | H35: =H34-G35 -> 2.3260833e+09 | I35: =H34*$B$5/12 -> 10712969 | J35: =SUM(G35,I35) -> 22004635
F36: November | G36: =$B$4/(20*12) -> 11291667 | H36: =H35-G36 -> 2.3147917e+09 | I36: =H35*$B$5/12 -> 10661215 | J36: =SUM(G36,I36) -> 21952882
F37: December | G37: =$B$4/(20*12) -> 11291667 | H37: =H36-G37 -> 2.3035e+09 | I37: =H36*$B$5/12 -> 10609462 | J37: =SUM(G37,I37) -> 21901128
E38: 2037 | F38: January | G38: =$B$4/(20*12) -> 11291667 | H38: =H37-G38 -> 2.2922083e+09 | I38: =H37*$B$6/12 -> 16316458 | J38: =SUM(G38,I38) -> 27608125 | K38: =SUM(J38:J49) -> 3.2601865e+08
F39: February | G39: =$B$4/(20*12) -> 11291667 | H39: =H38-G39 -> 2.2809167e+09 | I39: =H38*$B$6/12 -> 16236476 | J39: =SUM(G39,I39) -> 27528142
F40: March | G40: =$B$4/(20*12) -> 11291667 | H40: =H39-G40 -> 2.269625e+09 | I40: =H39*$B$6/12 -> 16156493 | J40: =SUM(G40,I40) -> 27448160
F41: April | G41: =$B$4/(20*12) -> 11291667 | H41: =H40-G41 -> 2.2583333e+09 | I41: =H40*$B$6/12 -> 16076510 | J41: =SUM(G41,I41) -> 27368177
F42: May | G42: =$B$4/(20*12) -> 11291667 | H42: =H41-G42 -> 2.2470417e+09 | I42: =H41*$B$6/12 -> 15996528 | J42: =SUM(G42,I42) -> 27288194
F43: June | G43: =$B$4/(20*12) -> 11291667 | H43: =H42-G43 -> 2.23575e+09 | I43: =H42*$B$6/12 -> 15916545 | J43: =SUM(G43,I43) -> 27208212
F44: July | G44: =$B$4/(20*12) -> 11291667 | H44: =H43-G44 -> 2.2244583e+09 | I44: =H43*$B$6/12 -> 15836563 | J44: =SUM(G44,I44) -> 27128229
F45: August | G45: =$B$4/(20*12) -> 11291667 | H45: =H44-G45 -> 2.2131667e+09 | I45: =H44*$B$6/12 -> 15756580 | J45: =SUM(G45,I45) -> 27048247
F46: September | G46: =$B$4/(20*12) -> 11291667 | H46: =H45-G46 -> 2.201875e+09 | I46: =H45*$B$6/12 -> 15676597 | J46: =SUM(G46,I46) -> 26968264
F47: October | G47: =$B$4/(20*12) -> 11291667 | H47: =H46-G47 -> 2.1905833e+09 | I47: =H46*$B$6/12 -> 15596615 | J47: =SUM(G47,I47) -> 26888281
F48: November | G48: =$B$4/(20*12) -> 11291667 | H48: =H47-G48 -> 2.1792917e+09 | I48: =H47*$B$6/12 -> 15516632 | J48: =SUM(G48,I48) -> 26808299
F49: December | G49: =$B$4/(20*12) -> 11291667 | H49: =H48-G49 -> 2.168e+09 | I49: =H48*$B$6/12 -> 15436649 | J49: =SUM(G49,I49) -> 26728316
E50: 2038 | F50: January | G50: =$B$4/(20*12) -> 11291667 | H50: =H49-G50 -> 2.1567083e+09 | I50: =H49*$B$6/12 -> 15356667 | J50: =SUM(G50,I50) -> 26648333 | K50: =SUM(J50:J61) -> 3.1450115e+08
F51: February | G51: =$B$4/(20*12) -> 11291667 | H51: =H50-G51 -> 2.1454167e+09 | I51: =H50*$B$6/12 -> 15276684 | J51: =SUM(G51,I51) -> 26568351
F52: March | G52: =$B$4/(20*12) -> 11291667 | H52: =H51-G52 -> 2.134125e+09 | I52: =H51*$B$6/12 -> 15196701 | J52: =SUM(G52,I52) -> 26488368
F53: April | G53: =$B$4/(20*12) -> 11291667 | H53: =H52-G53 -> 2.1228333e+09 | I53: =H52*$B$6/12 -> 15116719 | J53: =SUM(G53,I53) -> 26408385
F54: May | G54: =$B$4/(20*12) -> 11291667 | H54: =H53-G54 -> 2.1115417e+09 | I54: =H53*$B$6/12 -> 15036736 | J54: =SUM(G54,I54) -> 26328403
F55: June | G55: =$B$4/(20*12) -> 11291667 | H55: =H54-G55 -> 2.10025e+09 | I55: =H54*$B$6/12 -> 14956753 | J55: =SUM(G55,I55) -> 26248420
F56: July | G56: =$B$4/(20*12) -> 11291667 | H56: =H55-G56 -> 2.0889583e+09 | I56: =H55*$B$6/12 -> 14876771 | J56: =SUM(G56,I56) -> 26168438
F57: August | G57: =$B$4/(20*12) -> 11291667 | H57: =H56-G57 -> 2.0776667e+09 | I57: =H56*$B$6/12 -> 14796788 | J57: =SUM(G57,I57) -> 26088455
F58: September | G58: =$B$4/(20*12) -> 11291667 | H58: =H57-G58 -> 2.066375e+09 | I58: =H57*$B$6/12 -> 14716806 | J58: =SUM(G58,I58) -> 26008472
F59: October | G59: =$B$4/(20*12) -> 11291667 | H59: =H58-G59 -> 2.0550833e+09 | I59: =H58*$B$6/12 -> 14636823 | J59: =SUM(G59,I59) -> 25928490
F60: November | G60: =$B$4/(20*12) -> 11291667 | H60: =H59-G60 -> 2.0437917e+09 | I60: =H59*$B$6/12 -> 14556840 | J60: =SUM(G60,I60) -> 25848507
F61: December | G61: =$B$4/(20*12) -> 11291667 | H61: =H60-G61 -> 2.0325e+09 | I61: =H60*$B$6/12 -> 14476858 | J61: =SUM(G61,I61) -> 25768524
E62: 2039 | F62: January | G62: =$B$4/(20*12) -> 11291667 | H62: =H61-G62 -> 2.0212083e+09 | I62: =H61*$B$6/12 -> 14396875 | J62: =SUM(G62,I62) -> 25688542 | K62: =SUM(J62:J73) -> 3.0298365e+08
F63: February | G63: =$B$4/(20*12) -> 11291667 | H63: =H62-G63 -> 2.0099167e+09 | I63: =H62*$B$6/12 -> 14316892 | J63: =SUM(G63,I63) -> 25608559
F64: March | G64: =$B$4/(20*12) -> 11291667 | H64: =H63-G64 -> 1.998625e+09 | I64: =H63*$B$6/12 -> 14236910 | J64: =SUM(G64,I64) -> 25528576
F65: April | G65: =$B$4/(20*12) -> 11291667 | H65: =H64-G65 -> 1.9873333e+09 | I65: =H64*$B$6/12 -> 14156927 | J65: =SUM(G65,I65) -> 25448594
F66: May | G66: =$B$4/(20*12) -> 11291667 | H66: =H65-G66 -> 1.9760417e+09 | I66: =H65*$B$6/12 -> 14076944 | J66: =SUM(G66,I66) -> 25368611
F67: June | G67: =$B$4/(20*12) -> 11291667 | H67: =H66-G67 -> 1.96475e+09 | I67: =H66*$B$6/12 -> 13996962 | J67: =SUM(G67,I67) -> 25288628
F68: July | G68: =$B$4/(20*12) -> 11291667 | H68: =H67-G68 -> 1.9534583e+09 | I68: =H67*$B$6/12 -> 13916979 | J68: =SUM(G68,I68) -> 25208646
F69: August | G69: =$B$4/(20*12) -> 11291667 | H69: =H68-G69 -> 1.9421667e+09 | I69: =H68*$B$6/12 -> 13836997 | J69: =SUM(G69,I69) -> 25128663
F70: September | G70: =$B$4/(20*12) -> 11291667 | H70: =H69-G70 -> 1.930875e+09 | I70: =H69*$B$6/12 -> 13757014 | J70: =SUM(G70,I70) -> 25048681
F71: October | G71: =$B$4/(20*12) -> 11291667 | H71: =H70-G71 -> 1.9195833e+09 | I71: =H70*$B$6/12 -> 13677031 | J71: =SUM(G71,I71) -> 24968698
F72: November | G72: =$B$4/(20*12) -> 11291667 | H72: =H71-G72 -> 1.9082917e+09 | I72: =H71*$B$6/12 -> 13597049 | J72: =SUM(G72,I72) -> 24888715
F73: December | G73: =$B$4/(20*12) -> 11291667 | H73: =H72-G73 -> 1.897e+09 | I73: =H72*$B$6/12 -> 13517066 | J73: =SUM(G73,I73) -> 24808733
E74: 2040 | F74: January | G74: =$B$4/(20*12) -> 11291667 | H74: =H73-G74 -> 1.8857083e+09 | I74: =H73*$B$6/12 -> 13437083 | J74: =SUM(G74,I74) -> 24728750 | K74: =SUM(J74:J85) -> 2.9146615e+08
F75: February | G75: =$B$4/(20*12) -> 11291667 | H75: =H74-G75 -> 1.8744167e+09 | I75: =H74*$B$6/12 -> 13357101 | J75: =SUM(G75,I75) -> 24648767
F76: March | G76: =$B$4/(20*12) -> 11291667 | H76: =H75-G76 -> 1.863125e+09 | I76: =H75*$B$6/12 -> 13277118 | J76: =SUM(G76,I76) -> 24568785
F77: April | G77: =$B$4/(20*12) -> 11291667 | H77: =H76-G77 -> 1.8518333e+09 | I77: =H76*$B$6/12 -> 13197135 | J77: =SUM(G77,I77) -> 24488802
F78: May | G78: =$B$4/(20*12) -> 11291667 | H78: =H77-G78 -> 1.8405417e+09 | I78: =H77*$B$6/12 -> 13117153 | J78: =SUM(G78,I78) -> 24408819
F79: June | G79: =$B$4/(20*12) -> 11291667 | H79: =H78-G79 -> 1.82925e+09 | I79: =H78*$B$6/12 -> 13037170 | J79: =SUM(G79,I79) -> 24328837
F80: July | G80: =$B$4/(20*12) -> 11291667 | H80: =H79-G80 -> 1.8179583e+09 | I80: =H79*$B$6/12 -> 12957188 | J80: =SUM(G80,I80) -> 24248854
F81: August | G81: =$B$4/(20*12) -> 11291667 | H81: =H80-G81 -> 1.8066667e+09 | I81: =H80*$B$6/12 -> 12877205 | J81: =SUM(G81,I81) -> 24168872
F82: September | G82: =$B$4/(20*12) -> 11291667 | H82: =H81-G82 -> 1.795375e+09 | I82: =H81*$B$6/12 -> 12797222 | J82: =SUM(G82,I82) -> 24088889
F83: October | G83: =$B$4/(20*12) -> 11291667 | H83: =H82-G83 -> 1.7840833e+09 | I83: =H82*$B$6/12 -> 12717240 | J83: =SUM(G83,I83) -> 24008906
F84: November | G84: =$B$4/(20*12) -> 11291667 | H84: =H83-G84 -> 1.7727917e+09 | I84: =H83*$B$6/12 -> 12637257 | J84: =SUM(G84,I84) -> 23928924
F85: December | G85: =$B$4/(20*12) -> 11291667 | H85: =H84-G85 -> 1.7615e+09 | I85: =H84*$B$6/12 -> 12557274 | J85: =SUM(G85,I85) -> 23848941
E86: 2041 | F86: January | G86: =$B$4/(20*12) -> 11291667 | H86: =H85-G86 -> 1.7502083e+09 | I86: =H85*$B$6/12 -> 12477292 | J86: =SUM(G86,I86) -> 23768958 | K86: =SUM(J86:J97) -> 2.7994865e+08
F87: February | G87: =$B$4/(20*12) -> 11291667 | H87: =H86-G87 -> 1.7389167e+09 | I87: =H86*$B$6/12 -> 12397309 | J87: =SUM(G87,I87) -> 23688976
F88: March | G88: =$B$4/(20*12) -> 11291667 | H88: =H87-G88 -> 1.727625e+09 | I88: =H87*$B$6/12 -> 12317326 | J88: =SUM(G88,I88) -> 23608993
F89: April | G89: =$B$4/(20*12) -> 11291667 | H89: =H88-G89 -> 1.7163333e+09 | I89: =H88*$B$6/12 -> 12237344 | J89: =SUM(G89,I89) -> 23529010
F90: May | G90: =$B$4/(20*12) -> 11291667 | H90: =H89-G90 -> 1.7050417e+09 | I90: =H89*$B$6/12 -> 12157361 | J90: =SUM(G90,I90) -> 23449028
F91: June | G91: =$B$4/(20*12) -> 11291667 | H91: =H90-G91 -> 1.69375e+09 | I91: =H90*$B$6/12 -> 12077378 | J91: =SUM(G91,I91) -> 23369045
F92: July | G92: =$B$4/(20*12) -> 11291667 | H92: =H91-G92 -> 1.6824583e+09 | I92: =H91*$B$6/12 -> 11997396 | J92: =SUM(G92,I92) -> 23289063
F93: August | G93: =$B$4/(20*12) -> 11291667 | H93: =H92-G93 -> 1.6711667e+09 | I93: =H92*$B$6/12 -> 11917413 | J93: =SUM(G93,I93) -> 23209080
F94: September | G94: =$B$4/(20*12) -> 11291667 | H94: =H93-G94 -> 1.659875e+09 | I94: =H93*$B$6/12 -> 11837431 | J94: =SUM(G94,I94) -> 23129097
F95: October | G95: =$B$4/(20*12) -> 11291667 | H95: =H94-G95 -> 1.6485833e+09 | I95: =H94*$B$6/12 -> 11757448 | J95: =SUM(G95,I95) -> 23049115
F96: November | G96: =$B$4/(20*12) -> 11291667 | H96: =H95-G96 -> 1.6372917e+09 | I96: =H95*$B$6/12 -> 11677465 | J96: =SUM(G96,I96) -> 22969132
F97: December | G97: =$B$4/(20*12) -> 11291667 | H97: =H96-G97 -> 1.626e+09 | I97: =H96*$B$6/12 -> 11597483 | J97: =SUM(G97,I97) -> 22889149
E98: 2042 | F98: January | G98: =$B$4/(20*12) -> 11291667 | H98: =H97-G98 -> 1.6147083e+09 | I98: =H97*$B$6/12 -> 11517500 | J98: =SUM(G98,I98) -> 22809167 | K98: =SUM(J98:J109) -> 2.6843115e+08
F99: February | G99: =$B$4/(20*12) -> 11291667 | H99: =H98-G99 -> 1.6034167e+09 | I99: =H98*$B$6/12 -> 11437517 | J99: =SUM(G99,I99) -> 22729184
F100: March | G100: =$B$4/(20*12) -> 11291667 | H100: =H99-G100 -> 1.592125e+09 | I100: =H99*$B$6/12 -> 11357535 | J100: =SUM(G100,I100) -> 22649201
...

Sheet 2. Budgeting Statement
A1: TIMELINE
A2: Year | B2: 2025 | C2: 2026 | D2: 2027 | E2: 2028 | F2: 2029 | G2: 2030 | H2: 2031 | I2: 2032 | J2: 2033 | K2: 2034 | L2: 2035 | M2: 2036 | N2: 2037 | O2: 2038 | P2: 2039 | Q2: 2040 | R2: 2041 | S2: 2042 | T2: 2043 | U2: 2044 | V2: 2045 | W2: 2046 | X2: 2047 | Y2: 2048 | Z2: 2049 | AA2: 2050 | AB2: 2051 | AC2: 2052 | AD2: 2053 | AE2: 2054 | AF2: 2055 | AG2: 2056 | AH2: 2057 | AI2: 2058 | AJ2: 2059 | AK2: 2060 | AL2: 2061 | AM2: 2062 | AN2: 2063 | AO2: 2064 | AP2: 2065 | AQ2: 2066 | AR2: 2067 | AS2: 2068 | AT2: 2069 | AU2: 2070 | AV2: 2071 | AW2: 2072 | AX2: 2073 | AY2: 2074 | AZ2: 2075 | BA2: 2076 | BB2: 2077 | BC2: 2078 | BD2: 2079 | BE2: 2080 | BF2: 2081 | BG2: 2082 | BH2: 2083 | BI2: 2084 | BJ2: 2085 | BK2: 2086 | BL2: 2087 | BM2: 2088
A3: Age | B3: 22 | C3: 23 | D3: 24 | E3: 25 | F3: 26 | G3: 27 | H3: 28 | I3: 29 | J3: 30 | K3: 31 | L3: 32 | M3: 33 | N3: 34 | O3: 35 | P3: 36 | Q3: 37 | R3: 38 | S3: 39 | T3: 40 | U3: 41 | V3: 42 | W3: 43 | X3: 44 | Y3: 45 | Z3: 46 | AA3: 47 | AB3: 48 | AC3: 49 | AD3: 50 | AE3: 51 | AF3: 52 | AG3: 53 | AH3: 54 | AI3: 55 | AJ3: 56 | AK3: 57 | AL3: 58 | AM3: 59 | AN3: 60 | AO3: 61 | AP3: 62 | AQ3: 63 | AR3: 64 | AS3: 65 | AT3: 66 | AU3: 67 | AV3: 68 | AW3: 69 | AX3: 70 | AY3: 71 | AZ3: 72 | BA3: 73 | BB3: 74 | BC3: 75 | BD3: 76 | BE3: 77 | BF3: 78 | BG3: 79 | BH3: 80 | BI3: 81 | BJ3: 82 | BK3: 83 | BL3: 84 | BM3: 85
A4: Event | H4: Buy car | J4: Nhi's 6 months of maternity leave Buy apartment | K4: Child is born | AC4: Child goes to university | AF4: Child is independent (when year ends) | AN4: Nhi retires (when year ends) | AP4: Husband retires (when year ends) | AY4: Trash car Go travel around the world | BM4: Nhi and Husband die (when year ends)
A5: Inflation Rate | B5: ='1. Drivers'!B17 -> 0.0295 | C5: ='1. Drivers'!B18 -> 0.0249 | D5: ='1. Drivers'!B19 -> 0.028 | E5: ='1. Drivers'!B20 -> 0.029 | F5: ='1. Drivers'!B21 -> 0.029 | G5: ='1. Drivers'!B22 -> 0.029 | H5: ='1. Drivers'!$B$23 -> 0.02881 | I5: ='1. Drivers'!$B$23 -> 0.02881 | J5: ='1. Drivers'!$B$23 -> 0.02881 | K5: ='1. Drivers'!$B$23 -> 0.02881 | L5: ='1. Drivers'!$B$23 -> 0.02881 | M5: ='1. Drivers'!$B$23 -> 0.02881 | N5: ='1. Drivers'!$B$23 -> 0.02881 | O5: ='1. Drivers'!$B$23 -> 0.02881 | ... BM5: ='1. Drivers'!$B$23 -> 0.02881
A7: BUDGETING STATEMENT
A8: Nhi's After-tax Income | B8: ='2. Human Capital & Pension Valu'!B16 -> 160975000 | C8: ='2. Human Capital & Pension Valu'!C16 -> 1.6481894e+08 | D8: ='2. Human Capital & Pension Valu'!D16 -> 2.6164498e+08 | E8: ='2. Human Capital & Pension Valu'!E16 -> 2.6839749e+08 | F8: ='2. Human Capital & Pension Valu'!F16 -> 2.7534581e+08 | G8: ='2. Human Capital & Pension Valu'!G16 -> 4.342051e+08 | H8: ='2. Human Capital & Pension Valu'!H16 -> 4.4538353e+08 | I8: ='2. Human Capital & Pension Valu'!I16 -> 4.56884e+08 | ... AN8: ='2. Human Capital & Pension Valu'!AN16 -> 1.7741248e+09
A9: Nhi's Pension | AO9: ='2. Human Capital & Pension Valu'!AO45 -> 6.878382e+08 | AP9: ='2. Human Capital & Pension Valu'!AP45 -> 6.878382e+08 | AQ9: ='2. Human Capital & Pension Valu'!AQ45 -> 6.878382e+08 | AR9: ='2. Human Capital & Pension Valu'!AR45 -> 6.878382e+08 | AS9: ='2. Human Capital & Pension Valu'!AS45 -> 6.878382e+08 | AT9: ='2. Human Capital & Pension Valu'!AT45 -> 6.878382e+08 | AU9: ='2. Human Capital & Pension Valu'!AU45 -> 6.878382e+08 | AV9: ='2. Human Capital & Pension Valu'!AV45 -> 6.878382e+08 | ... BM9: ='2. Human Capital & Pension Valu'!BM45 -> 6.878382e+08
A10: Husband's After-tax Income | B10: ='2. Human Capital & Pension Valu'!B30 -> 203400000 | C10: ='2. Human Capital & Pension Valu'!C30 -> 2.0806128e+08 | D10: ='2. Human Capital & Pension Valu'!D30 -> 2.134334e+08 | E10: ='2. Human Capital & Pension Valu'!E30 -> 4.5210633e+08 | F10: ='2. Human Capital & Pension Valu'!F30 -> 4.6357276e+08 | G10: ='2. Human Capital & Pension Valu'!G30 -> 4.7492837e+08 | H10: ='2. Human Capital & Pension Valu'!H30 -> 4.8653674e+08 | I10: ='2. Human Capital & Pension Valu'!I30 -> 4.9847954e+08 | ... AP10: ='2. Human Capital & Pension Valu'!AP30 -> 1.7371507e+09
A11: Husband's Pension | AQ11: ='2. Human Capital & Pension Valu'!AQ51 -> 7.5574597e+08 | AR11: ='2. Human Capital & Pension Valu'!AR51 -> 7.5574597e+08 | AS11: ='2. Human Capital & Pension Valu'!AS51 -> 7.5574597e+08 | AT11: ='2. Human Capital & Pension Valu'!AT51 -> 7.5574597e+08 | AU11: ='2. Human Capital & Pension Valu'!AU51 -> 7.5574597e+08 | AV11: ='2. Human Capital & Pension Valu'!AV51 -> 7.5574597e+08 | AW11: ='2. Human Capital & Pension Valu'!AW51 -> 7.5574597e+08 | AX11: ='2. Human Capital & Pension Valu'!AX51 -> 7.5574597e+08 | ... BM11: ='2. Human Capital & Pension Valu'!BM51 -> 7.5574597e+08
A12: Insurance Maturity | AK12: ='4. Life Insurance'!B62 -> 6.2666315e+09
A13: Investment Return | B13: ='3. Monte Carlo'!Q2 -> 6048829.3 | C13: ='3. Monte Carlo'!Q3 -> 1459729.5 | D13: {=TRANSPOSE('3. Monte Carlo'!Q4:Q65)} -> 6827565.1 | E13: 36093013 | F13: 1.14911e+08 | G13: 2.0969738e+08 | H13: -1.3311373e+08 | I13: 4.0157139e+08 | J13: -90064907 | K13: 81186098 | L13: -2.7317349e+08 | M13: -10364351 | N13: 2.9938754e+08 | O13: -2.0233137e+08 | P13: 2.9203319e+08 | Q13: 4.2996937e+08 | R13: 1.508429e+08 | S13: 4.1196347e+08 | T13: 1.5140155e+09 | U13: -2.6622111e+08 | V13: 1.6442178e+09 | W13: 4.7724198e+08 | X13: -5.4913868e+08 | Y13: 3.0223591e+09 | Z13: 2.6690543e+08 | AA13: -2.9869503e+08 | AB13: 4.7211299e+08 | AC13: -2.8613582e+08 | AD13: 1.9146664e+09 | AE13: 3.562327e+09 | AF13: 2.8457704e+09 | AG13: 8.682252e+09 | AH13: 5.4893144e+09 | AI13: 1.3408722e+10 | AJ13: 9.231761e+09 | AK13: 3.3858777e+09 | AL13: 5.4234958e+08 | AM13: -5.8006103e+09 | AN13: 4.2926281e+09 | AO13: 1.4278996e+10 | AP13: -2.8280205e+09 | AQ13: -6.8604593e+09 | AR13: -4.340677e+09 | AS13: 5.7373436e+10 | AT13: -3.7038996e+09 | AU13: -4.090534e+10 | AV13: 1.1476828e+10 | AW13: 3.5495726e+09 | AX13: 3.946684e+10 | AY13: 3.7064601e+10 | AZ13: 2.2290567e+10 | BA13: 3.0763827e+10 | BB13: -4.6748124e+10 | BC13: 5.6936702e+10 | BD13: -2.0569844e+10 | BE13: 6.4690648e+10 | BF13: 6.4789079e+10 | BG13: -8.8538938e+09 | BH13: 8.782966e+09 | BI13: -8.5842277e+10 | BJ13: -1.8942583e+10 | BK13: -6.1482845e+10 | BL13: -3.7411352e+09 | BM13: 5.5419414e+10
A14: Total Income | B14: =SUM(B8:B13) -> 3.7042383e+08 | C14: =SUM(C8:C13) -> 3.7433995e+08 | D14: =SUM(D8:D13) -> 4.8190594e+08 | E14: =SUM(E8:E13) -> 7.5659683e+08 | F14: =SUM(F8:F13) -> 8.5382957e+08 | G14: =SUM(G8:G13) -> 1.1188308e+09 | H14: =SUM(H8:H13) -> 7.9880654e+08 | I14: =SUM(I8:I13) -> 1.3569349e+09 | ... BM14: =SUM(BM8:BM13) -> 5.6862998e+10
A15: Total Expenses | B15: ='2. Consumption Needs'!B20 -> 3.2846829e+08 | C15: ='2. Consumption Needs'!C20 -> 3.3664715e+08 | D15: ='2. Consumption Needs'!D20 -> 3.4607328e+08 | E15: ='2. Consumption Needs'!E20 -> 3.561094e+08 | F15: ='2. Consumption Needs'!F20 -> 3.6643657e+08 | G15: ='2. Consumption Needs'!G20 -> 3.7706323e+08 | H15: ='2. Consumption Needs'!H20 -> 9.5972918e+08 | I15: ='2. Consumption Needs'!I20 -> 4.5397579e+08 | ... BM15: ='2. Consumption Needs'!BM20 -> 1.6357017e+09
A16: ANNUAL SURPLUS/DEFICIT | B16: =B14-B15 -> 41955535 | C16: =C14-C15 -> 37692792 | D16: =D14-D15 -> 1.3583267e+08 | E16: =E14-E15 -> 4.0048743e+08 | F16: =F14-F15 -> 4.87393e+08 | G16: =G14-G15 -> 7.4176761e+08 | H16: =H14-H15 -> -1.6092265e+08 | I16: =I14-I15 -> 9.0295914e+08 | ... BM16: =BM14-BM15 -> 5.5227296e+10
A17: TOTAL ACCOUNT BALANCE | B17: =B16 -> 41955535 | C17: =B17+C16 -> 79648327 | D17: =C17+D16 -> 2.1548099e+08 | E17: =D17+E16 -> 6.1596842e+08 | F17: =E17+F16 -> 1.1033614e+09 | G17: =F17+G16 -> 1.845129e+09 | H17: =G17+H16 -> 1.6842064e+09 | I17: =H17+I16 -> 2.5871655e+09 | J17: =I17+J16 -> 1.6440168e+09 | ... BM17: =BL17+BM16 -> 2.6724129e+11

Sheet 3. Funding Allocation
A1: TIMELINE | E1: ASSET ALLOCATION | I1: FUNDING ALLOCATION
A3: Year | B3: Age | C3: Events | E3: Savings Account | F3: Bond | G3: Stock | I3: Annual Income | J3: Annual Expense | K3: Surplus/Deficit | L3: Beginning Emerency Fund | M3: Desired Emergeny Fund | N3: Addition in Emergency Fund | O3: Drawdown from Emergency Fund | P3: Surplus/Deficit after Emergency Fund | Q3: Beginning Savings Account | R3: Addition in Savings Account | S3: Drawdown from Savings Account | T3: Surplus/Deficit after Savings Account | U3: Beginning Investment Account | V3: Addition in Investment Account | W3: Drawdown from Investment Account | X3: Surplus/Deficit left
A4: 2025 | B4: 22 | C4: {=TRANSPOSE('2. Budgeting Statement'!B4:BM4)} -> 0 | E4: 0.2 | F4: 0.4 | G4: 0.4 | I4: {=TRANSPOSE('2. Budgeting Statement'!B14:BM14)} -> 3.7042383e+08 | J4: {=TRANSPOSE('2. Budgeting Statement'!B15:BM15)} -> 3.2846829e+08 | K4: =I4-J4 -> 41955535 | L4: 0 | M4: =CEILING(J4/12*3,1) -> 82117074 | N4: =IF(K4>0,IF(AND(K4>M4,M4>L4),M4-L4,IF(AND(K4<M4,M4>L4),K4,0)),0) -> 41955535 | O4: =IF(K4<0,IF(L4>-K4,K4,-L4),0) -> 0 | P4: =IF(K4>0,K4-N4,K4-O4) -> 0 | Q4: ='2. Balance Sheet & Cashflow Sta'!B5 -> 60000000 | R4: =IF(P4<0,0,P4*E4) -> 0 | S4: =IF(P4<0,IF(Q4>-P4,P4,-Q4),0) -> 0 | T4: =IF(P4>0,P4-R4,P4-S4) -> 0 | U4: 0 | V4: =IF(T4<0,0,T4) -> 0 | W4: =IF(T4<0,IF(U4>-T4,T4,-U4),0) -> 0 | X4: =IF(T4>0,T4-V4,T4-W4) -> 0
A5: 2026 | B5: 23 | C5: 0 | E5: 0.2 | F5: 0.4 | G5: 0.4 | I5: 3.7433995e+08 | J5: 3.3664715e+08 | K5: =I5-J5 -> 37692792 | L5: =SUM(L4,N4:O4) -> 41955535 | M5: =CEILING(J5/12*3,1) -> 84161789 | N5: =IF(K5>0,IF(AND(K5>M5,M5>L5),M5-L5,IF(AND(K5<M5,M5>L5),K5,0)),0) -> 37692792 | O5: =IF(K5<0,IF(L5>-K5,K5,-L5),0) -> 0 | P5: =IF(K5>0,K5-N5,K5-O5) -> 0 | Q5: =SUM(Q4:S4) -> 60000000 | R5: =IF(P5<0,0,P5*E5) -> 0 | S5: =IF(P5<0,IF(Q5>-P5,P5,-Q5),0) -> 0 | T5: =IF(P5>0,P5-R5,P5-S5) -> 0 | U5: =SUM(U4:W4) -> 0 | V5: =IF(T5<0,0,T5) -> 0 | W5: =IF(T5<0,IF(U5>-T5,T5,-U5),0) -> 0 | X5: =IF(T5>0,T5-V5,T5-W5) -> 0
A6: 2027 | B6: 24 | C6: 0 | E6: 0.2 | F6: 0.4 | G6: 0.4 | I6: 4.8190594e+08 | J6: 3.4607328e+08 | K6: =I6-J6 -> 1.3583267e+08 | L6: =SUM(L5,N5:O5) -> 79648327 | M6: =CEILING(J6/12*3,1) -> 86518319 | N6: =IF(K6>0,IF(AND(K6>M6,M6>L6),M6-L6,IF(AND(K6<M6,M6>L6),K6,0)),0) -> 6869991.8 | O6: =IF(K6<0,IF(L6>-K6,K6,-L6),0) -> 0 | P6: =IF(K6>0,K6-N6,K6-O6) -> 1.2896268e+08 | Q6: =SUM(Q5:S5) -> 60000000 | R6: =IF(P6<0,0,P6*E6) -> 25792535 | S6: =IF(P6<0,IF(Q6>-P6,P6,-Q6),0) -> 0 | T6: =IF(P6>0,P6-R6,P6-S6) -> 1.0317014e+08 | U6: =SUM(U5:W5) -> 0 | V6: =IF(T6<0,0,T6) -> 1.0317014e+08 | W6: =IF(T6<0,IF(U6>-T6,T6,-U6),0) -> 0 | X6: =IF(T6>0,T6-V6,T6-W6) -> 0
A7: 2028 | B7: 25 | C7: 0 | E7: 0.2 | F7: 0.4 | G7: 0.4 | I7: 7.5659683e+08 | J7: 3.561094e+08 | K7: =I7-J7 -> 4.0048743e+08 | L7: =SUM(L6,N6:O6) -> 86518319 | M7: =CEILING(J7/12*3,1) -> 89027351 | N7: =IF(K7>0,IF(AND(K7>M7,M7>L7),M7-L7,IF(AND(K7<M7,M7>L7),K7,0)),0) -> 2509032 | O7: =IF(K7<0,IF(L7>-K7,K7,-L7),0) -> 0 | P7: =IF(K7>0,K7-N7,K7-O7) -> 3.979784e+08 | Q7: =SUM(Q6:S6) -> 85792535 | R7: =IF(P7<0,0,P7*E7) -> 79595679 | S7: =IF(P7<0,IF(Q7>-P7,P7,-Q7),0) -> 0 | T7: =IF(P7>0,P7-R7,P7-S7) -> 3.1838272e+08 | U7: =SUM(U6:W6) -> 1.0317014e+08 | V7: =IF(T7<0,0,T7) -> 3.1838272e+08 | W7: =IF(T7<0,IF(U7>-T7,T7,-U7),0) -> 0 | X7: =IF(T7>0,T7-V7,T7-W7) -> 0
A8: 2029 | B8: 26 | C8: 0 | E8: 0.2 | F8: 0.4 | G8: 0.4 | I8: 8.5382957e+08 | J8: 3.6643657e+08 | K8: =I8-J8 -> 4.87393e+08 | L8: =SUM(L7,N7:O7) -> 89027351 | M8: =CEILING(J8/12*3,1) -> 91609144 | N8: =IF(K8>0,IF(AND(K8>M8,M8>L8),M8-L8,IF(AND(K8<M8,M8>L8),K8,0)),0) -> 2581793 | O8: =IF(K8<0,IF(L8>-K8,K8,-L8),0) -> 0 | P8: =IF(K8>0,K8-N8,K8-O8) -> 4.848112e+08 | Q8: =SUM(Q7:S7) -> 1.6538821e+08 | R8: =IF(P8<0,0,P8*E8) -> 96962241 | S8: =IF(P8<0,IF(Q8>-P8,P8,-Q8),0) -> 0 | T8: =IF(P8>0,P8-R8,P8-S8) -> 3.8784896e+08 | U8: =SUM(U7:W7) -> 4.2155286e+08 | V8: =IF(T8<0,0,T8) -> 3.8784896e+08 | W8: =IF(T8<0,IF(U8>-T8,T8,-U8),0) -> 0 | X8: =IF(T8>0,T8-V8,T8-W8) -> 0
A9: 2030 | B9: 27 | C9: 0 | E9: 0.2 | F9: 0.4 | G9: 0.4 | I9: 1.1188308e+09 | J9: 3.7706323e+08 | K9: =I9-J9 -> 7.4176761e+08 | L9: =SUM(L8,N8:O8) -> 91609144 | M9: =CEILING(J9/12*3,1) -> 94265809 | N9: =IF(K9>0,IF(AND(K9>M9,M9>L9),M9-L9,IF(AND(K9<M9,M9>L9),K9,0)),0) -> 2656665 | O9: =IF(K9<0,IF(L9>-K9,K9,-L9),0) -> 0 | P9: =IF(K9>0,K9-N9,K9-O9) -> 7.3911095e+08 | Q9: =SUM(Q8:S8) -> 2.6235045e+08 | R9: =IF(P9<0,0,P9*E9) -> 1.4782219e+08 | S9: =IF(P9<0,IF(Q9>-P9,P9,-Q9),0) -> 0 | T9: =IF(P9>0,P9-R9,P9-S9) -> 5.9128876e+08 | U9: =SUM(U8:W8) -> 8.0940182e+08 | V9: =IF(T9<0,0,T9) -> 5.9128876e+08 | W9: =IF(T9<0,IF(U9>-T9,T9,-U9),0) -> 0 | X9: =IF(T9>0,T9-V9,T9-W9) -> 0
A10: 2031 | B10: 28 | C10: Buy car | E10: 0.2 | F10: 0.4 | G10: 0.4 | I10: 7.9880654e+08 | J10: 9.5972918e+08 | K10: =I10-J10 -> -1.6092265e+08 | L10: =SUM(L9,N9:O9) -> 94265809 | M10: =CEILING(J10/12*3,1) -> 239932296 | N10: =IF(K10>0,IF(AND(K10>M10,M10>L10),M10-L10,IF(AND(K10<M10,M10>L10),K10,0)),0) -> 0 | O10: =IF(K10<0,IF(L10>-K10,K10,-L10),0) -> -94265809 | P10: =IF(K10>0,K10-N10,K10-O10) -> -66656838 | Q10: =SUM(Q9:S9) -> 4.1017264e+08 | R10: =IF(P10<0,0,P10*E10) -> 0 | S10: =IF(P10<0,IF(Q10>-P10,P10,-Q10),0) -> -66656838 | T10: =IF(P10>0,P10-R10,P10-S10) -> 0 | U10: =SUM(U9:W9) -> 1.4006906e+09 | V10: =IF(T10<0,0,T10) -> 0 | W10: =IF(T10<0,IF(U10>-T10,T10,-U10),0) -> 0 | X10: =IF(T10>0,T10-V10,T10-W10) -> 0
A11: 2032 | B11: 29 | C11: 0 | E11: 0.2 | F11: 0.4 | G11: 0.4 | I11: 1.3569349e+09 | J11: 4.5397579e+08 | K11: =I11-J11 -> 9.0295914e+08 | L11: =SUM(L10,N10:O10) -> 0 | M11: =CEILING(J11/12*3,1) -> 113493949 | N11: =IF(K11>0,IF(AND(K11>M11,M11>L11),M11-L11,IF(AND(K11<M11,M11>L11),K11,0)),0) -> 113493949 | O11: =IF(K11<0,IF(L11>-K11,K11,-L11),0) -> 0 | P11: =IF(K11>0,K11-N11,K11-O11) -> 7.894652e+08 | Q11: =SUM(Q10:S10) -> 3.4351581e+08 | R11: =IF(P11<0,0,P11*E11) -> 1.5789304e+08 | S11: =IF(P11<0,IF(Q11>-P11,P11,-Q11),0) -> 0 | T11: =IF(P11>0,P11-R11,P11-S11) -> 6.3157216e+08 | U11: =SUM(U10:W10) -> 1.4006906e+09 | V11: =IF(T11<0,0,T11) -> 6.3157216e+08 | W11: =IF(T11<0,IF(U11>-T11,T11,-U11),0) -> 0 | X11: =IF(T11>0,T11-V11,T11-W11) -> 0
A12: 2033 | B12: 30 | C12: Nhi's 6 months of maternity leave Buy apartment | E12: 0.2 | F12: 0.4 | G12: 0.4 | I12: 7.2941245e+08 | J12: 1.6725612e+09 | K12: =I12-J12 -> -9.431487e+08 | L12: =SUM(L11,N11:O11) -> 113493949 | M12: =CEILING(J12/12*3,1) -> 418140290 | N12: =IF(K12>0,IF(AND(K12>M12,M12>L12),M12-L12,IF(AND(K12<M12,M12>L12),K12,0)),0) -> 0 | O12: =IF(K12<0,IF(L12>-K12,K12,-L12),0) -> -113493949 | P12: =IF(K12>0,K12-N12,K12-O12) -> -8.2965475e+08 | Q12: =SUM(Q11:S11) -> 5.0140885e+08 | R12: =IF(P12<0,0,P12*E12) -> 0 | S12: =IF(P12<0,IF(Q12>-P12,P12,-Q12),0) -> -5.0140885e+08 | T12: =IF(P12>0,P12-R12,P12-S12) -> -3.2824591e+08 | U12: =SUM(U11:W11) -> 2.0322627e+09 | V12: =IF(T12<0,0,T12) -> 0 | W12: =IF(T12<0,IF(U12>-T12,T12,-U12),0) -> -3.2824591e+08 | X12: =IF(T12>0,T12-V12,T12-W12) -> 0
A13: 2034 | B13: 31 | C13: Child is born | E13: 0.2 | F13: 0.4 | G13: 0.4 | I13: 1.1725484e+09 | J13: 9.1225701e+08 | K13: =I13-J13 -> 2.6029137e+08 | L13: =SUM(L12,N12:O12) -> 0 | M13: =CEILING(J13/12*3,1) -> 228064252 | N13: =IF(K13>0,IF(AND(K13>M13,M13>L13),M13-L13,IF(AND(K13<M13,M13>L13),K13,0)),0) -> 228064252 | O13: =IF(K13<0,IF(L13>-K13,K13,-L13),0) -> 0 | P13: =IF(K13>0,K13-N13,K13-O13) -> 32227122 | Q13: =SUM(Q12:S12) -> 0 | R13: =IF(P13<0,0,P13*E13) -> 6445424.3 | S13: =IF(P13<0,IF(Q13>-P13,P13,-Q13),0) -> 0 | T13: =IF(P13>0,P13-R13,P13-S13) -> 25781697 | U13: =SUM(U12:W12) -> 1.7040168e+09 | V13: =IF(T13<0,0,T13) -> 25781697 | W13: =IF(T13<0,IF(U13>-T13,T13,-U13),0) -> 0 | X13: =IF(T13>0,T13-V13,T13-W13) -> 0
A14: 2035 | B14: 32 | C14: 0 | E14: 0.2 | F14: 0.4 | G14: 0.4 | I14: 8.45102e+08 | J14: 8.034447e+08 | K14: =I14-J14 -> 41657303 | L14: =SUM(L13,N13:O13) -> 228064252 | M14: =CEILING(J14/12*3,1) -> 200861176 | N14: =IF(K14>0,IF(AND(K14>M14,M14>L14),M14-L14,IF(AND(K14<M14,M14>L14),K14,0)),0) -> 0 | O14: =IF(K14<0,IF(L14>-K14,K14,-L14),0) -> 0 | P14: =IF(K14>0,K14-N14,K14-O14) -> 41657303 | Q14: =SUM(Q13:S13) -> 6445424.3 | R14: =IF(P14<0,0,P14*E14) -> 8331460.6 | S14: =IF(P14<0,IF(Q14>-P14,P14,-Q14),0) -> 0 | T14: =IF(P14>0,P14-R14,P14-S14) -> 33325842 | U14: =SUM(U13:W13) -> 1.7297985e+09 | V14: =IF(T14<0,0,T14) -> 33325842 | W14: =IF(T14<0,IF(U14>-T14,T14,-U14),0) -> 0 | X14: =IF(T14>0,T14-V14,T14-W14) -> 0
A15: 2036 | B15: 33 | C15: 0 | E15: 0.2 | F15: 0.4 | G15: 0.4 | I15: 1.1355997e+09 | J15: 8.1002913e+08 | K15: =I15-J15 -> 3.255706e+08 | L15: =SUM(L14,N14:O14) -> 228064252 | M15: =CEILING(J15/12*3,1) -> 202507282 | N15: =IF(K15>0,IF(AND(K15>M15,M15>L15),M15-L15,IF(AND(K15<M15,M15>L15),K15,0)),0) -> 0 | O15: =IF(K15<0,IF(L15>-K15,K15,-L15),0) -> 0 | P15: =IF(K15>0,K15-N15,K15-O15) -> 3.255706e+08 | Q15: =SUM(Q14:S14) -> 14776885 | R15: =IF(P15<0,0,P15*E15) -> 65114121 | S15: =IF(P15<0,IF(Q15>-P15,P15,-Q15),0) -> 0 | T15: =IF(P15>0,P15-R15,P15-S15) -> 2.6045648e+08 | U15: =SUM(U14:W14) -> 1.7631244e+09 | V15: =IF(T15<0,0,T15) -> 2.6045648e+08 | W15: =IF(T15<0,IF(U15>-T15,T15,-U15),0) -> 0 | X15: =IF(T15>0,T15-V15,T15-W15) -> 0
A16: 2037 | B16: 34 | C16: 0 | E16: 0.1 | F16: 0.3 | G16: 0.6 | I16: 1.4738379e+09 | J16: 8.5693982e+08 | K16: =I16-J16 -> 6.1689809e+08 | L16: =SUM(L15,N15:O15) -> 228064252 | M16: =CEILING(J16/12*3,1) -> 214234956 | N16: =IF(K16>0,IF(AND(K16>M16,M16>L16),M16-L16,IF(AND(K16<M16,M16>L16),K16,0)),0) -> 0 | O16: =IF(K16<0,IF(L16>-K16,K16,-L16),0) -> 0 | P16: =IF(K16>0,K16-N16,K16-O16) -> 6.1689809e+08 | Q16: =SUM(Q15:S15) -> 79891006 | R16: =IF(P16<0,0,P16*E16) -> 61689809 | S16: =IF(P16<0,IF(Q16>-P16,P16,-Q16),0) -> 0 | T16: =IF(P16>0,P16-R16,P16-S16) -> 5.5520828e+08 | U16: =SUM(U15:W15) -> 2.0235808e+09 | V16: =IF(T16<0,0,T16) -> 5.5520828e+08 | W16: =IF(T16<0,IF(U16>-T16,T16,-U16),0) -> 0 | X16: =IF(T16>0,T16-V16,T16-W16) -> 0
A17: 2038 | B17: 35 | C17: 0 | E17: 0.1 | F17: 0.3 | G17: 0.6 | I17: 1.1399015e+09 | J17: 8.6046656e+08 | K17: =I17-J17 -> 2.7943498e+08 | L17: =SUM(L16,N16:O16) -> 228064252 | M17: =CEILING(J17/12*3,1) -> 215116639 | N17: =IF(K17>0,IF(AND(K17>M17,M17>L17),M17-L17,IF(AND(K17<M17,M17>L17),K17,0)),0) -> 0 | O17: =IF(K17<0,IF(L17>-K17,K17,-L17),0) -> 0 | P17: =IF(K17>0,K17-N17,K17-O17) -> 2.7943498e+08 | Q17: =SUM(Q16:S16) -> 1.4158082e+08 | R17: =IF(P17<0,0,P17*E17) -> 27943498 | S17: =IF(P17<0,IF(Q17>-P17,P17,-Q17),0) -> 0 | T17: =IF(P17>0,P17-R17,P17-S17) -> 2.5149148e+08 | U17: =SUM(U16:W16) -> 2.5787891e+09 | V17: =IF(T17<0,0,T17) -> 2.5149148e+08 | W17: =IF(T17<0,IF(U17>-T17,T17,-U17),0) -> 0 | X17: =IF(T17>0,T17-V17,T17-W17) -> 0
A18: 2039 | B18: 36 | C18: 0 | E18: 0.1 | F18: 0.3 | G18: 0.6 | I18: 1.667291e+09 | J18: 8.6442671e+08 | K18: =I18-J18 -> 8.0286425e+08 | L18: =SUM(L17,N17:O17) -> 228064252 | M18: =CEILING(J18/12*3,1) -> 216106679 | N18: =IF(K18>0,IF(AND(K18>M18,M18>L18),M18-L18,IF(AND(K18<M18,M18>L18),K18,0)),0) -> 0 | O18: =IF(K18<0,IF(L18>-K18,K18,-L18),0) -> 0 | P18: =IF(K18>0,K18-N18,K18-O18) -> 8.0286425e+08 | Q18: =SUM(Q17:S17) -> 1.6952431e+08 | R18: =IF(P18<0,0,P18*E18) -> 80286425 | S18: =IF(P18<0,IF(Q18>-P18,P18,-Q18),0) -> 0 | T18: =IF(P18>0,P18-R18,P18-S18) -> 7.2257783e+08 | U18: =SUM(U17:W17) -> 2.8302806e+09 | V18: =IF(T18<0,0,T18) -> 7.2257783e+08 | W18: =IF(T18<0,IF(U18>-T18,T18,-U18),0) -> 0 | X18: =IF(T18>0,T18-V18,T18-W18) -> 0
A19: 2040 | B19: 37 | C19: 0 | E19: 0.1 | F19: 0.3 | G19: 0.6 | I19: 2.0856265e+09 | J19: 8.2964004e+08 | K19: =I19-J19 -> 1.2559864e+09 | L19: =SUM(L18,N18:O18) -> 228064252 | M19: =CEILING(J19/12*3,1) -> 207410011 | N19: =IF(K19>0,IF(AND(K19>M19,M19>L19),M19-L19,IF(AND(K19<M19,M19>L19),K19,0)),0) -> 0 | O19: =IF(K19<0,IF(L19>-K19,K19,-L19),0) -> 0 | P19: =IF(K19>0,K19-N19,K19-O19) -> 1.2559864e+09 | Q19: =SUM(Q18:S18) -> 2.4981074e+08 | R19: =IF(P19<0,0,P19*E19) -> 1.2559864e+08 | S19: =IF(P19<0,IF(Q19>-P19,P19,-Q19),0) -> 0 | T19: =IF(P19>0,P19-R19,P19-S19) -> 1.1303878e+09 | U19: =SUM(U18:W18) -> 3.5528584e+09 | V19: =IF(T19<0,0,T19) -> 1.1303878e+09 | W19: =IF(T19<0,IF(U19>-T19,T19,-U19),0) -> 0 | X19: =IF(T19>0,T19-V19,T19-W19) -> 0
A20: 2041 | B20: 38 | C20: 0 | E20: 0.1 | F20: 0.3 | G20: 0.6 | I20: 1.8457674e+09 | J20: 8.3244027e+08 | K20: =I20-J20 -> 1.0133271e+09 | L20: =SUM(L19,N19:O19) -> 228064252 | M20: =CEILING(J20/12*3,1) -> 208110067 | N20: =IF(K20>0,IF(AND(K20>M20,M20>L20),M20-L20,IF(AND(K20<M20,M20>L20),K20,0)),0) -> 0 | O20: =IF(K20<0,IF(L20>-K20,K20,-L20),0) -> 0 | P20: =IF(K20>0,K20-N20,K20-O20) -> 1.0133271e+09 | Q20: =SUM(Q19:S19) -> 3.7540938e+08 | R20: =IF(P20<0,0,P20*E20) -> 1.0133271e+08 | S20: =IF(P20<0,IF(Q20>-P20,P20,-Q20),0) -> 0 | T20: =IF(P20>0,P20-R20,P20-S20) -> 9.1199438e+08 | U20: =SUM(U19:W19) -> 4.6832462e+09 | V20: =IF(T20<0,0,T20) -> 9.1199438e+08 | W20: =IF(T20<0,IF(U20>-T20,T20,-U20),0) -> 0 | X20: =IF(T20>0,T20-V20,T20-W20) -> 0
A21: 2042 | B21: 39 | C21: 0 | E21: 0.1 | F21: 0.3 | G21: 0.6 | I21: 2.1472866e+09 | J21: 8.3658844e+08 | K21: =I21-J21 -> 1.3106981e+09 | L21: =SUM(L20,N20:O20) -> 228064252 | M21: =CEILING(J21/12*3,1) -> 209147112 | N21: =IF(K21>0,IF(AND(K21>M21,M21>L21),M21-L21,IF(AND(K21<M21,M21>L21),K21,0)),0) -> 0 | O21: =IF(K21<0,IF(L21>-K21,K21,-L21),0) -> 0 | P21: =IF(K21>0,K21-N21,K21-O21) -> 1.3106981e+09 | Q21: =SUM(Q20:S20) -> 4.7674209e+08 | R21: =IF(P21<0,0,P21*E21) -> 1.3106981e+08 | S21: =IF(P21<0,IF(Q21>-P21,P21,-Q21),0) -> 0 | T21: =IF(P21>0,P21-R21,P21-S21) -> 1.1796283e+09 | U21: =SUM(U20:W20) -> 5.5952406e+09 | V21: =IF(T21<0,0,T21) -> 1.1796283e+09 | W21: =IF(T21<0,IF(U21>-T21,T21,-U21),0) -> 0 | X21: =IF(T21>0,T21-V21,T21-W21) -> 0
A22: 2043 | B22: 40 | C22: 0 | E22: 0.1 | F22: 0.3 | G22: 0.6 | I22: 3.2909012e+09 | J22: 8.4118795e+08 | K22: =I22-J22 -> 2.4497133e+09 | L22: =SUM(L21,N21:O21) -> 228064252 | M22: =CEILING(J22/12*3,1) -> 210296988 | N22: =IF(K22>0,IF(AND(K22>M22,M22>L22),M22-L22,IF(AND(K22<M22,M22>L22),K22,0)),0) -> 0 | O22: =IF(K22<0,IF(L22>-K22,K22,-L22),0) -> 0 | P22: =IF(K22>0,K22-N22,K22-O22) -> 2.4497133e+09 | Q22: =SUM(Q21:S21) -> 6.078119e+08 | R22: =IF(P22<0,0,P22*E22) -> 2.4497133e+08 | S22: =IF(P22<0,IF(Q22>-P22,P22,-Q22),0) -> 0 | T22: =IF(P22>0,P22-R22,P22-S22) -> 2.2047419e+09 | U22: =SUM(U21:W21) -> 6.7748689e+09 | V22: =IF(T22<0,0,T22) -> 2.2047419e+09 | W22: =IF(T22<0,IF(U22>-T22,T22,-U22),0) -> 0 | X22: =IF(T22>0,T22-V22,T22-W22) -> 0
A23: 2044 | B23: 41 | C23: 0 | E23: 0.1 | F23: 0.3 | G23: 0.6 | I23: 1.5534245e+09 | J23: 8.4645741e+08 | K23: =I23-J23 -> 7.0696712e+08 | L23: =SUM(L22,N22:O22) -> 228064252 | M23: =CEILING(J23/12*3,1) -> 211614352 | N23: =IF(K23>0,IF(AND(K23>M23,M23>L23),M23-L23,IF(AND(K23<M23,M23>L23),K23,0)),0) -> 0 | O23: =IF(K23<0,IF(L23>-K23,K23,-L23),0) -> 0 | P23: =IF(K23>0,K23-N23,K23-O23) -> 7.0696712e+08 | Q23: =SUM(Q22:S22) -> 8.5278323e+08 | R23: =IF(P23<0,0,P23*E23) -> 70696712 | S23: =IF(P23<0,IF(Q23>-P23,P23,-Q23),0) -> 0 | T23: =IF(P23>0,P23-R23,P23-S23) -> 6.3627041e+08 | U23: =SUM(U22:W22) -> 8.9796109e+09 | V23: =IF(T23<0,0,T23) -> 6.3627041e+08 | W23: =IF(T23<0,IF(U23>-T23,T23,-U23),0) -> 0 | X23: =IF(T23>0,T23-V23,T23-W23) -> 0
A24: 2045 | B24: 42 | C24: 0 | E24: 0.1 | F24: 0.3 | G24: 0.6 | I24: 3.5078553e+09 | J24: 8.82677e+08 | K24: =I24-J24 -> 2.6251783e+09 | L24: =SUM(L23,N23:O23) -> 228064252 | M24: =CEILING(J24/12*3,1) -> 220669250 | N24: =IF(K24>0,IF(AND(K24>M24,M24>L24),M24-L24,IF(AND(K24<M24,M24>L24),K24,0)),0) -> 0 | O24: =IF(K24<0,IF(L24>-K24,K24,-L24),0) -> 0 | P24: =IF(K24>0,K24-N24,K24-O24) -> 2.6251783e+09 | Q24: =SUM(Q23:S23) -> 9.2347994e+08 | R24: =IF(P24<0,0,P24*E24) -> 2.6251783e+08 | S24: =IF(P24<0,IF(Q24>-P24,P24,-Q24),0) -> 0 | T24: =IF(P24>0,P24-R24,P24-S24) -> 2.3626605e+09 | U24: =SUM(U23:W23) -> 9.6158813e+09 | V24: =IF(T24<0,0,T24) -> 2.3626605e+09 | W24: =IF(T24<0,IF(U24>-T24,T24,-U24),0) -> 0 | X24: =IF(T24>0,T24-V24,T24-W24) -> 0
A25: 2046 | B25: 43 | C25: 0 | E25: 0.1 | F25: 0.3 | G25: 0.6 | I25: 2.3861388e+09 | J25: 8.8959977e+08 | K25: =I25-J25 -> 1.496539e+09 | L25: =SUM(L24,N24:O24) -> 228064252 | M25: =CEILING(J25/12*3,1) -> 222399944 | N25: =IF(K25>0,IF(AND(K25>M25,M25>L25),M25-L25,IF(AND(K25<M25,M25>L25),K25,0)),0) -> 0 | O25: =IF(K25<0,IF(L25>-K25,K25,-L25),0) -> 0 | P25: =IF(K25>0,K25-N25,K25-O25) -> 1.496539e+09 | Q25: =SUM(Q24:S24) -> 1.1859978e+09 | R25: =IF(P25<0,0,P25*E25) -> 1.496539e+08 | S25: =IF(P25<0,IF(Q25>-P25,P25,-Q25),0) -> 0 | T25: =IF(P25>0,P25-R25,P25-S25) -> 1.3468851e+09 | U25: =SUM(U24:W24) -> 1.1978542e+10 | V25: =IF(T25<0,0,T25) -> 1.3468851e+09 | W25: =IF(T25<0,IF(U25>-T25,T25,-U25),0) -> 0 | X25: =IF(T25>0,T25-V25,T25-W25) -> 0
... A30: 2051 | B30: 48 | C30: 0 | E30: 0.1 | F30: 0.3 | G30: 0.6 | I30: 3.0209309e+09 | J30: 9.4830133e+08 | K30: =I30-J30 -> 2.0726296e+09 | L30: =SUM(L29,N29:O29) -> 234530523 | M30: =CEILING(J30/12*3,1) -> 237075334 | N30: =IF(K30>0,IF(AND(K30>M30,M30>L30),M30-L30,IF(AND(K30<M30,M30>L30),K30,0)),0) -> 2544811 | O30: =IF(K30<0,IF(L30>-K30,K30,-L30),0) -> 0 | P30: =IF(K30>0,K30-N30,K30-O30) -> 2.0700848e+09 | Q30: =SUM(Q29:S29) -> 2.1361571e+09 | R30: =IF(P30<0,0,P30*E30) -> 2.0700848e+08 | S30: =IF(P30<0,IF(Q30>-P30,P30,-Q30),0) -> 0 | T30: =IF(P30>0,P30-R30,P30-S30) -> 1.8630763e+09 | U30: =SUM(U29:W29) -> 2.0529975e+10 | V30: =IF(T30<0,0,T30) -> 1.8630763e+09 | W30: =IF(T30<0,IF(U30>-T30,T30,-U30),0) -> 0 | X30: =IF(T30>0,T30-V30,T30-W30) -> 0
A31: 2052 | B31: 49 | C31: Child goes to university | E31: 0.1 | F31: 0.3 | G31: 0.6 | I31: 2.3076284e+09 | J31: 1.2173855e+09 | K31: =I31-J31 -> 1.0902429e+09 | L31: =SUM(L30,N30:O30) -> 237075334 | M31: =CEILING(J31/12*3,1) -> 304346386 | N31: =IF(K31>0,IF(AND(K31>M31,M31>L31),M31-L31,IF(AND(K31<M31,M31>L31),K31,0)),0) -> 67271052 | O31: =IF(K31<0,IF(L31>-K31,K31,-L31),0) -> 0 | P31: =IF(K31>0,K31-N31,K31-O31) -> 1.0229718e+09 | Q31: =SUM(Q30:S30) -> 2.3431655e+09 | R31: =IF(P31<0,0,P31*E31) -> 1.0229718e+08 | S31: =IF(P31<0,IF(Q31>-P31,P31,-Q31),0) -> 0 | T31: =IF(P31>0,P31-R31,P31-S31) -> 9.2067463e+08 | U31: =SUM(U30:W30) -> 2.2393052e+10 | V31: =IF(T31<0,0,T31) -> 9.2067463e+08 | W31: =IF(T31<0,IF(U31>-T31,T31,-U31),0) -> 0 | X31: =IF(T31>0,T31-V31,T31-W31) -> 0
A32: 2053 | B32: 50 | C32: 0 | E32: 0.1 | F32: 0.3 | G32: 0.6 | I32: 4.5736843e+09 | J32: 1.0966493e+09 | K32: =I32-J32 -> 3.477035e+09 | L32: =SUM(L31,N31:O31) -> 304346386 | M32: =CEILING(J32/12*3,1) -> 274162321 | N32: =IF(K32>0,IF(AND(K32>M32,M32>L32),M32-L32,IF(AND(K32<M32,M32>L32),K32,0)),0) -> 0 | O32: =IF(K32<0,IF(L32>-K32,K32,-L32),0) -> 0 | P32: =IF(K32>0,K32-N32,K32-O32) -> 3.477035e+09 | Q32: =SUM(Q31:S31) -> 2.4454627e+09 | R32: =IF(P32<0,0,P32*E32) -> 3.477035e+08 | S32: =IF(P32<0,IF(Q32>-P32,P32,-Q32),0) -> 0 | T32: =IF(P32>0,P32-R32,P32-S32) -> 3.1293315e+09 | U32: =SUM(U31:W31) -> 2.3313726e+10 | V32: =IF(T32<0,0,T32) -> 3.1293315e+09 | W32: =IF(T32<0,IF(U32>-T32,T32,-U32),0) -> 0 | X32: =IF(T32>0,T32-V32,T32-W32) -> 0
A33: 2054 | B33: 51 | C33: 0 | E33: 0.1 | F33: 0.3 | G33: 0.6 | I33: 6.2884785e+09 | J33: 9.8271632e+08 | K33: =I33-J33 -> 5.3057621e+09 | L33: =SUM(L32,N32:O32) -> 304346386 | M33: =CEILING(J33/12*3,1) -> 245679081 | N33: =IF(K33>0,IF(AND(K33>M33,M33>L33),M33-L33,IF(AND(K33<M33,M33>L33),K33,0)),0) -> 0 | O33: =IF(K33<0,IF(L33>-K33,K33,-L33),0) -> 0 | P33: =IF(K33>0,K33-N33,K33-O33) -> 5.3057621e+09 | Q33: =SUM(Q32:S32) -> 2.7931662e+09 | R33: =IF(P33<0,0,P33*E33) -> 5.3057621e+08 | S33: =IF(P33<0,IF(Q33>-P33,P33,-Q33),0) -> 0 | T33: =IF(P33>0,P33-R33,P33-S33) -> 4.7751859e+09 | U33: =SUM(U32:W32) -> 2.6443058e+10 | V33: =IF(T33<0,0,T33) -> 4.7751859e+09 | W33: =IF(T33<0,IF(U33>-T33,T33,-U33),0) -> 0 | X33: =IF(T33>0,T33-V33,T33-W33) -> 0
A34: 2055 | B34: 52 | C34: Child is independent (when year ends) | E34: 0.1 | F34: 0.3 | G34: 0.6 | I34: 5.6409895e+09 | J34: 1.0107768e+09 | K34: =I34-J34 -> 4.6302127e+09 | L34: =SUM(L33,N33:O33) -> 304346386 | M34: =CEILING(J34/12*3,1) -> 252694194 | N34: =IF(K34>0,IF(AND(K34>M34,M34>L34),M34-L34,IF(AND(K34<M34,M34>L34),K34,0)),0) -> 0 | O34: =IF(K34<0,IF(L34>-K34,K34,-L34),0) -> 0 | P34: =IF(K34>0,K34-N34,K34-O34) -> 4.6302127e+09 | Q34: =SUM(Q33:S33) -> 3.3237424e+09 | R34: =IF(P34<0,0,P34*E34) -> 4.6302127e+08 | S34: =IF(P34<0,IF(Q34>-P34,P34,-Q34),0) -> 0 | T34: =IF(P34>0,P34-R34,P34-S34) -> 4.1671914e+09 | U34: =SUM(U33:W33) -> 3.1218244e+10 | V34: =IF(T34<0,0,T34) -> 4.1671914e+09 | W34: =IF(T34<0,IF(U34>-T34,T34,-U34),0) -> 0 | X34: =IF(T34>0,T34-V34,T34-W34) -> 0
A35: 2056 | B35: 53 | C35: 0 | E35: 0.1 | F35: 0.3 | G35: 0.6 | I35: 1.1548529e+10 | J35: 1.1718821e+09 | K35: =I35-J35 -> 1.0376647e+10 | L35: =SUM(L34,N34:O34) -> 304346386 | M35: =CEILING(J35/12*3,1) -> 292970529 | N35: =IF(K35>0,IF(AND(K35>M35,M35>L35),M35-L35,IF(AND(K35<M35,M35>L35),K35,0)),0) -> 0 | O35: =IF(K35<0,IF(L35>-K35,K35,-L35),0) -> 0 | P35: =IF(K35>0,K35-N35,K35-O35) -> 1.0376647e+10 | Q35: =SUM(Q34:S34) -> 3.7867637e+09 | R35: =IF(P35<0,0,P35*E35) -> 1.0376647e+09 | S35: =IF(P35<0,IF(Q35>-P35,P35,-Q35),0) -> 0 | T35: =IF(P35>0,P35-R35,P35-S35) -> 9.3389819e+09 | U35: =SUM(U34:W34) -> 3.5385435e+10 | V35: =IF(T35<0,0,T35) -> 9.3389819e+09 | W35: =IF(T35<0,IF(U35>-T35,T35,-U35),0) -> 0 | X35: =IF(T35>0,T35-V35,T35-W35) -> 0
A36: 2057 | B36: 54 | C36: 0 | E36: 0.1 | F36: 0.3 | G36: 0.6 | I36: 8.4286958e+09 | J36: 8.022816e+08 | K36: =I36-J36 -> 7.6264142e+09 | L36: =SUM(L35,N35:O35) -> 304346386 | M36: =CEILING(J36/12*3,1) -> 200570400 | N36: =IF(K36>0,IF(AND(K36>M36,M36>L36),M36-L36,IF(AND(K36<M36,M36>L36),K36,0)),0) -> 0 | O36: =IF(K36<0,IF(L36>-K36,K36,-L36),0) -> 0 | P36: =IF(K36>0,K36-N36,K36-O36) -> 7.6264142e+09 | Q36: =SUM(Q35:S35) -> 4.8244284e+09 | R36: =IF(P36<0,0,P36*E36) -> 7.6264142e+08 | S36: =IF(P36<0,IF(Q36>-P36,P36,-Q36),0) -> 0 | T36: =IF(P36>0,P36-R36,P36-S36) -> 6.8637728e+09 | U36: =SUM(U35:W35) -> 4.4724417e+10 | V36: =IF(T36<0,0,T36) -> 6.8637728e+09 | W36: =IF(T36<0,IF(U36>-T36,T36,-U36),0) -> 0 | X36: =IF(T36>0,T36-V36,T36-W36) -> 0
A37: 2058 | B37: 55 | C37: 0 | E37: 0.1 | F37: 0.3 | G37: 0.6 | I37: 1.6423314e+10 | J37: 8.2514373e+08 | K37: =I37-J37 -> 1.559817e+10 | L37: =SUM(L36,N36:O36) -> 304346386 | M37: =CEILING(J37/12*3,1) -> 206285932 | N37: =IF(K37>0,IF(AND(K37>M37,M37>L37),M37-L37,IF(AND(K37<M37,M37>L37),K37,0)),0) -> 0 | O37: =IF(K37<0,IF(L37>-K37,K37,-L37),0) -> 0 | P37: =IF(K37>0,K37-N37,K37-O37) -> 1.559817e+10 | Q37: =SUM(Q36:S36) -> 5.5870698e+09 | R37: =IF(P37<0,0,P37*E37) -> 1.559817e+09 | S37: =IF(P37<0,IF(Q37>-P37,P37,-Q37),0) -> 0 | T37: =IF(P37>0,P37-R37,P37-S37) -> 1.4038353e+10 | U37: =SUM(U36:W36) -> 5.158819e+10 | V37: =IF(T37<0,0,T37) -> 1.4038353e+10 | W37: =IF(T37<0,IF(U37>-T37,T37,-U37),0) -> 0 | X37: =IF(T37>0,T37-V37,T37-W37) -> 0
A38: 2059 | B38: 56 | C38: 0 | E38: 0.1 | F38: 0.3 | G38: 0.6 | I38: 1.2323731e+10 | J38: 8.4866451e+08 | K38: =I38-J38 -> 1.1475066e+10 | L38: =SUM(L37,N37:O37) -> 304346386 | M38: =CEILING(J38/12*3,1) -> 212166128 | N38: =IF(K38>0,IF(AND(K38>M38,M38>L38),M38-L38,IF(AND(K38<M38,M38>L38),K38,0)),0) -> 0 | O38: =IF(K38<0,IF(L38>-K38,K38,-L38),0) -> 0 | P38: =IF(K38>0,K38-N38,K38-O38) -> 1.1475066e+10 | Q38: =SUM(Q37:S37) -> 7.1468868e+09 | R38: =IF(P38<0,0,P38*E38) -> 1.1475066e+09 | S38: =IF(P38<0,IF(Q38>-P38,P38,-Q38),0) -> 0 | T38: =IF(P38>0,P38-R38,P38-S38) -> 1.032756e+10 | U38: =SUM(U37:W37) -> 6.5626543e+10 | V38: =IF(T38<0,0,T38) -> 1.032756e+10 | W38: =IF(T38<0,IF(U38>-T38,T38,-U38),0) -> 0 | X38: =IF(T38>0,T38-V38,T38-W38) -> 0
A39: 2060 | B39: 57 | C39: 0 | E39: 0.1 | F39: 0.3 | G39: 0.6 | I39: 1.2824086e+10 | J39: 8.6412967e+08 | K39: =I39-J39 -> 1.1959956e+10 | L39: =SUM(L38,N38:O38) -> 304346386 | M39: =CEILING(J39/12*3,1) -> 216032418 | N39: =IF(K39>0,IF(AND(K39>M39,M39>L39),M39-L39,IF(AND(K39<M39,M39>L39),K39,0)),0) -> 0 | O39: =IF(K39<0,IF(L39>-K39,K39,-L39),0) -> 0 | P39: =IF(K39>0,K39-N39,K39-O39) -> 1.1959956e+10 | Q39: =SUM(Q38:S38) -> 8.2943934e+09 | R39: =IF(P39<0,0,P39*E39) -> 1.1959956e+09 | S39: =IF(P39<0,IF(Q39>-P39,P39,-Q39),0) -> 0 | T39: =IF(P39>0,P39-R39,P39-S39) -> 1.0763961e+10 | U39: =SUM(U38:W38) -> 7.5954103e+10 | V39: =IF(T39<0,0,T39) -> 1.0763961e+10 | W39: =IF(T39<0,IF(U39>-T39,T39,-U39),0) -> 0 | X39: =IF(T39>0,T39-V39,T39-W39) -> 0
A40: 2061 | B40: 58 | C40: 0 | E40: 0.1 | F40: 0.3 | G40: 0.6 | I40: 3.7958268e+09 | J40: 8.8902525e+08 | K40: =I40-J40 -> 2.9068015e+09 | L40: =SUM(L39,N39:O39) -> 304346386 | M40: =CEILING(J40/12*3,1) -> 222256312 | N40: =IF(K40>0,IF(AND(K40>M40,M40>L40),M40-L40,IF(AND(K40<M40,M40>L40),K40,0)),0) -> 0 | O40: =IF(K40<0,IF(L40>-K40,K40,-L40),0) -> 0 | P40: =IF(K40>0,K40-N40,K40-O40) -> 2.9068015e+09 | Q40: =SUM(Q39:S39) -> 9.4903891e+09 | R40: =IF(P40<0,0,P40*E40) -> 2.9068015e+08 | S40: =IF(P40<0,IF(Q40>-P40,P40,-Q40),0) -> 0 | T40: =IF(P40>0,P40-R40,P40-S40) -> 2.6161214e+09 | U40: =SUM(U39:W39) -> 8.6718063e+10 | V40: =IF(T40<0,0,T40) -> 2.6161214e+09 | W40: =IF(T40<0,IF(U40>-T40,T40,-U40),0) -> 0 | X40: =IF(T40>0,T40-V40,T40-W40) -> 0
A41: 2062 | B41: 59 | C41: 0 | E41: 0.1 | F41: 0.3 | G41: 0.6 | I41: -2.4628732e+09 | J41: 9.1463806e+08 | K41: =I41-J41 -> -3.3775112e+09 | L41: =SUM(L40,N40:O40) -> 304346386 | M41: =CEILING(J41/12*3,1) -> 228659516 | N41: =IF(K41>0,IF(AND(K41>M41,M41>L41),M41-L41,IF(AND(K41<M41,M41>L41),K41,0)),0) -> 0 | O41: =IF(K41<0,IF(L41>-K41,K41,-L41),0) -> -304346386 | P41: =IF(K41>0,K41-N41,K41-O41) -> -3.0731648e+09 | Q41: =SUM(Q40:S40) -> 9.7810692e+09 | R41: =IF(P41<0,0,P41*E41) -> 0 | S41: =IF(P41<0,IF(Q41>-P41,P41,-Q41),0) -> -3.0731648e+09 | T41: =IF(P41>0,P41-R41,P41-S41) -> 0 | U41: =SUM(U40:W40) -> 8.9334185e+10 | V41: =IF(T41<0,0,T41) -> 0 | W41: =IF(T41<0,IF(U41>-T41,T41,-U41),0) -> 0 | X41: =IF(T41>0,T41-V41,T41-W41) -> 0
A42: 2063 | B42: 60 | C42: Nhi retires (when year ends) | E42: 0.1 | F42: 0.3 | G42: 0.6 | I42: 7.7170527e+09 | J42: 9.4098879e+08 | K42: =I42-J42 -> 6.7760639e+09 | L42: =SUM(L41,N41:O41) -> 0 | M42: =CEILING(J42/12*3,1) -> 235247197 | N42: =IF(K42>0,IF(AND(K42>M42,M42>L42),M42-L42,IF(AND(K42<M42,M42>L42),K42,0)),0) -> 235247197 | O42: =IF(K42<0,IF(L42>-K42,K42,-L42),0) -> 0 | P42: =IF(K42>0,K42-N42,K42-O42) -> 6.5408167e+09 | Q42: =SUM(Q41:S41) -> 6.7079044e+09 | R42: =IF(P42<0,0,P42*E42) -> 6.5408167e+08 | S42: =IF(P42<0,IF(Q42>-P42,P42,-Q42),0) -> 0 | T42: =IF(P42>0,P42-R42,P42-S42) -> 5.8867351e+09 | U42: =SUM(U41:W41) -> 8.9334185e+10 | V42: =IF(T42<0,0,T42) -> 5.8867351e+09 | W42: =IF(T42<0,IF(U42>-T42,T42,-U42),0) -> 0 | X42: =IF(T42>0,T42-V42,T42-W42) -> 0
A43: 2064 | B43: 61 | C43: 0 | E43: 0.6 | F43: 0.3 | G43: 0.1 | I43: 1.6659943e+10 | J43: 9.5721228e+08 | K43: =I43-J43 -> 1.5702731e+10 | L43: =SUM(L42,N42:O42) -> 235247197 | M43: =CEILING(J43/12*3,1) -> 239303070 | N43: =IF(K43>0,IF(AND(K43>M43,M43>L43),M43-L43,IF(AND(K43<M43,M43>L43),K43,0)),0) -> 4055873 | O43: =IF(K43<0,IF(L43>-K43,K43,-L43),0) -> 0 | P43: =IF(K43>0,K43-N43,K43-O43) -> 1.5698675e+10 | Q43: =SUM(Q42:S42) -> 7.3619861e+09 | R43: =IF(P43<0,0,P43*E43) -> 9.419205e+09 | S43: =IF(P43<0,IF(Q43>-P43,P43,-Q43),0) -> 0 | T43: =IF(P43>0,P43-R43,P43-S43) -> 6.27947e+09 | U43: =SUM(U42:W42) -> 9.522092e+10 | V43: =IF(T43<0,0,T43) -> 6.27947e+09 | W43: =IF(T43<0,IF(U43>-T43,T43,-U43),0) -> 0 | X43: =IF(T43>0,T43-V43,T43-W43) -> 0
A44: 2065 | B44: 62 | C44: Husband retires (when year ends) | E44: 0.6 | F44: 0.3 | G44: 0.1 | I44: -4.030316e+08 | J44: 9.8478956e+08 | K44: =I44-J44 -> -1.3878212e+09 | L44: =SUM(L43,N43:O43) -> 239303070 | M44: =CEILING(J44/12*3,1) -> 246197392 | N44: =IF(K44>0,IF(AND(K44>M44,M44>L44),M44-L44,IF(AND(K44<M44,M44>L44),K44,0)),0) -> 0 | O44: =IF(K44<0,IF(L44>-K44,K44,-L44),0) -> -239303070 | P44: =IF(K44>0,K44-N44,K44-O44) -> -1.1485181e+09 | Q44: =SUM(Q43:S43) -> 1.6781191e+10 | R44: =IF(P44<0,0,P44*E44) -> 0 | S44: =IF(P44<0,IF(Q44>-P44,P44,-Q44),0) -> -1.1485181e+09 | T44: =IF(P44>0,P44-R44,P44-S44) -> 0 | U44: =SUM(U43:W43) -> 1.0150039e+11 | V44: =IF(T44<0,0,T44) -> 0 | W44: =IF(T44<0,IF(U44>-T44,T44,-U44),0) -> 0 | X44: =IF(T44>0,T44-V44,T44-W44) -> 0
A45: 2066 | B45: 63 | C45: 0 | E45: 0.6 | F45: 0.3 | G45: 0.1 | I45: -5.4168751e+09 | J45: 1.0131614e+09 | K45: =I45-J45 -> -6.4300365e+09 | L45: =SUM(L44,N44:O44) -> 0 | M45: =CEILING(J45/12*3,1) -> 253290338 | N45: =IF(K45>0,IF(AND(K45>M45,M45>L45),M45-L45,IF(AND(K45<M45,M45>L45),K45,0)),0) -> 0 | O45: =IF(K45<0,IF(L45>-K45,K45,-L45),0) -> 0 | P45: =IF(K45>0,K45-N45,K45-O45) -> -6.4300365e+09 | Q45: =SUM(Q44:S44) -> 1.5632673e+10 | R45: =IF(P45<0,0,P45*E45) -> 0 | S45: =IF(P45<0,IF(Q45>-P45,P45,-Q45),0) -> -6.4300365e+09 | T45: =IF(P45>0,P45-R45,P45-S45) -> 0 | U45: =SUM(U44:W44) -> 1.0150039e+11 | V45: =IF(T45<0,0,T45) -> 0 | W45: =IF(T45<0,IF(U45>-T45,T45,-U45),0) -> 0 | X45: =IF(T45>0,T45-V45,T45-W45) -> 0
A46: 2067 | B46: 64 | C46: 0 | E46: 0.6 | F46: 0.3 | G46: 0.1 | I46: -2.8970928e+09 | J46: 1.0423505e+09 | K46: =I46-J46 -> -3.9394434e+09 | L46: =SUM(L45,N45:O45) -> 0 | M46: =CEILING(J46/12*3,1) -> 260587633 | N46: =IF(K46>0,IF(AND(K46>M46,M46>L46),M46-L46,IF(AND(K46<M46,M46>L46),K46,0)),0) -> 0 | O46: =IF(K46<0,IF(L46>-K46,K46,-L46),0) -> 0 | P46: =IF(K46>0,K46-N46,K46-O46) -> -3.9394434e+09 | Q46: =SUM(Q45:S45) -> 9.2026365e+09 | R46: =IF(P46<0,0,P46*E46) -> 0 | S46: =IF(P46<0,IF(Q46>-P46,P46,-Q46),0) -> -3.9394434e+09 | T46: =IF(P46>0,P46-R46,P46-S46) -> 0 | U46: =SUM(U45:W45) -> 1.0150039e+11 | V46: =IF(T46<0,0,T46) -> 0 | W46: =IF(T46<0,IF(U46>-T46,T46,-U46),0) -> 0 | X46: =IF(T46>0,T46-V46,T46-W46) -> 0
A47: 2068 | B47: 65 | C47: 0 | E47: 0.6 | F47: 0.3 | G47: 0.1 | I47: 5.8817021e+10 | J47: 1.0723806e+09 | K47: =I47-J47 -> 5.774464e+10 | L47: =SUM(L46,N46:O46) -> 0 | M47: =CEILING(J47/12*3,1) -> 268095163 | N47: =IF(K47>0,IF(AND(K47>M47,M47>L47),M47-L47,IF(AND(K47<M47,M47>L47),K47,0)),0) -> 268095163 | O47: =IF(K47<0,IF(L47>-K47,K47,-L47),0) -> 0 | P47: =IF(K47>0,K47-N47,K47-O47) -> 5.7476545e+10 | Q47: =SUM(Q46:S46) -> 5.2631932e+09 | R47: =IF(P47<0,0,P47*E47) -> 3.4485927e+10 | S47: =IF(P47<0,IF(Q47>-P47,P47,-Q47),0) -> 0 | T47: =IF(P47>0,P47-R47,P47-S47) -> 2.2990618e+10 | U47: =SUM(U46:W46) -> 1.0150039e+11 | V47: =IF(T47<0,0,T47) -> 2.2990618e+10 | W47: =IF(T47<0,IF(U47>-T47,T47,-U47),0) -> 0 | X47: =IF(T47>0,T47-V47,T47-W47) -> 0
A48: 2069 | B48: 66 | C48: 0 | E48: 0.6 | F48: 0.3 | G48: 0.1 | I48: -2.2603155e+09 | J48: 1.1032759e+09 | K48: =I48-J48 -> -3.3635914e+09 | L48: =SUM(L47,N47:O47) -> 268095163 | M48: =CEILING(J48/12*3,1) -> 275818984 | N48: =IF(K48>0,IF(AND(K48>M48,M48>L48),M48-L48,IF(AND(K48<M48,M48>L48),K48,0)),0) -> 0 | O48: =IF(K48<0,IF(L48>-K48,K48,-L48),0) -> -268095163 | P48: =IF(K48>0,K48-N48,K48-O48) -> -3.0954962e+09 | Q48: =SUM(Q47:S47) -> 3.974912e+10 | R48: =IF(P48<0,0,P48*E48) -> 0 | S48: =IF(P48<0,IF(Q48>-P48,P48,-Q48),0) -> -3.0954962e+09 | T48: =IF(P48>0,P48-R48,P48-S48) -> 0 | U48: =SUM(U47:W47) -> 1.2449101e+11 | V48: =IF(T48<0,0,T48) -> 0 | W48: =IF(T48<0,IF(U48>-T48,T48,-U48),0) -> 0 | X48: =IF(T48>0,T48-V48,T48-W48) -> 0
A49: 2070 | B49: 67 | C49: 0 | E49: 0.6 | F49: 0.3 | G49: 0.1 | I49: -3.9461756e+10 | J49: 1.1350613e+09 | K49: =I49-J49 -> -4.0596817e+10 | L49: =SUM(L48,N48:O48) -> 0 | M49: =CEILING(J49/12*3,1) -> 283765329 | N49: =IF(K49>0,IF(AND(K49>M49,M49>L49),M49-L49,IF(AND(K49<M49,M49>L49),K49,0)),0) -> 0 | O49: =IF(K49<0,IF(L49>-K49,K49,-L49),0) -> 0 | P49: =IF(K49>0,K49-N49,K49-O49) -> -4.0596817e+10 | Q49: =SUM(Q48:S48) -> 3.6653624e+10 | R49: =IF(P49<0,0,P49*E49) -> 0 | S49: =IF(P49<0,IF(Q49>-P49,P49,-Q49),0) -> -3.6653624e+10 | T49: =IF(P49>0,P49-R49,P49-S49) -> -3.9431936e+09 | U49: =SUM(U48:W48) -> 1.2449101e+11 | V49: =IF(T49<0,0,T49) -> 0 | W49: =IF(T49<0,IF(U49>-T49,T49,-U49),0) -> -3.9431936e+09 | X49: =IF(T49>0,T49-V49,T49-W49) -> 0
A50: 2071 | B50: 68 | C50: 0 | E50: 0.6 | F50: 0.3 | G50: 0.1 | I50: 1.2920412e+10 | J50: 1.1677624e+09 | K50: =I50-J50 -> 1.175265e+10 | L50: =SUM(L49,N49:O49) -> 0 | M50: =CEILING(J50/12*3,1) -> 291940608 | N50: =IF(K50>0,IF(AND(K50>M50,M50>L50),M50-L50,IF(AND(K50<M50,M50>L50),K50,0)),0) -> 291940608 | O50: =IF(K50<0,IF(L50>-K50,K50,-L50),0) -> 0 | P50: =IF(K50>0,K50-N50,K50-O50) -> 1.1460709e+10 | Q50: =SUM(Q49:S49) -> 0 | R50: =IF(P50<0,0,P50*E50) -> 6.8764255e+09 | S50: =IF(P50<0,IF(Q50>-P50,P50,-Q50),0) -> 0 | T50: =IF(P50>0,P50-R50,P50-S50) -> 4.5842837e+09 | U50: =SUM(U49:W49) -> 1.2054781e+11 | V50: =IF(T50<0,0,T50) -> 4.5842837e+09 | W50: =IF(T50<0,IF(U50>-T50,T50,-U50),0) -> 0 | X50: =IF(T50>0,T50-V50,T50-W50) -> 0
A51: 2072 | B51: 69 | C51: 0 | E51: 0.6 | F51: 0.3 | G51: 0.1 | I51: 4.9931568e+09 | J51: 1.2014057e+09 | K51: =I51-J51 -> 3.7917511e+09 | L51: =SUM(L50,N50:O50) -> 291940608 | M51: =CEILING(J51/12*3,1) -> 300351417 | N51: =IF(K51>0,IF(AND(K51>M51,M51>L51),M51-L51,IF(AND(K51<M51,M51>L51),K51,0)),0) -> 8410809 | O51: =IF(K51<0,IF(L51>-K51,K51,-L51),0) -> 0 | P51: =IF(K51>0,K51-N51,K51-O51) -> 3.7833403e+09 | Q51: =SUM(Q50:S50) -> 6.8764255e+09 | R51: =IF(P51<0,0,P51*E51) -> 2.2700042e+09 | S51: =IF(P51<0,IF(Q51>-P51,P51,-Q51),0) -> 0 | T51: =IF(P51>0,P51-R51,P51-S51) -> 1.5133361e+09 | U51: =SUM(U50:W50) -> 1.251321e+11 | V51: =IF(T51<0,0,T51) -> 1.5133361e+09 | W51: =IF(T51<0,IF(U51>-T51,T51,-U51),0) -> 0 | X51: =IF(T51>0,T51-V51,T51-W51) -> 0
A52: 2073 | B52: 70 | C52: 0 | E52: 0.6 | F52: 0.3 | G52: 0.1 | I52: 4.0910425e+10 | J52: 1.2360182e+09 | K52: =I52-J52 -> 3.9674406e+10 | L52: =SUM(L51,N51:O51) -> 300351417 | M52: =CEILING(J52/12*3,1) -> 309004542 | N52: =IF(K52>0,IF(AND(K52>M52,M52>L52),M52-L52,IF(AND(K52<M52,M52>L52),K52,0)),0) -> 8653125 | O52: =IF(K52<0,IF(L52>-K52,K52,-L52),0) -> 0 | P52: =IF(K52>0,K52-N52,K52-O52) -> 3.9665753e+10 | Q52: =SUM(Q51:S51) -> 9.1464297e+09 | R52: =IF(P52<0,0,P52*E52) -> 2.3799452e+10 | S52: =IF(P52<0,IF(Q52>-P52,P52,-Q52),0) -> 0 | T52: =IF(P52>0,P52-R52,P52-S52) -> 1.5866301e+10 | U52: =SUM(U51:W51) -> 1.2664543e+11 | V52: =IF(T52<0,0,T52) -> 1.5866301e+10 | W52: =IF(T52<0,IF(U52>-T52,T52,-U52),0) -> 0 | X52: =IF(T52>0,T52-V52,T52-W52) -> 0
A53: 2074 | B53: 71 | C53: Trash car Go travel around the world | E53: 0.6 | F53: 0.3 | G53: 0.1 | I53: 3.8508186e+10 | J53: 5.5117493e+09 | K53: =I53-J53 -> 3.2996436e+10 | L53: =SUM(L52,N52:O52) -> 309004542 | M53: =CEILING(J53/12*3,1) -> 1377937317 | N53: =IF(K53>0,IF(AND(K53>M53,M53>L53),M53-L53,IF(AND(K53<M53,M53>L53),K53,0)),0) -> 1068932775 | O53: =IF(K53<0,IF(L53>-K53,K53,-L53),0) -> 0 | P53: =IF(K53>0,K53-N53,K53-O53) -> 3.1927504e+10 | Q53: =SUM(Q52:S52) -> 3.2945882e+10 | R53: =IF(P53<0,0,P53*E53) -> 1.9156502e+10 | S53: =IF(P53<0,IF(Q53>-P53,P53,-Q53),0) -> 0 | T53: =IF(P53>0,P53-R53,P53-S53) -> 1.2771001e+10 | U53: =SUM(U52:W52) -> 1.4251174e+11 | V53: =IF(T53<0,0,T53) -> 1.2771001e+10 | W53: =IF(T53<0,IF(U53>-T53,T53,-U53),0) -> 0 | X53: =IF(T53>0,T53-V53,T53-W53) -> 0
A54: 2075 | B54: 72 | C54: 0 | E54: 0.6 | F54: 0.3 | G54: 0.1 | I54: 2.3734152e+10 | J54: 1.1306985e+09 | K54: =I54-J54 -> 2.2603453e+10 | L54: =SUM(L53,N53:O53) -> 1377937317 | M54: =CEILING(J54/12*3,1) -> 282674618 | N54: =IF(K54>0,IF(AND(K54>M54,M54>L54),M54-L54,IF(AND(K54<M54,M54>L54),K54,0)),0) -> 0 | O54: =IF(K54<0,IF(L54>-K54,K54,-L54),0) -> 0 | P54: =IF(K54>0,K54-N54,K54-O54) -> 2.2603453e+10 | Q54: =SUM(Q53:S53) -> 5.2102384e+10 | R54: =IF(P54<0,0,P54*E54) -> 1.3562072e+10 | S54: =IF(P54<0,IF(Q54>-P54,P54,-Q54),0) -> 0 | T54: =IF(P54>0,P54-R54,P54-S54) -> 9.0413812e+09 | U54: =SUM(U53:W53) -> 1.5528274e+11 | V54: =IF(T54<0,0,T54) -> 9.0413812e+09 | W54: =IF(T54<0,IF(U54>-T54,T54,-U54),0) -> 0 | X54: =IF(T54>0,T54-V54,T54-W54) -> 0
A55: 2076 | B55: 73 | C55: 0 | E55: 0.6 | F55: 0.3 | G55: 0.1 | I55: 3.2207411e+10 | J55: 1.1632739e+09 | K55: =I55-J55 -> 3.1044137e+10 | L55: =SUM(L54,N54:O54) -> 1377937317 | M55: =CEILING(J55/12*3,1) -> 290818474 | N55: =IF(K55>0,IF(AND(K55>M55,M55>L55),M55-L55,IF(AND(K55<M55,M55>L55),K55,0)),0) -> 0 | O55: =IF(K55<0,IF(L55>-K55,K55,-L55),0) -> 0 | P55: =IF(K55>0,K55-N55,K55-O55) -> 3.1044137e+10 | Q55: =SUM(Q54:S54) -> 6.5664456e+10 | R55: =IF(P55<0,0,P55*E55) -> 1.8626482e+10 | S55: =IF(P55<0,IF(Q55>-P55,P55,-Q55),0) -> 0 | T55: =IF(P55>0,P55-R55,P55-S55) -> 1.2417655e+10 | U55: =SUM(U54:W54) -> 1.6432412e+11 | V55: =IF(T55<0,0,T55) -> 1.2417655e+10 | W55: =IF(T55<0,IF(U55>-T55,T55,-U55),0) -> 0 | X55: =IF(T55>0,T55-V55,T55-W55) -> 0
A56: 2077 | B56: 74 | C56: 0 | E56: 0.6 | F56: 0.3 | G56: 0.1 | I56: -4.5304539e+10 | J56: 1.1967878e+09 | K56: =I56-J56 -> -4.6501327e+10 | L56: =SUM(L55,N55:O55) -> 1377937317 | M56: =CEILING(J56/12*3,1) -> 299196954 | N56: =IF(K56>0,IF(AND(K56>M56,M56>L56),M56-L56,IF(AND(K56<M56,M56>L56),K56,0)),0) -> 0 | O56: =IF(K56<0,IF(L56>-K56,K56,-L56),0) -> -1377937317 | P56: =IF(K56>0,K56-N56,K56-O56) -> -4.512339e+10 | Q56: =SUM(Q55:S55) -> 8.4290938e+10 | R56: =IF(P56<0,0,P56*E56) -> 0 | S56: =IF(P56<0,IF(Q56>-P56,P56,-Q56),0) -> -4.512339e+10 | T56: =IF(P56>0,P56-R56,P56-S56) -> 0 | U56: =SUM(U55:W55) -> 1.7674177e+11 | V56: =IF(T56<0,0,T56) -> 0 | W56: =IF(T56<0,IF(U56>-T56,T56,-U56),0) -> 0 | X56: =IF(T56>0,T56-V56,T56-W56) -> 0
A57: 2078 | B57: 75 | C57: 0 | E57: 0.6 | F57: 0.3 | G57: 0.1 | I57: 5.8380286e+10 | J57: 1.2312673e+09 | K57: =I57-J57 -> 5.7149018e+10 | L57: =SUM(L56,N56:O56) -> 0 | M57: =CEILING(J57/12*3,1) -> 307816819 | N57: =IF(K57>0,IF(AND(K57>M57,M57>L57),M57-L57,IF(AND(K57<M57,M57>L57),K57,0)),0) -> 307816819 | O57: =IF(K57<0,IF(L57>-K57,K57,-L57),0) -> 0 | P57: =IF(K57>0,K57-N57,K57-O57) -> 5.6841202e+10 | Q57: =SUM(Q56:S56) -> 3.9167548e+10 | R57: =IF(P57<0,0,P57*E57) -> 3.4104721e+10 | S57: =IF(P57<0,IF(Q57>-P57,P57,-Q57),0) -> 0 | T57: =IF(P57>0,P57-R57,P57-S57) -> 2.2736481e+10 | U57: =SUM(U56:W56) -> 1.7674177e+11 | V57: =IF(T57<0,0,T57) -> 2.2736481e+10 | W57: =IF(T57<0,IF(U57>-T57,T57,-U57),0) -> 0 | X57: =IF(T57>0,T57-V57,T57-W57) -> 0
A58: 2079 | B58: 76 | C58: 0 | E58: 0.6 | F58: 0.3 | G58: 0.1 | I58: -1.912626e+10 | J58: 1.2667401e+09 | K58: =I58-J58 -> -2.0393e+10 | L58: =SUM(L57,N57:O57) -> 307816819 | M58: =CEILING(J58/12*3,1) -> 316685021 | N58: =IF(K58>0,IF(AND(K58>M58,M58>L58),M58-L58,IF(AND(K58<M58,M58>L58),K58,0)),0) -> 0 | O58: =IF(K58<0,IF(L58>-K58,K58,-L58),0) -> -307816819 | P58: =IF(K58>0,K58-N58,K58-O58) -> -2.0085183e+10 | Q58: =SUM(Q57:S57) -> 7.3272269e+10 | R58: =IF(P58<0,0,P58*E58) -> 0 | S58: =IF(P58<0,IF(Q58>-P58,P58,-Q58),0) -> -2.0085183e+10 | T58: =IF(P58>0,P58-R58,P58-S58) -> 0 | U58: =SUM(U57:W57) -> 1.9947825e+11 | V58: =IF(T58<0,0,T58) -> 0 | W58: =IF(T58<0,IF(U58>-T58,T58,-U58),0) -> 0 | X58: =IF(T58>0,T58-V58,T58-W58) -> 0
A59: 2080 | B59: 77 | C59: 0 | E59: 0.6 | F59: 0.3 | G59: 0.1 | I59: 6.6134232e+10 | J59: 1.3032349e+09 | K59: =I59-J59 -> 6.4830997e+10 | L59: =SUM(L58,N58:O58) -> 0 | M59: =CEILING(J59/12*3,1) -> 325808717 | N59: =IF(K59>0,IF(AND(K59>M59,M59>L59),M59-L59,IF(AND(K59<M59,M59>L59),K59,0)),0) -> 325808717 | O59: =IF(K59<0,IF(L59>-K59,K59,-L59),0) -> 0 | P59: =IF(K59>0,K59-N59,K59-O59) -> 6.4505189e+10 | Q59: =SUM(Q58:S58) -> 5.3187086e+10 | R59: =IF(P59<0,0,P59*E59) -> 3.8703113e+10 | S59: =IF(P59<0,IF(Q59>-P59,P59,-Q59),0) -> 0 | T59: =IF(P59>0,P59-R59,P59-S59) -> 2.5802076e+10 | U59: =SUM(U58:W58) -> 1.9947825e+11 | V59: =IF(T59<0,0,T59) -> 2.5802076e+10 | W59: =IF(T59<0,IF(U59>-T59,T59,-U59),0) -> 0 | X59: =IF(T59>0,T59-V59,T59-W59) -> 0
A60: 2081 | B60: 78 | C60: 0 | E60: 0.6 | F60: 0.3 | G60: 0.1 | I60: 6.6232663e+10 | J60: 1.3407811e+09 | K60: =I60-J60 -> 6.4891882e+10 | L60: =SUM(L59,N59:O59) -> 325808717 | M60: =CEILING(J60/12*3,1) -> 335195266 | N60: =IF(K60>0,IF(AND(K60>M60,M60>L60),M60-L60,IF(AND(K60<M60,M60>L60),K60,0)),0) -> 9386549 | O60: =IF(K60<0,IF(L60>-K60,K60,-L60),0) -> 0 | P60: =IF(K60>0,K60-N60,K60-O60) -> 6.4882495e+10 | Q60: =SUM(Q59:S59) -> 9.1890199e+10 | R60: =IF(P60<0,0,P60*E60) -> 3.8929497e+10 | S60: =IF(P60<0,IF(Q60>-P60,P60,-Q60),0) -> 0 | T60: =IF(P60>0,P60-R60,P60-S60) -> 2.5952998e+10 | U60: =SUM(U59:W59) -> 2.2528033e+11 | V60: =IF(T60<0,0,T60) -> 2.5952998e+10 | W60: =IF(T60<0,IF(U60>-T60,T60,-U60),0) -> 0 | X60: =IF(T60>0,T60-V60,T60-W60) -> 0
A61: 2082 | B61: 79 | C61: 0 | E61: 0.6 | F61: 0.3 | G61: 0.1 | I61: -7.4103096e+09 | J61: 1.379409e+09 | K61: =I61-J61 -> -8.7897186e+09 | L61: =SUM(L60,N60:O60) -> 335195266 | M61: =CEILING(J61/12*3,1) -> 344852241 | N61: =IF(K61>0,IF(AND(K61>M61,M61>L61),M61-L61,IF(AND(K61<M61,M61>L61),K61,0)),0) -> 0 | O61: =IF(K61<0,IF(L61>-K61,K61,-L61),0) -> -335195266 | P61: =IF(K61>0,K61-N61,K61-O61) -> -8.4545233e+09 | Q61: =SUM(Q60:S60) -> 1.308197e+11 | R61: =IF(P61<0,0,P61*E61) -> 0 | S61: =IF(P61<0,IF(Q61>-P61,P61,-Q61),0) -> -8.4545233e+09 | T61: =IF(P61>0,P61-R61,P61-S61) -> 0 | U61: =SUM(U60:W60) -> 2.5123333e+11 | V61: =IF(T61<0,0,T61) -> 0 | W61: =IF(T61<0,IF(U61>-T61,T61,-U61),0) -> 0 | X61: =IF(T61>0,T61-V61,T61-W61) -> 0
A62: 2083 | B62: 80 | C62: 0 | E62: 0.6 | F62: 0.3 | G62: 0.1 | I62: 1.022655e+10 | J62: 1.4191497e+09 | K62: =I62-J62 -> 8.8074004e+09 | L62: =SUM(L61,N61:O61) -> 0 | M62: =CEILING(J62/12*3,1) -> 354787434 | N62: =IF(K62>0,IF(AND(K62>M62,M62>L62),M62-L62,IF(AND(K62<M62,M62>L62),K62,0)),0) -> 354787434 | O62: =IF(K62<0,IF(L62>-K62,K62,-L62),0) -> 0 | P62: =IF(K62>0,K62-N62,K62-O62) -> 8.452613e+09 | Q62: =SUM(Q61:S61) -> 1.2236517e+11 | R62: =IF(P62<0,0,P62*E62) -> 5.0715678e+09 | S62: =IF(P62<0,IF(Q62>-P62,P62,-Q62),0) -> 0 | T62: =IF(P62>0,P62-R62,P62-S62) -> 3.3810452e+09 | U62: =SUM(U61:W61) -> 2.5123333e+11 | V62: =IF(T62<0,0,T62) -> 3.3810452e+09 | W62: =IF(T62<0,IF(U62>-T62,T62,-U62),0) -> 0 | X62: =IF(T62>0,T62-V62,T62-W62) -> 0
A63: 2084 | B63: 81 | C63: 0 | E63: 0.6 | F63: 0.3 | G63: 0.1 | I63: -8.4398693e+10 | J63: 1.4600354e+09 | K63: =I63-J63 -> -8.5858729e+10 | L63: =SUM(L62,N62:O62) -> 354787434 | M63: =CEILING(J63/12*3,1) -> 365008860 | N63: =IF(K63>0,IF(AND(K63>M63,M63>L63),M63-L63,IF(AND(K63<M63,M63>L63),K63,0)),0) -> 0 | O63: =IF(K63<0,IF(L63>-K63,K63,-L63),0) -> -354787434 | P63: =IF(K63>0,K63-N63,K63-O63) -> -8.5503941e+10 | Q63: =SUM(Q62:S62) -> 1.2743674e+11 | R63: =IF(P63<0,0,P63*E63) -> 0 | S63: =IF(P63<0,IF(Q63>-P63,P63,-Q63),0) -> -8.5503941e+10 | T63: =IF(P63>0,P63-R63,P63-S63) -> 0 | U63: =SUM(U62:W62) -> 2.5461437e+11 | V63: =IF(T63<0,0,T63) -> 0 | W63: =IF(T63<0,IF(U63>-T63,T63,-U63),0) -> 0 | X63: =IF(T63>0,T63-V63,T63-W63) -> 0
A64: 2085 | B64: 82 | C64: 0 | E64: 0.6 | F64: 0.3 | G64: 0.1 | I64: -1.7498999e+10 | J64: 1.5020991e+09 | K64: =I64-J64 -> -1.9001098e+10 | L64: =SUM(L63,N63:O63) -> 0 | M64: =CEILING(J64/12*3,1) -> 375524766 | N64: =IF(K64>0,IF(AND(K64>M64,M64>L64),M64-L64,IF(AND(K64<M64,M64>L64),K64,0)),0) -> 0 | O64: =IF(K64<0,IF(L64>-K64,K64,-L64),0) -> 0 | P64: =IF(K64>0,K64-N64,K64-O64) -> -1.9001098e+10 | Q64: =SUM(Q63:S63) -> 4.19328e+10 | R64: =IF(P64<0,0,P64*E64) -> 0 | S64: =IF(P64<0,IF(Q64>-P64,P64,-Q64),0) -> -1.9001098e+10 | T64: =IF(P64>0,P64-R64,P64-S64) -> 0 | U64: =SUM(U63:W63) -> 2.5461437e+11 | V64: =IF(T64<0,0,T64) -> 0 | W64: =IF(T64<0,IF(U64>-T64,T64,-U64),0) -> 0 | X64: =IF(T64>0,T64-V64,T64-W64) -> 0
A65: 2086 | B65: 83 | C65: 0 | E65: 0.6 | F65: 0.3 | G65: 0.1 | I65: -6.0039261e+10 | J65: 1.5453745e+09 | K65: =I65-J65 -> -6.1584636e+10 | L65: =SUM(L64,N64:O64) -> 0 | M65: =CEILING(J65/12*3,1) -> 386343634 | N65: =IF(K65>0,IF(AND(K65>M65,M65>L65),M65-L65,IF(AND(K65<M65,M65>L65),K65,0)),0) -> 0 | O65: =IF(K65<0,IF(L65>-K65,K65,-L65),0) -> 0 | P65: =IF(K65>0,K65-N65,K65-O65) -> -6.1584636e+10 | Q65: =SUM(Q64:S64) -> 2.2931702e+10 | R65: =IF(P65<0,0,P65*E65) -> 0 | S65: =IF(P65<0,IF(Q65>-P65,P65,-Q65),0) -> -2.2931702e+10 | T65: =IF(P65>0,P65-R65,P65-S65) -> -3.8652934e+10 | U65: =SUM(U64:W64) -> 2.5461437e+11 | V65: =IF(T65<0,0,T65) -> 0 | W65: =IF(T65<0,IF(U65>-T65,T65,-U65),0) -> -3.8652934e+10 | X65: =IF(T65>0,T65-V65,T65-W65) -> 0
A66: 2087 | B66: 84 | C66: 0 | E66: 0.6 | F66: 0.3 | G66: 0.1 | I66: -2.297551e+09 | J66: 1.5898968e+09 | K66: =I66-J66 -> -3.8874478e+09 | L66: =SUM(L65,N65:O65) -> 0 | M66: =CEILING(J66/12*3,1) -> 397474194 | N66: =IF(K66>0,IF(AND(K66>M66,M66>L66),M66-L66,IF(AND(K66<M66,M66>L66),K66,0)),0) -> 0 | O66: =IF(K66<0,IF(L66>-K66,K66,-L66),0) -> 0 | P66: =IF(K66>0,K66-N66,K66-O66) -> -3.8874478e+09 | Q66: =SUM(Q65:S65) -> 0 | R66: =IF(P66<0,0,P66*E66) -> 0 | S66: =IF(P66<0,IF(Q66>-P66,P66,-Q66),0) -> 0 | T66: =IF(P66>0,P66-R66,P66-S66) -> -3.8874478e+09 | U66: =SUM(U65:W65) -> 2.1596144e+11 | V66: =IF(T66<0,0,T66) -> 0 | W66: =IF(T66<0,IF(U66>-T66,T66,-U66),0) -> -3.8874478e+09 | X66: =IF(T66>0,T66-V66,T66-W66) -> 0
A67: 2088 | B67: 85 | C67: Nhi and Husband die (when year ends) | E67: 0.6 | F67: 0.3 | G67: 0.1 | I67: 5.6862998e+10 | J67: 1.6357017e+09 | K67: =I67-J67 -> 5.5227296e+10 | L67: =SUM(L66,N66:O66) -> 0 | M67: =CEILING(J67/12*3,1) -> 408925426 | N67: =IF(K67>0,IF(AND(K67>M67,M67>L67),M67-L67,IF(AND(K67<M67,M67>L67),K67,0)),0) -> 408925426 | O67: =IF(K67<0,IF(L67>-K67,K67,-L67),0) -> 0 | P67: =IF(K67>0,K67-N67,K67-O67) -> 5.4818371e+10 | Q67: =SUM(Q66:S66) -> 0 | R67: =IF(P67<0,0,P67*E67) -> 3.2891023e+10 | S67: =IF(P67<0,IF(Q67>-P67,P67,-Q67),0) -> 0 | T67: =IF(P67>0,P67-R67,P67-S67) -> 2.1927348e+10 | U67: =SUM(U66:W66) -> 2.1207399e+11 | V67: =IF(T67<0,0,T67) -> 2.1927348e+10 | W67: =IF(T67<0,IF(U67>-T67,T67,-U67),0) -> 0 | X67: =IF(T67>0,T67-V67,T67-W67) -> 0

Sheet 3. Monte Carlo
A1: Savings | D1: Year | E1: Age | F1: Wealth at Beginning | G1: Savings Account | H1: %Bond | I1: Bond | J1: %Stock | K1: Stock | L1: Random number (Normal) | M1: 1+Return on Savings Account | N1: 1+Return on Bond | O1: 1+Return on Stock | P1: Wealth when Year ends | Q1: Total Return | S1: Simulation | T1: =P40 -> 1.0033472e+11 | V1: Resource Available at Retirement
A2: Expected Return | B2: ='1. Drivers'!K19 -> 0.066057692 | D2: 2025 | E2: 22 | F2: ='3. Funding Allocation'!Q4+'3. Funding Allocation'!U4 -> 60000000 | G2: ='3. Funding Allocation'!Q4 -> 60000000 | H2: ='3. Funding Allocation'!F4/('3. Funding Allocation'!F4+'3. Funding Allocation'!G4) -> 0.5 | I2: ='3. Funding Allocation'!U4*H2 -> 0 | J2: ='3. Funding Allocation'!G4/('3. Funding Allocation'!F4+'3. Funding Allocation'!G4) -> 0.5 | K2: ='3. Funding Allocation'!U4*J2 -> 0 | L2: =NORMSINV(RAND()) -> 1.2621459 | M2: =1+($B$2+$B$3*L2) -> 1.1008138 | N2: =1+($B$6+$B$7*L2) -> 1.4422993 | O2: =1+($B$10+$B$11*L2) -> 1.086556 | P2: =G2*M2+I2*N2+K2*O2 -> 66048829 | Q2: =P2-F2 -> 6048829.3 | S2: 1 | T2: 8.2888768e+10 | V2: Average | W2: =AVERAGE(T2:T1001) -> 1.0348794e+11
A3: Standard Deviation | B3: ='1. Drivers'!K20 -> 0.027537331 | D3: 2026 | E3: 23 | F3: ='3. Funding Allocation'!Q5+'3. Funding Allocation'!U5 -> 60000000 | G3: ='3. Funding Allocation'!Q5 -> 60000000 | H3: ='3. Funding Allocation'!F5/('3. Funding Allocation'!F5+'3. Funding Allocation'!G5) -> 0.5 | I3: ='3. Funding Allocation'!U5*H3 -> 0 | J3: ='3. Funding Allocation'!G5/('3. Funding Allocation'!F5+'3. Funding Allocation'!G5) -> 0.5 | K3: ='3. Funding Allocation'!U5*J3 -> 0 | L3: =NORMSINV(RAND()) -> -1.5153563 | M3: =1+($B$2+$B$3*L3) -> 1.0243288 | N3: =1+($B$6+$B$7*L3) -> 0.62241493 | O3: =1+($B$10+$B$11*L3) -> 1.0420752 | P3: =G3*M3+I3*N3+K3*O3 -> 61459730 | Q3: =P3-F3 -> 1459729.5 | S3: 2 | T3: 8.1312179e+10 | V3: Volatility | W3: =_xlfn.STDEV.S(T2:T1001) -> 3.3531329e+10
D4: 2027 | E4: 24 | F4: ='3. Funding Allocation'!Q6+'3. Funding Allocation'!U6 -> 60000000 | G4: ='3. Funding Allocation'!Q6 -> 60000000 | H4: ='3. Funding Allocation'!F6/('3. Funding Allocation'!F6+'3. Funding Allocation'!G6) -> 0.5 | I4: ='3. Funding Allocation'!U6*H4 -> 0 | J4: ='3. Funding Allocation'!G6/('3. Funding Allocation'!F6+'3. Funding Allocation'!G6) -> 0.5 | K4: ='3. Funding Allocation'!U6*J4 -> 0 | L4: =NORMSINV(RAND()) -> 1.7334672 | M4: =1+($B$2+$B$3*L4) -> 1.1137928 | N4: =1+($B$6+$B$7*L4) -> 1.5814275 | O4: =1+($B$10+$B$11*L4) -> 1.0941041 | P4: =G4*M4+I4*N4+K4*O4 -> 66827565 | Q4: =P4-F4 -> 6827565.1 | S4: 3 | T4: 1.6585157e+11 | V4: 25th Percentile | W4: =_xlfn.PERCENTILE.EXC(T2:T1001,0.25) -> 8.0349285e+10
A5: Stock | D5: 2028 | E5: 25 | F5: ='3. Funding Allocation'!Q7+'3. Funding Allocation'!U7 -> 1.8896268e+08 | G5: ='3. Funding Allocation'!Q7 -> 85792535 | H5: ='3. Funding Allocation'!F7/('3. Funding Allocation'!F7+'3. Funding Allocation'!G7) -> 0.5 | I5: ='3. Funding Allocation'!U7*H5 -> 51585070 | J5: ='3. Funding Allocation'!G7/('3. Funding Allocation'!F7+'3. Funding Allocation'!G7) -> 0.5 | K5: ='3. Funding Allocation'!U7*J5 -> 51585070 | L5: =NORMSINV(RAND()) -> 1.2709915 | M5: =1+($B$2+$B$3*L5) -> 1.1010574 | N5: =1+($B$6+$B$7*L5) -> 1.4449104 | O5: =1+($B$10+$B$11*L5) -> 1.0866977 | P5: =G5*M5+I5*N5+K5*O5 -> 2.2505569e+08 | Q5: =P5-F5 -> 36093013 | S5: 4 | T5: 9.2643691e+10 | V5: 50th Percentile | W5: =_xlfn.PERCENTILE.EXC(T3:T1002,0.5) -> 9.6987127e+10
A6: Expected Return | B6: ='1. Drivers'!O30 -> 0.069729412 | D6: 2029 | E6: 26 | F6: ='3. Funding Allocation'!Q8+'3. Funding Allocation'!U8 -> 5.8694107e+08 | G6: ='3. Funding Allocation'!Q8 -> 1.6538821e+08 | H6: ='3. Funding Allocation'!F8/('3. Funding Allocation'!F8+'3. Funding Allocation'!G8) -> 0.5 | I6: ='3. Funding Allocation'!U8*H6 -> 2.1077643e+08 | J6: ='3. Funding Allocation'!G8/('3. Funding Allocation'!F8+'3. Funding Allocation'!G8) -> 0.5 | K6: ='3. Funding Allocation'!U8*J6 -> 2.1077643e+08 | L6: =NORMSINV(RAND()) -> 1.0735079 | M6: =1+($B$2+$B$3*L6) -> 1.0956192 | N6: =1+($B$6+$B$7*L6) -> 1.3866157 | O6: =1+($B$10+$B$11*L6) -> 1.0835351 | P6: =G6*M6+I6*N6+K6*O6 -> 7.0185207e+08 | Q6: =P6-F6 -> 1.14911e+08 | S6: 5 | T6: 5.842955e+10 | V6: 75th Percentile | W6: =_xlfn.PERCENTILE.EXC(T4:T1003,0.75) -> 1.1903058e+11
A7: Standard Deviation | B7: ='1. Drivers'!O31 -> 0.29518767 | D7: 2030 | E7: 27 | F7: ='3. Funding Allocation'!Q9+'3. Funding Allocation'!U9 -> 1.0717523e+09 | G7: ='3. Funding Allocation'!Q9 -> 2.6235045e+08 | H7: ='3. Funding Allocation'!F9/('3. Funding Allocation'!F9+'3. Funding Allocation'!G9) -> 0.5 | I7: ='3. Funding Allocation'!U9*H7 -> 4.0470091e+08 | J7: ='3. Funding Allocation'!G9/('3. Funding Allocation'!F9+'3. Funding Allocation'!G9) -> 0.5 | K7: ='3. Funding Allocation'!U9*J7 -> 4.0470091e+08 | L7: =NORMSINV(RAND()) -> 1.0310142 | M7: =1+($B$2+$B$3*L7) -> 1.0944491 | N7: =1+($B$6+$B$7*L7) -> 1.3740721 | O7: =1+($B$10+$B$11*L7) -> 1.0828545 | P7: =G7*M7+I7*N7+K7*O7 -> 1.2814496e+09 | Q7: =P7-F7 -> 2.0969738e+08 | S7: 6 | T7: 8.0290394e+10 | V7: 95th Percentile | W7: =_xlfn.PERCENTILE.EXC(T5:T1004,0.95) -> 1.6875079e+11
D8: 2031 | E8: 28 | F8: ='3. Funding Allocation'!Q10+'3. Funding Allocation'!U10 -> 1.8108632e+09 | G8: ='3. Funding Allocation'!Q10 -> 4.1017264e+08 | H8: ='3. Funding Allocation'!F10/('3. Funding Allocation'!F10+'3. Funding Allocation'!G10) -> 0.5 | I8: ='3. Funding Allocation'!U10*H8 -> 7.0034529e+08 | J8: ='3. Funding Allocation'!G10/('3. Funding Allocation'!F10+'3. Funding Allocation'!G10) -> 0.5 | K8: ='3. Funding Allocation'!U10*J8 -> 7.0034529e+08 | L8: =NORMSINV(RAND()) -> -1.1145608 | M8: =1+($B$2+$B$3*L8) -> 1.0353657 | N8: =1+($B$6+$B$7*L8) -> 0.74072482 | O8: =1+($B$10+$B$11*L8) -> 1.0484938 | P8: =G8*M8+I8*N8+K8*O8 -> 1.6777495e+09 | Q8: =P8-F8 -> -1.3311373e+08 | S8: 7 | T8: 1.3243808e+11
A9: Bond | D9: 2032 | E9: 29 | F9: ='3. Funding Allocation'!Q11+'3. Funding Allocation'!U11 -> 1.7442064e+09 | G9: ='3. Funding Allocation'!Q11 -> 3.4351581e+08 | H9: ='3. Funding Allocation'!F11/('3. Funding Allocation'!F11+'3. Funding Allocation'!G11) -> 0.5 | I9: ='3. Funding Allocation'!U11*H9 -> 7.0034529e+08 | J9: ='3. Funding Allocation'!G11/('3. Funding Allocation'!F11+'3. Funding Allocation'!G11) -> 0.5 | K9: ='3. Funding Allocation'!U11*J9 -> 7.0034529e+08 | L9: =NORMSINV(RAND()) -> 1.2470141 | M9: =1+($B$2+$B$3*L9) -> 1.1003971 | N9: =1+($B$6+$B$7*L9) -> 1.4378326 | O9: =1+($B$10+$B$11*L9) -> 1.0863137 | P9: =G9*M9+I9*N9+K9*O9 -> 2.1457778e+09 | Q9: =P9-F9 -> 4.0157139e+08 | S9: 8 | T9: 7.2495601e+10 | V9: Retirement Expenses | W9: =SUM('2. Budgeting Statement'!AN15:BM15)-SUM('2. Budgeting Statement'!AN16:BM16) -> -1.3472859e+11
A10: Expected Return | B10: ='1. Drivers'!T23 -> 0.066343149 | D10: 2033 | E10: 30 | F10: ='3. Funding Allocation'!Q12+'3. Funding Allocation'!U12 -> 2.5336716e+09 | G10: ='3. Funding Allocation'!Q12 -> 5.0140885e+08 | H10: ='3. Funding Allocation'!F12/('3. Funding Allocation'!F12+'3. Funding Allocation'!G12) -> 0.5 | I10: ='3. Funding Allocation'!U12*H10 -> 1.0161314e+09 | J10: ='3. Funding Allocation'!G12/('3. Funding Allocation'!F12+'3. Funding Allocation'!G12) -> 0.5 | K10: ='3. Funding Allocation'!U12*J10 -> 1.0161314e+09 | L10: =NORMSINV(RAND()) -> -0.7922142 | M10: =1+($B$2+$B$3*L10) -> 1.0442422 | N10: =1+($B$6+$B$7*L10) -> 0.83587755 | O10: =1+($B$10+$B$11*L10) -> 1.0536561 | P10: =G10*M10+I10*N10+K10*O10 -> 2.4436067e+09 | Q10: =P10-F10 -> -90064907 | S10: 9 | T10: 8.4668531e+10 | V10: % Successful | W10: =COUNTIF(T2:T1001,">="&$W$9)/COUNT(S2:S1001) -> 1
A11: Standard Deviation | B11: ='1. Drivers'!T24 -> 0.016014706 | D11: 2034 | E11: 31 | F11: ='3. Funding Allocation'!Q13+'3. Funding Allocation'!U13 -> 1.7040168e+09 | G11: ='3. Funding Allocation'!Q13 -> 0 | H11: ='3. Funding Allocation'!F13/('3. Funding Allocation'!F13+'3. Funding Allocation'!G13) -> 0.5 | I11: ='3. Funding Allocation'!U13*H11 -> 8.5200841e+08 | J11: ='3. Funding Allocation'!G13/('3. Funding Allocation'!F13+'3. Funding Allocation'!G13) -> 0.5 | K11: ='3. Funding Allocation'!U13*J11 -> 8.5200841e+08 | L11: =NORMSINV(RAND()) -> -0.13105509 | M11: =1+($B$2+$B$3*L11) -> 1.0624488 | N11: =1+($B$6+$B$7*L11) -> 1.0310436 | O11: =1+($B$10+$B$11*L11) -> 1.0642443 | P11: =G11*M11+I11*N11+K11*O11 -> 1.7852029e+09 | Q11: =P11-F11 -> 81186098 | S11: 10 | T11: 1.0456152e+11
D12: 2035 | E12: 32 | F12: ='3. Funding Allocation'!Q14+'3. Funding Allocation'!U14 -> 1.7362439e+09 | G12: ='3. Funding Allocation'!Q14 -> 6445424.3 | H12: ='3. Funding Allocation'!F14/('3. Funding Allocation'!F14+'3. Funding Allocation'!G14) -> 0.5 | I12: ='3. Funding Allocation'!U14*H12 -> 8.6489926e+08 | J12: ='3. Funding Allocation'!G14/('3. Funding Allocation'!F14+'3. Funding Allocation'!G14) -> 0.5 | K12: ='3. Funding Allocation'!U14*J12 -> 8.6489926e+08 | L12: =NORMSINV(RAND()) -> -1.4527877 | M12: =1+($B$2+$B$3*L12) -> 1.0260518 | N12: =1+($B$6+$B$7*L12) -> 0.64088439 | O12: =1+($B$10+$B$11*L12) -> 1.0430772 | P12: =G12*M12+I12*N12+K12*O12 -> 1.4630705e+09 | Q12: =P12-F12 -> -2.7317349e+08 | S12: 11 | T12: 9.4276321e+10
D13: 2036 | E13: 33 | F13: ='3. Funding Allocation'!Q15+'3. Funding Allocation'!U15 -> 1.7779013e+09 | G13: ='3. Funding Allocation'!Q15 -> 14776885 | H13: ='3. Funding Allocation'!F15/('3. Funding Allocation'!F15+'3. Funding Allocation'!G15) -> 0.5 | I13: ='3. Funding Allocation'!U15*H13 -> 8.8156218e+08 | J13: ='3. Funding Allocation'!G15/('3. Funding Allocation'!F15+'3. Funding Allocation'!G15) -> 0.5 | K13: ='3. Funding Allocation'!U15*J13 -> 8.8156218e+08 | L13: =NORMSINV(RAND()) -> -0.47787569 | M13: =1+($B$2+$B$3*L13) -> 1.0528983 | N13: =1+($B$6+$B$7*L13) -> 0.9286664 | O13: =1+($B$10+$B$11*L13) -> 1.0586901 | P13: =G13*M13+I13*N13+K13*O13 -> 1.7675369e+09 | Q13: =P13-F13 -> -10364351 | S13: 12 | T13: 9.1443062e+10
D14: 2037 | E14: 34 | F14: ='3. Funding Allocation'!Q16+'3. Funding Allocation'!U16 -> 2.1034719e+09 | G14: ='3. Funding Allocation'!Q16 -> 79891006 | H14: ='3. Funding Allocation'!F16/('3. Funding Allocation'!F16+'3. Funding Allocation'!G16) -> 0.33333333 | I14: ='3. Funding Allocation'!U16*H14 -> 6.7452695e+08 | J14: ='3. Funding Allocation'!G16/('3. Funding Allocation'!F16+'3. Funding Allocation'!G16) -> 0.66666667 | K14: ='3. Funding Allocation'!U16*J14 -> 1.3490539e+09 | L14: =NORMSINV(RAND()) -> 0.70687955 | M14: =1+($B$2+$B$3*L14) -> 1.0855233 | N14: =1+($B$6+$B$7*L14) -> 1.2783915 | O14: =1+($B$10+$B$11*L14) -> 1.0776636 | P14: =G14*M14+I14*N14+K14*O14 -> 2.4028594e+09 | Q14: =P14-F14 -> 2.9938754e+08 | S14: 13 | T14: 8.5575281e+10
D15: 2038 | E15: 35 | F15: ='3. Funding Allocation'!Q17+'3. Funding Allocation'!U17 -> 2.7203699e+09 | G15: ='3. Funding Allocation'!Q17 -> 1.4158082e+08 | H15: ='3. Funding Allocation'!F17/('3. Funding Allocation'!F17+'3. Funding Allocation'!G17) -> 0.33333333 | I15: ='3. Funding Allocation'!U17*H15 -> 8.5959638e+08 | J15: ='3. Funding Allocation'!G17/('3. Funding Allocation'!F17+'3. Funding Allocation'!G17) -> 0.66666667 | K15: ='3. Funding Allocation'!U17*J15 -> 1.7191928e+09 | L15: =NORMSINV(RAND()) -> -1.3524393 | M15: =1+($B$2+$B$3*L15) -> 1.0288151 | N15: =1+($B$6+$B$7*L15) -> 0.67050601 | O15: =1+($B$10+$B$11*L15) -> 1.0446842 | P15: =G15*M15+I15*N15+K15*O15 -> 2.5180386e+09 | Q15: =P15-F15 -> -2.0233137e+08 | S15: 14 | T15: 9.4485352e+10
D16: 2039 | E16: 36 | F16: ='3. Funding Allocation'!Q18+'3. Funding Allocation'!U18 -> 2.9998049e+09 | G16: ='3. Funding Allocation'!Q18 -> 1.6952431e+08 | H16: ='3. Funding Allocation'!F18/('3. Funding Allocation'!F18+'3. Funding Allocation'!G18) -> 0.33333333 | I16: ='3. Funding Allocation'!U18*H16 -> 9.4342687e+08 | J16: ='3. Funding Allocation'!G18/('3. Funding Allocation'!F18+'3. Funding Allocation'!G18) -> 0.66666667 | K16: ='3. Funding Allocation'!U18*J16 -> 1.8868537e+09 | L16: =NORMSINV(RAND()) -> 0.2867835 | M16: =1+($B$2+$B$3*L16) -> 1.0739549 | N16: =1+($B$6+$B$7*L16) -> 1.1543844 | O16: =1+($B$10+$B$11*L16) -> 1.0709359 | P16: =G16*M16+I16*N16+K16*O16 -> 3.2918381e+09 | Q16: =P16-F16 -> 2.9203319e+08 | S16: 15 | T16: 8.1930395e+10
D17: 2040 | E17: 37 | F17: ='3. Funding Allocation'!Q19+'3. Funding Allocation'!U19 -> 3.8026692e+09 | G17: ='3. Funding Allocation'!Q19 -> 2.4981074e+08 | H17: ='3. Funding Allocation'!F19/('3. Funding Allocation'!F19+'3. Funding Allocation'!G19) -> 0.33333333 | I17: ='3. Funding Allocation'!U19*H17 -> 1.1842861e+09 | J17: ='3. Funding Allocation'!G19/('3. Funding Allocation'!F19+'3. Funding Allocation'!G19) -> 0.66666667 | K17: ='3. Funding Allocation'!U19*J17 -> 2.3685723e+09 | L17: =NORMSINV(RAND()) -> 0.44054338 | M17: =1+($B$2+$B$3*L17) -> 1.0781891 | N17: =1+($B$6+$B$7*L17) -> 1.1997724 | O17: =1+($B$10+$B$11*L17) -> 1.0733983 | P17: =G17*M17+I17*N17+K17*O17 -> 4.2326386e+09 | Q17: =P17-F17 -> 4.2996937e+08 | S17: 16 | T17: 7.8497616e+10
D18: 2041 | E18: 38 | F18: ='3. Funding Allocation'!Q20+'3. Funding Allocation'!U20 -> 5.0586556e+09 | G18: ='3. Funding Allocation'!Q20 -> 3.7540938e+08 | H18: ='3. Funding Allocation'!F20/('3. Funding Allocation'!F20+'3. Funding Allocation'!G20) -> 0.33333333 | I18: ='3. Funding Allocation'!U20*H18 -> 1.5610821e+09 | J18: ='3. Funding Allocation'!G20/('3. Funding Allocation'!F20+'3. Funding Allocation'!G20) -> 0.66666667 | K18: ='3. Funding Allocation'!U20*J18 -> 3.1221641e+09 | L18: =NORMSINV(RAND()) -> -0.36446923 | M18: =1+($B$2+$B$3*L18) -> 1.0560212 | N18: =1+($B$6+$B$7*L18) -> 0.96214259 | O18: =1+($B$10+$B$11*L18) -> 1.0605063 | P18: =G18*M18+I18*N18+K18*O18 -> 5.2094985e+09 | Q18: =P18-F18 -> 1.508429e+08 | S18: 17 | T18: 8.0397245e+10
D19: 2042 | E19: 39 | F19: ='3. Funding Allocation'!Q21+'3. Funding Allocation'!U21 -> 6.0719827e+09 | G19: ='3. Funding Allocation'!Q21 -> 4.7674209e+08 | H19: ='3. Funding Allocation'!F21/('3. Funding Allocation'!F21+'3. Funding Allocation'!G21) -> 0.33333333 | I19: ='3. Funding Allocation'!U21*H19 -> 1.8650802e+09 | J19: ='3. Funding Allocation'!G21/('3. Funding Allocation'!F21+'3. Funding Allocation'!G21) -> 0.66666667 | K19: ='3. Funding Allocation'!U21*J19 -> 3.7301604e+09 | L19: =NORMSINV(RAND()) -> 0.0047311264 | M19: =1+($B$2+$B$3*L19) -> 1.066188 | N19: =1+($B$6+$B$7*L19) -> 1.071126 | O19: =1+($B$10+$B$11*L19) -> 1.0664189 | P19: =G19*M19+I19*N19+K19*O19 -> 6.4839462e+09 | Q19: =P19-F19 -> 4.1196347e+08 | S19: 18 | T19: 1.318651e+11
D20: 2043 | E20: 40 | F20: ='3. Funding Allocation'!Q22+'3. Funding Allocation'!U22 -> 7.3826808e+09 | G20: ='3. Funding Allocation'!Q22 -> 6.078119e+08 | H20: ='3. Funding Allocation'!F22/('3. Funding Allocation'!F22+'3. Funding Allocation'!G22) -> 0.33333333 | I20: ='3. Funding Allocation'!U22*H20 -> 2.2582896e+09 | J20: ='3. Funding Allocation'!G22/('3. Funding Allocation'!F22+'3. Funding Allocation'!G22) -> 0.66666667 | K20: ='3. Funding Allocation'!U22*J20 -> 4.5165793e+09 | L20: =NORMSINV(RAND()) -> 1.3454639 | M20: =1+($B$2+$B$3*L20) -> 1.1031082 | N20: =1+($B$6+$B$7*L20) -> 1.4668938 | O20: =1+($B$10+$B$11*L20) -> 1.0878904 | P20: =G20*M20+I20*N20+K20*O20 -> 8.8966964e+09 | Q20: =P20-F20 -> 1.5140155e+09 | S20: 19 | T20: 1.0459977e+11
D21: 2044 | E21: 41 | F21: ='3. Funding Allocation'!Q23+'3. Funding Allocation'!U23 -> 9.8323941e+09 | G21: ='3. Funding Allocation'!Q23 -> 8.5278323e+08 | H21: ='3. Funding Allocation'!F23/('3. Funding Allocation'!F23+'3. Funding Allocation'!G23) -> 0.33333333 | I21: ='3. Funding Allocation'!U23*H21 -> 2.9932036e+09 | J21: ='3. Funding Allocation'!G23/('3. Funding Allocation'!F23+'3. Funding Allocation'!G23) -> 0.66666667 | K21: ='3. Funding Allocation'!U23*J21 -> 5.9864072e+09 | L21: =NORMSINV(RAND()) -> -0.92573089 | M21: =1+($B$2+$B$3*L21) -> 1.0405655 | N21: =1+($B$6+$B$7*L21) -> 0.79646507 | O21: =1+($B$10+$B$11*L21) -> 1.0515178 | P21: =G21*M21+I21*N21+K21*O21 -> 9.566173e+09 | Q21: =P21-F21 -> -2.6622111e+08 | S21: 20 | T21: 6.3500698e+10
D22: 2045 | E22: 42 | F22: ='3. Funding Allocation'!Q24+'3. Funding Allocation'!U24 -> 1.0539361e+10 | G22: ='3. Funding Allocation'!Q24 -> 9.2347994e+08 | H22: ='3. Funding Allocation'!F24/('3. Funding Allocation'!F24+'3. Funding Allocation'!G24) -> 0.33333333 | I22: ='3. Funding Allocation'!U24*H22 -> 3.2052938e+09 | J22: ='3. Funding Allocation'!G24/('3. Funding Allocation'!F24+'3. Funding Allocation'!G24) -> 0.66666667 | K22: ='3. Funding Allocation'!U24*J22 -> 6.4105875e+09 | L22: =NORMSINV(RAND()) -> 0.86982258 | M22: =1+($B$2+$B$3*L22) -> 1.0900103 | N22: =1+($B$6+$B$7*L22) -> 1.3264903 | O22: =1+($B$10+$B$11*L22) -> 1.0802731 | P22: =G22*M22+I22*N22+K22*O22 -> 1.2183579e+10 | Q22: =P22-F22 -> 1.6442178e+09 | S22: 21 | T22: 1.1964679e+11
D23: 2046 | E23: 43 | F23: ='3. Funding Allocation'!Q25+'3. Funding Allocation'!U25 -> 1.316454e+10 | G23: ='3. Funding Allocation'!Q25 -> 1.1859978e+09 | H23: ='3. Funding Allocation'!F25/('3. Funding Allocation'!F25+'3. Funding Allocation'!G25) -> 0.33333333 | I23: ='3. Funding Allocation'!U25*H23 -> 3.9928472e+09 | J23: ='3. Funding Allocation'!G25/('3. Funding Allocation'!F25+'3. Funding Allocation'!G25) -> 0.66666667 | K23: ='3. Funding Allocation'!U25*J23 -> 7.9856945e+09 | L23: =NORMSINV(RAND()) -> -0.30564611 | M23: =1+($B$2+$B$3*L23) -> 1.057641 | N23: =1+($B$6+$B$7*L23) -> 0.97950645 | O23: =1+($B$10+$B$11*L23) -> 1.0614483 | P23: =G23*M23+I23*N23+K23*O23 -> 1.3641781e+10 | Q23: =P23-F23 -> 4.7724198e+08 | S23: 22 | T23: 8.7386766e+10
... D65: 2088 | E65: 85 | F65: ='3. Funding Allocation'!Q67+'3. Funding Allocation'!U67 -> 2.1207399e+11 | G65: ='3. Funding Allocation'!Q67 -> 0 | H65: ='3. Funding Allocation'!F67/('3. Funding Allocation'!F67+'3. Funding Allocation'!G67) -> 0.75 | I65: ='3. Funding Allocation'!U67*H65 -> 1.5905549e+11 | J65: ='3. Funding Allocation'!G67/('3. Funding Allocation'!F67+'3. Funding Allocation'!G67) -> 0.25 | K65: ='3. Funding Allocation'!U67*J65 -> 5.3018498e+10 | L65: =NORMSINV(RAND()) -> 0.85378455 | M65: =1+($B$2+$B$3*L65) -> 1.0895686 | N65: =1+($B$6+$B$7*L65) -> 1.3217561 | O65: =1+($B$10+$B$11*L65) -> 1.0800163 | P65: =G65*M65+I65*N65+K65*O65 -> 2.674934e+11 | Q65: =P65-F65 -> 5.5419414e+10 | S65: 64 | T65: 7.2674705e+10
S66: 65 | T66: 9.6298379e+10
S67: 66 | T67: 9.0312906e+10
S68: 67 | T68: 7.3089226e+10
S69: 68 | T69: 7.0759146e+10
S70: 69 | T70: 1.3603786e+11
S71: 70 | T71: 1.1672745e+11
S72: 71 | T72: 1.2885211e+11
S73: 72 | T73: 1.0682324e+11
S74: 73 | T74: 6.1467985e+10
S75: 74 | T75: 7.2296911e+10
S76: 75 | T76: 7.9649889e+10
S77: 76 | T77: 8.9917336e+10
... S1001: 1000 | T1001: 1.5910944e+11

Sheet 4. Health and Car Insurance
A1: TIMELINE
A2: Year | B2: 2025 | C2: 2026 | D2: 2027 | E2: 2028 | F2: 2029 | G2: 2030 | H2: 2031 | I2: 2032 | J2: 2033 | K2: 2034 | L2: 2035 | M2: 2036 | N2: 2037 | O2: 2038 | P2: 2039 | Q2: 2040 | R2: 2041 | S2: 2042 | T2: 2043 | U2: 2044 | V2: 2045 | W2: 2046 | X2: 2047 | Y2: 2048 | Z2: 2049 | AA2: 2050 | AB2: 2051 | AC2: 2052 | AD2: 2053 | AE2: 2054 | AF2: 2055 | AG2: 2056 | AH2: 2057 | AI2: 2058 | AJ2: 2059 | AK2: 2060 | AL2: 2061 | AM2: 2062 | AN2: 2063 | AO2: 2064 | AP2: 2065 | AQ2: 2066 | AR2: 2067 | AS2: 2068 | AT2: 2069 | AU2: 2070 | AV2: 2071 | AW2: 2072 | AX2: 2073 | AY2: 2074 | AZ2: 2075 | BA2: 2076 | BB2: 2077 | BC2: 2078 | BD2: 2079 | BE2: 2080 | BF2: 2081 | BG2: 2082 | BH2: 2083 | BI2: 2084 | BJ2: 2085 | BK2: 2086 | BL2: 2087 | BM2: 2088
A3: Age | B3: 22 | C3: 23 | D3: 24 | E3: 25 | F3: 26 | G3: 27 | H3: 28 | I3: 29 | J3: 30 | K3: 31 | L3: 32 | M3: 33 | N3: 34 | O3: 35 | P3: 36 | Q3: 37 | R3: 38 | S3: 39 | T3: 40 | U3: 41 | V3: 42 | W3: 43 | X3: 44 | Y3: 45 | Z3: 46 | AA3: 47 | AB3: 48 | AC3: 49 | AD3: 50 | AE3: 51 | AF3: 52 | AG3: 53 | AH3: 54 | AI3: 55 | AJ3: 56 | AK3: 57 | AL3: 58 | AM3: 59 | AN3: 60 | AO3: 61 | AP3: 62 | AQ3: 63 | AR3: 64 | AS3: 65 | AT3: 66 | AU3: 67 | AV3: 68 | AW3: 69 | AX3: 70 | AY3: 71 | AZ3: 72 | BA3: 73 | BB3: 74 | BC3: 75 | BD3: 76 | BE3: 77 | BF3: 78 | BG3: 79 | BH3: 80 | BI3: 81 | BJ3: 82 | BK3: 83 | BL3: 84 | BM3: 85
A4: Event | H4: Buy car | J4: Nhi's 6 months of maternity leave Buy apartment | K4: Child is born | AC4: Child goes to university | AF4: Child is independent (when year ends) | AN4: Nhi retires (when year ends) | AP4: Husband retires (when year ends) | AY4: Trash car Go travel around the world | BM4: Nhi and Husband die (when year ends)
A5: Inflation Rate | B5: ='1. Drivers'!B17 -> 0.0295 | C5: ='1. Drivers'!B18 -> 0.0249 | D5: ='1. Drivers'!B19 -> 0.028 | E5: ='1. Drivers'!B20 -> 0.029 | F5: ='1. Drivers'!B21 -> 0.029 | G5: ='1. Drivers'!B22 -> 0.029 | H5: ='1. Drivers'!$B$23 -> 0.02881 | I5: ='1. Drivers'!$B$23 -> 0.02881 | J5: ='1. Drivers'!$B$23 -> 0.02881 | K5: ='1. Drivers'!$B$23 -> 0.02881 | L5: ='1. Drivers'!$B$23 -> 0.02881 | M5: ='1. Drivers'!$B$23 -> 0.02881 | N5: ='1. Drivers'!$B$23 -> 0.02881 | O5: ='1. Drivers'!$B$23 -> 0.02881 | ... BM5: ='1. Drivers'!$B$23 -> 0.02881
A7: HEALTH INSURANCE | G7: CAR INSURANCE
B8: Bảo Việt An Gia | C8: PVI | D8: PJICO | H8: Bảo Việt | I8: PVI | J8: PJICO
A9: Insurance | B9: BẢO VIỆT AN GIA Bronze package (Inpatient and outpatient) | C9: PVI 5th PACKAGE | D9: PJICO Standard Pack 1 | E9: COMPARISION | G9: Insurance | H9: BẢO VIỆT Package with 50% Car Value < Compensation Amount < 120% Car Value Purchase Price From 500,000,000 ₫ to 600,000,000 ₫ | I9: PVI | J9: PJICO Package Above 800,000,000 ₫ | K9: COMPARISION
A10: Coverage Aspects | B10: Maximum Cover Amount Up to 99.800.000 VND/year/person | C10: Maximum Cover Amount Up to 115.000.000 VND/year/person | D10: Maximum Cover Amount Up to 100.000.000 VND/year/person | E10: PVI: Highest Bảo Việt An Gia: Medium PJICO: Lowest | G10: Coverage Aspects | H10: 1. Collisions, overturning, sinking, or falling objects 2. Fire or explosion 3. Natural disasters (e.g., storms, floods, earthquakes, lightning) 4. Theft or robbery (total loss) 5. Malicious acts (excluding those by the owner, insured, or driver) | K10: The same
A11: Age Eligible | B11: Not above 65 | C11: Not above 60 | D11: Not above 65 | E11: Bảo Việt An Gia and PJICO have larger range than PVI. | G11: Exclusions | H11: 1. The damage is intentional or involves fraud. 2. The driver has no valid or appropriate license, or is using a fake/suspended one. 3. The vehicle lacks valid registration or inspection, or has expired documents. 4. The driver is under the influence of alcohol or drugs. 5. The vehicle is driven against traffic rules (wrong way, ignoring signs or police). 6. The vehicle is used without lights at night or with illegal modifications (e.g., sirens). 7. It's used to transport banned or hazardous items without legal permission. 8. The incident occurs outside Vietnam or in restricted/military zones. 9. The damage is due to racing, riots, terrorism, or war. 10. The cause is mechanical failure, wear and tear, poor maintenance, or faulty repairs. 11. The engine is damaged by driving through floods or attempting to restart when submerged. 12. Only parts/accessories are stolen (not the whole vehicle). 13. The vehicle’s declared value is too low (underinsured). 14. The accident results from legal violations or ongoing disputes. | K11: The same
A12: Exclusions | B12: For first year: 1. Respiratory system diseases: Adenoiditis requiring curettage, sinusitis, deviated septum, asthma. For bronchitis, bronchiolitis, and pneumonia of all types, a waiting period of 6 months is applied for children ≤ 6 years old. 2. Ear system diseases: Otitis media requiring surgery, nasopharyngeal polyps, removal of spiral bone. 3. Vascular system diseases: Phlebitis and venous thrombosis/obstruction, varicose veins of lower limbs, carpal tunnel syndrome, lymphatic vessels/nodes, hemorrhoids. 4. Metabolic disorders of all types 5. Musculoskeletal system diseases: Chronic arthritis/polyarthritis, degenerative disease of the spine, vertebral bodies, herniated discs, bone density and structure disorders, gout. 6. Digestive system diseases: Gastric and duodenal ulcers. 7. Other diseases: Stones, cysts, warts, moles of all kinds, vestibular disorders. General exclusions: 1. Nervous system: Central nervous system inflammation, atrophy affecting the nervous system, extrapyramidal movement disorders, Alzheimer's, Apalic syndrome/dementia, epilepsy, coma, cerebral palsy and other paralytic syndromes... 2. Respiratory system: Pulmonary failure, pneumothorax 3. Circulatory system: a. Heart disease. b. Hypertension/high blood pressure, idiopathic hyperdynamic vasoconstriction, c. Cerebrovascular diseases/stroke and sequelae of this disease 4. Digestive system: a. Liver diseases: hepatitis A, B, C. Liver failure/cirrhosis b. Gallbladder diseases: Gallstones | C12: 1. Individuals suffering from mental illness, leprosy, or cancer. 2. Individuals with a permanent disability or permanent injury of 50% or more. 3. Individuals currently undergoing treatment for an illness or injury. 4. Events occurring outside the scope clearly defined in the insurance contract. 5. The policyholder undergoes treatment or uses medication not in accordance with the instructions or guidance of the healthcare facility/doctor, or requests unrelated to standard treatment or surgery as regulated by the Ministry of Health. 6. The method of examination, treatment, or use of medication that has not undergone clinical trials or has not been proven based on widely accepted medical knowledge. 7. The insured person is in violation of the law and is serving a criminal sentence, intentionally committing traffic law violations according to the conclusions of the competent authority. 8. Consequences of the policyholder using alcohol, drugs, stimulants, etc. 9. Services for examination and treatment at home. | D12: 1. Intentional acts by the insured or their legal heirs. 2. Criminal acts or serious legal violations (e.g., illegal racing, driving without a valid license, wrong-way driving). 3. Accidents due to alcohol over legal limits or use of stimulants. 4. Fighting, unless proven as self-defense. 5. Medical treatment or drug use without a doctor’s prescription. 6. Participation in aviation (except as a passenger), military training, or armed conflict. 7. Natural disasters: earthquakes, tsunamis, volcanic eruptions, radiation, pandemics (WHO level 6+). 8. War, civil unrest, terrorism, riots, strikes, rebellion, or armed uprisings. 9. Participation in professional sports or any type of race. 10. Treatment of tuberculosis, malaria, STDs (e.g., syphilis, gonorrhea), or HIV-related illnesses. 11. Treatment/surgery for genetic diseases, birth defects, or conditions existing before coverage start date. 12. Routine check-ups, fatigue treatment, medical exams, health counseling, all vaccines (except post-accident or animal/insect bites). 13. Vision/hearing exams or correction of degenerative or refractive issues (e.g., myopia, astigmatism). 14. Treatment at the request of the insured without medical necessity. 15. Cosmetic surgeries or treatments (e.g., acne, pigmentation, hair loss). 16. Treatment for metabolic or biochemical abnormalities (e.g., high cholesterol, liver enzymes). 17. Costs for medical aids/prosthetics, except limited coverage for trauma-related orthopedic use (10% of accident medical limit). 18. Supplements, dietary products, vitamins, or cosmetics not prescribed by a doctor. 19. Family planning, infertility treatment, artificial reproduction, gender transition, or related complications. 20. Weight management (gain/loss). 21. Treatment for mental disorders, epilepsy, sleep issues, stress, or nervous breakdown. 22. Treatment at unlicensed clinics or without valid invoices, unless stated otherwise in the policy. 23. Maternity-related costs unless maternity benefit is included. 24. Pre-existing and specific diseases within the first policy year. | E12: Bảo Việt An Gia is the insurance with the most exclusions, especially in the first year and common diseases (respiratory, digestive, bone and joint...). PJICO and PVI have a standard exclusion list, PVI is the package with the least exclusions and is more friendly to new buyers. | G12: Insurance Fees Adjusted for Years of Usage | H12: Under 3 years of usage: 1.97% From 03 - 06 years: 2.26% From 06 - 10 years: 2.4% Above 10 years: 2.56% | I12: Normal Car (Under 3 years of usage): 1,50% From 03 - 06 years: 10% higher than fees for Normal Car Under 3 years From 06 - 10 years: 20% higher than fees for Normal Car Under 3 years From 10 - 15 years: 30% higher than fees for Normal Car Under 3 years From 15 - 20 years: 40% higher than fees for Normal Car Under 3 years Above 20 years: 50% higher than fees for Normal Car Under 3 years | J12: Under 3 years of usage: 1.2% From 03 - 06 years: 1.35% From 06 - 10 years: 1.5% Above 10 years: 1.6% | K12: Bảo Việt: Highest PVI: Medium PJICO: Lowest
A13: Advantages | B13: 1. No time wasted collecting claim documents and no need to pay hospital fees 2. Fast, accurate compensation within 15 working days 3. Premium 24/7 hospital fee guarantees service at nearly 90 high-quality hospitals nationwide | C13: 1. The application process is simple and easy for all customers. 2. The insurance package does not limit the treatment and medical examination addresses nationwide. 3. Insurance covers hospital fees, examinations, and treatments at no cost within a network of high-quality hospitals and clinics across the country. | D13: 1. PJICO partners with many hospitals and clinics across Vietnam, including top-tier hospitals. 2. Offers relatively affordable plans that suit a broad range of customers. 3. Quick, streamlined, and professional procedures ensuring maximum customer benefits. 4. Wide insurance coverage, attractive options, and strong financial capacity for claim payments. | E13: All three insurance have similar advantages. | G13: Fees Adjusted for Covered Amount In Case Accident/person | H13: Package 1: From 5,000,000 ₫ to 200,000,000 ₫: 0.10% Package 2: From 5,000 $ to 10,000$: 0.10% Package 3: From 10,000$ to 30,000$: 0.15% Package 4: From 30,000$ to 50,000$: 0.30% | I13: Package 1: From 10,000,000 ₫ to 50,000,000 ₫: 0.55% Package 2: From 50,000,000 ₫ to 150,000,000 ₫: 1.00% Package 3: From 150,000,000 ₫ to 400,000,000 ₫: 2.00% | J13: Package 1: Up to 20,000,000 ₫: 0.15% Package 2: From 20,000,000 ₫ to 50,000,000 ₫: 0.20% Package 3: From 50,000,000 ₫ to 100,000,000 ₫: 0.35% | K13: PVI: Highest PJICO: Medium Bảo Việt: Lowest
A14: Fees Adjusted for Age | B14: 1-3 years old: 5,955,000 ₫ 4-6 years old: 3,350,000 ₫ 7-9 years old: 3,040,000 ₫ 10-18 years old: 2,893,800 ₫ 19-30 years old: 2,756,000 ₫ 31-40 years old: 3,031,600 ₫ 41-50 years old: 3,169,400 ₫ 51-60 years old: 3,307,200 ₫ | C14: 1-3 years old: 3,008,750 ₫ 4-10 years old: 1,805,250 ₫ 11-18 years old: 1,564,550 ₫ 19-40 years old: 1,504,375 ₫ 41-50 years: 1,684,900 ₫ 51-60 years: 1,805,250 ₫ | D14: 1-5 years old: 3,750,000 ₫ 6-59 years old: 2,500,000 ₫ 60-65 years old: 3,250,000 ₫ | E14: Bảo Việt Gia An: Highest PJICO: Medium PVI: Lowest
A15: Discount | B15: No Information | C15: No Information | D15: Family Discounts of 5%/person, provided that the whole family joins insurance at the same time. | E15: Only PJICO have discounts available for family, but accompanies with conditions.
A17: Selection Health Insurance | B17: PVI 5th PACKAGE | G17: Selection Car Insurance | H17: PJICO Package Above 800,000,000 ₫
A19: Categories | B19: Annual Fees | G19: Car Purchase Price | H19: ='2. Consumption Needs'!K47*(1+C5)*(1+D5)*(1+E5)*(1+F5)*(1+G5)*(1+H5) -> 5.1846618e+08
A20: For Nhi and Husband
A21: 22-40 years old | B21: =1504375*2 -> 3008750 | G21: Categories | H21: Annual Fees
A22: 41-50 years old | B22: =1684900*2 -> 3369800 | G22: For Car
A23: 51-60 years old | B23: =1805250*2 -> 3610500 | G23: Under 3 years | H23: =H19*1.2% -> 6221594.1
A24: For 1 Child | G24: 3-6 years | H24: =H19*(1-22%)*1.35% -> 5459448.8 | I24: After 3 years
A25: 1-3 years old | B25: 3008750 | G25: 6-10 years | H25: =H19*(1-39%)*1.5% -> 4743965.5 | I25: After 5 years
A26: 4-10 years old | B26: 1805250 | G26: Above 10 years | H26: =H19*50%*1.6% -> 4147729.4 | I26: After 10 years
A27: 11-18 years old | B27: 1564550 | G27: For People in Car
A28: 19-22 years old | B28: =1504375 -> 1504375 | G28: Package 3 for 5 people, choosing covered amount up to 100,000,000 ₫ | H28: =100000000*5*0.35% -> 1750000
A30: HEALTH INSURANCE EXPENSES
A31: For Nhi and Husband | B31: =B21 -> 3008750 | C31: =B31*(1+C5) -> 3083667.9 | D31: =C31*(1+D5) -> 3170010.6 | E31: =D31*(1+E5) -> 3261940.9 | F31: =E31*(1+F5) -> 3356537.2 | G31: =F31*(1+G5) -> 3453876.7 | H31: =G31*(1+H5) -> 3553382.9 | I31: =H31*(1+I5) -> 3655755.9 | J31: =I31*(1+J5) -> 3761078.2 | ... T31: =S31*(1+T5) -> 4996479.8 | U31: =$B$22*(1+$C$5)*(1+$D$5)*(1+$E$5)*(1+$F$5)*(1+$G$5)*(1+$H$5)^(U2-$H$2+1) -> 5757279.8 | V31: =U31*(1+V5) -> 5923147 | W31: =V31*(1+W5) -> 6093792.9 | X31: =W31*(1+X5) -> 6269355.1 | Y31: =X31*(1+Y5) -> 6449975.2 | Z31: =Y31*(1+Z5) -> 6635799 | AA31: =Z31*(1+AA5) -> 6826976.3 | AB31: =AA31*(1+AB5) -> 7023661.5 | AC31: =AB31*(1+AC5) -> 7226013.2 | AD31: =AC31*(1+AD5) -> 7434194.6 | AE31: =$B$23*(1+$C$5)*(1+$D$5)*(1+$E$5)*(1+$F$5)*(1+$G$5)*(1+$H$5)^(AE2-$H$2+1) -> 8194686.2 | AF31: =AE31*(1+AF5) -> 8430775.1 | AG31: =AF31*(1+AG5) -> 8673665.7 | AH31: =AG31*(1+AH5) -> 8923554 | AI31: =AH31*(1+AI5) -> 9180641.6 | AJ31: =AI31*(1+AJ5) -> 9445135.9 | AK31: =AJ31*(1+AK5) -> 9717250.3 | AL31: =AK31*(1+AL5) -> 9997204.3 | AM31: =AL31*(1+AM5) -> 10285224 | AN31: =AM31*(1+AN5) -> 10581541
A32: For 1 Child | K32: =$B$25*(1+$C$5)*(1+$D$5)*(1+$E$5)*(1+$F$5)*(1+$G$5)*(1+$H$5)^(K2-$H$2+1) -> 3869434.9 | L32: =K32*(1+L5) -> 3980913.3 | M32: =L32*(1+M5) -> 4095603.4 | N32: =$B$26*(1+$C$5)*(1+$D$5)*(1+$E$5)*(1+$F$5)*(1+$G$5)*(1+$H$5)^(N2-$H$2+1) -> 2528158.7 | O32: =N32*(1+O5) -> 2600994.9 | P32: =O32*(1+P5) -> 2675929.6 | Q32: =P32*(1+Q5) -> 2753023.1 | R32: =Q32*(1+R5) -> 2832337.7 | S32: =R32*(1+S5) -> 2913937.3 | T32: =S32*(1+T5) -> 2997887.9 | U32: =$B$27*(1+$C$5)*(1+$D$5)*(1+$E$5)*(1+$F$5)*(1+$G$5)*(1+$H$5)^(U2-$H$2+1) -> 2673022.8 | V32: =U32*(1+V5) -> 2750032.5 | W32: =V32*(1+W5) -> 2829261 | X32: =W32*(1+X5) -> 2910772 | Y32: =X32*(1+Y5) -> 2994631.3 | Z32: =Y32*(1+Z5) -> 3080906.7 | AA32: =Z32*(1+AA5) -> 3169667.6 | AB32: =AA32*(1+AB5) -> 3260985.7 | AC32: =$B$28*(1+$C$5)*(1+$D$5)*(1+$E$5)*(1+$F$5)*(1+$G$5)*(1+$H$5)^(AC2-$H$2+1) -> 3225898.7 | AD32: =$B$26*(1+$C$5)*(1+$D$5)*(1+$E$5)*(1+$F$5)*(1+$G$5)*(1+$H$5)^(AD2-$H$2+1) -> 3982604.3 | AE32: =AD32*(1+AE5) -> 4097343.1 | AF32: =AE32*(1+AF5) -> 4215387.6
A33: Total Health Insurance Expenses | B33: =SUM(B31:B32) -> 3008750 | C33: =SUM(C31:C32) -> 3083667.9 | D33: =SUM(D31:D32) -> 3170010.6 | E33: =SUM(E31:E32) -> 3261940.9 | F33: =SUM(F31:F32) -> 3356537.2 | G33: =SUM(G31:G32) -> 3453876.7 | H33: =SUM(H31:H32) -> 3553382.9 | I33: =SUM(I31:I32) -> 3655755.9 | ... AN33: =SUM(AN31:AN32) -> 10581541
A35: CAR INSURANCE EXPENSES
A36: For Car | H36: =H23*(1+$C$5)*(1+$D$5)*(1+$E$5)*(1+$F$5)*(1+$G$5)*(1+$H$5) -> 7347804.4 | I36: =H36*(1+I5) -> 7559494.6 | J36: =H24*(1+$C$5)*(1+$D$5)*(1+$E$5)*(1+$F$5)*(1+$G$5)*(1+$H$5)^(J2-$H$2+1) -> 6824566.4 | K36: =J36*(1+K5) -> 7021182.2 | L36: =K36*(1+L5) -> 7223462.4 | M36: =H25*(1+$C$5)*(1+$D$5)*(1+$E$5)*(1+$F$5)*(1+$G$5)*(1+$H$5)^(M2-$H$2+1) -> 6457632.4 | N36: =M36*(1+N5) -> 6643676.8 | O36: =N36*(1+O5) -> 6835081.1 | P36: =O36*(1+P5) -> 7031999.8 | Q36: =P36*(1+Q5) -> 7234591.7 | R36: =H26*(1+$C$5)*(1+$D$5)*(1+$E$5)*(1+$F$5)*(1+$G$5)*(1+$H$5)^(R2-$H$2+1) -> 6507558.7 | S36: =R36*(1+S5) -> 6695041.5 | T36: =S36*(1+T5) -> 6887925.6 | U36: =T36*(1+U5) -> 7086366.8 | V36: =U36*(1+V5) -> 7290525 | W36: =V36*(1+W5) -> 7500565 | X36: =W36*(1+X5) -> 7716656.3 | Y36: =X36*(1+Y5) -> 7938973.1 | Z36: =Y36*(1+Z5) -> 8167695 | ... AX36: =AW36*(1+AX5) -> 16148930
A37: For People in Car | H37: =H28*(1+$C$5)*(1+$D$5)*(1+$E$5)*(1+$F$5)*(1+$G$5)*(1+$H$5) -> 2066778.6 | I37: =H37*(1+I5) -> 2126322.5 | J37: =I37*(1+J5) -> 2187581.9 | K37: =J37*(1+K5) -> 2250606.1 | L37: =K37*(1+L5) -> 2315446 | M37: =L37*(1+M5) -> 2382154 | N37: =M37*(1+N5) -> 2450783.9 | O37: =N37*(1+O5) -> 2521391 | P37: =O37*(1+P5) -> 2594032.3 | ... AX37: =AW37*(1+AX5) -> 6813517.7
A38: Total Car Insurance Expenses | H38: =SUM(H36:H37) -> 9414583 | I38: =SUM(I36:I37) -> 9685817.1 | J38: =SUM(J36:J37) -> 9012148.2 | K38: =SUM(K36:K37) -> 9271788.2 | L38: =SUM(L36:L37) -> 9538908.5 | M38: =SUM(M36:M37) -> 8839786.4 | N38: =SUM(N36:N37) -> 9094460.7 | O38: =SUM(O36:O37) -> 9356472.1 | ... AX38: =SUM(AX36:AX37) -> 22962448

Sheet 4. Life Insurance
A1: TIMELINE
A2: Year | B2: 2025 | C2: 2026 | D2: 2027 | E2: 2028 | F2: 2029 | G2: 2030 | H2: 2031 | I2: 2032 | J2: 2033 | K2: 2034 | L2: 2035 | M2: 2036 | N2: 2037 | O2: 2038 | P2: 2039 | Q2: 2040 | R2: 2041 | S2: 2042 | T2: 2043 | U2: 2044 | V2: 2045 | W2: 2046 | X2: 2047 | Y2: 2048 | Z2: 2049 | AA2: 2050 | AB2: 2051 | AC2: 2052 | AD2: 2053 | AE2: 2054 | AF2: 2055 | AG2: 2056 | AH2: 2057 | AI2: 2058 | AJ2: 2059 | AK2: 2060 | AL2: 2061 | AM2: 2062 | AN2: 2063 | AO2: 2064 | AP2: 2065 | AQ2: 2066 | AR2: 2067 | AS2: 2068 | AT2: 2069 | AU2: 2070 | AV2: 2071 | AW2: 2072 | AX2: 2073 | AY2: 2074 | AZ2: 2075 | BA2: 2076 | BB2: 2077 | BC2: 2078 | BD2: 2079 | BE2: 2080 | BF2: 2081 | BG2: 2082 | BH2: 2083 | BI2: 2084 | BJ2: 2085 | BK2: 2086 | BL2: 2087 | BM2: 2088
A3: Age | B3: 22 | C3: 23 | D3: 24 | E3: 25 | F3: 26 | G3: 27 | H3: 28 | I3: 29 | J3: 30 | K3: 31 | L3: 32 | M3: 33 | N3: 34 | O3: 35 | P3: 36 | Q3: 37 | R3: 38 | S3: 39 | T3: 40 | U3: 41 | V3: 42 | W3: 43 | X3: 44 | Y3: 45 | Z3: 46 | AA3: 47 | AB3: 48 | AC3: 49 | AD3: 50 | AE3: 51 | AF3: 52 | AG3: 53 | AH3: 54 | AI3: 55 | AJ3: 56 | AK3: 57 | AL3: 58 | AM3: 59 | AN3: 60 | AO3: 61 | AP3: 62 | AQ3: 63 | AR3: 64 | AS3: 65 | AT3: 66 | AU3: 67 | AV3: 68 | AW3: 69 | AX3: 70 | AY3: 71 | AZ3: 72 | BA3: 73 | BB3: 74 | BC3: 75 | BD3: 76 | BE3: 77 | BF3: 78 | BG3: 79 | BH3: 80 | BI3: 81 | BJ3: 82 | BK3: 83 | BL3: 84 | BM3: 85
A4: Event | H4: Buy car | J4: Nhi's 6 months of maternity leave Buy apartment | K4: Child is born | AC4: Child goes to university | AF4: Child is independent (when year ends) | AN4: Nhi retires (when year ends) | AP4: Husband retires (when year ends) | AY4: Trash car Go travel around the world | BM4: Nhi and Husband die (when year ends)
A5: Inflation Rate | B5: ='1. Drivers'!B17 -> 0.0295 | C5: ='1. Drivers'!B18 -> 0.0249 | D5: ='1. Drivers'!B19 -> 0.028 | E5: ='1. Drivers'!B20 -> 0.029 | F5: ='1. Drivers'!B21 -> 0.029 | G5: ='1. Drivers'!B22 -> 0.029 | H5: ='1. Drivers'!$B$23 -> 0.02881 | I5: ='1. Drivers'!$B$23 -> 0.02881 | J5: ='1. Drivers'!$B$23 -> 0.02881 | K5: ='1. Drivers'!$B$23 -> 0.02881 | L5: ='1. Drivers'!$B$23 -> 0.02881 | M5: ='1. Drivers'!$B$23 -> 0.02881 | N5: ='1. Drivers'!$B$23 -> 0.02881 | O5: ='1. Drivers'!$B$23 -> 0.02881 | ... BM5: ='1. Drivers'!$B$23 -> 0.02881
A7: LIFE INSURANCE
B8: An Phát Trọn Đời | C8: An Bình Ưu Việt | D8: Phú - Bảo An
A9: Insurance | B9: BẢO VIỆT AN BÌNH THỊNH VƯỢNG | C9: AIA AN BÌNH ƯU VIỆT | D9: PRUDENTIAL PHÚ - BẢO AN | E9: COMPARISION
A10: Provider's credibility | B10: 1. Member of Bao Viet Group - Vietnam's leading financial insurance group with nearly 60 years of experience 2. Network of 76 member companies across 63 provinces and cities 3. TOP 10 "Typical Brands Asia - Pacific" 4. Voted as "The most prestigious Life Insurance Company in Vietnam" for many consecutive years 5. Proud to be the only Life Insurance Company to achieve "National Brand Vietnam 2022" | C10: 1. Member of AIA Group - the world's largest independent, Asian-origin life insurance group, established in 2000 2. 200 offices nationwide and 30 partner banks 3. Amcham Awards (2022) 4. Certificate of Merit awarded by the Prime Minister of Vietnam in recognition of the company's outstanding achievements in social charity work, contributing to the cause of national development (2016) | D10: 1. Member of Prudential Group, the world's leading financial group established in 1848 2. Possessing strong potential with a system of agency offices covering 63 provinces and cities nationwide and closely cooperating with 6 leading banks 3. Second-class Labor Medal awarded by the President of Vietnam in 2014 4. Golden Dragon Award 2016 with the title "Leading Life Insurance Company in Vietnam" 5. Top 5 Most Prestigious Life Insurance Companies in 2016 6. "Vietnam Trade and Service Award 2016" 7. Award for Best Community Support Activities in Asia in 2014 | E10: Bảo Việt stands out with its domestic reputation, extensive network and national brand. AIA is international, has a large office system and is recognized by the Government for its social activities. Prudential possesses extensive global experience, combined with prestigious awards for service quality and community responsibility.
A11: Conditions | B11: 1. Age eligible to join: 18 - 60 2. Contract expiration: at 75 years old 3. Contract period: 10, 15, 20, 25 years 4. Premium paying period: same as contract period 5. Flexible payment schedule: 12-month, 6-month, 3-month, 1-month | C11: 1. Age eligible to join: 30 days old - 65 2. Contract expiration: at 70 years old 3. Contract period: 5, 10, 15 years (above 15 years must buy rider, max 20 years) 4. Premium paying period: same as contract period | D11: 1. Age eligible to join: 15 - 60 2. Contract expiration: at 65 years old 3. Contract period: 5-30 years 4. Premium paying period: same as contract period | E11: Phú - Bảo An has largest range, next is An Bình Thịnh Vượng. Finally, An Bình Ưu Việt has the smallest contract period and insufficient to Nhi and Husband's need (20<25). Therefore, An Bình Ưu Việt is excluded from consideration.
A12: Coverage Aspects | B12: 1. Coverage against 46 critical illnesses 2. Coverage up to 1,000 days of hospitalisation 3. Coverage up to 200% of Sum Insured against death 4. Attractive Contract Dividends and Premiums 5. Payment of benefits every 3 years starting from the 3rd contract anniversary | C12: 1. Death benefits: Up to 125% of insurance value in case of death. 2. Receive 100% of insurance money in case of permanent disability. 3. Preferential insurance fees for non-smokers: 10% lower than for smokers. | D12: 1. Total and permanent disability: 10% of insurance amount/year x 10 years. 2. Death benefits: 100% insurance amount. Includes insurance against cancer and fatal diseases. 3. Minimum sum insured received: 1 billion VNĐ. 4. Covers medical expenses before, during and after hospitalization, surgery and emergency expenses due to accidents abroad. | E12: An Bình Thịnh Vượng has customizable term life and generous death benefits, but premiums and benefits vary with financial situation. An Bình Ưu Việt has customizable term life and easily convert to other products of AIA to suit customer's needs without financial assessment, but benefits regarding protection against serious illnesses and hospital fee allowances are limited. Phú - Bảo An has unchanged premiums throughout the contract term, making financial planning an easy and flexible choice of protection period according to needs but a very costly insurance premium.
A13: Costs (Paying Period of 25 years) | B13: =B14*B59 -> 2.1833148e+08 | C13: Not enough Information | D13: =D14*B59 -> 4.4149662e+08 | E13: Phú - Bảo An annual premium is as twice as An Bình Thịnh Vượng. Although An Bình Ưu Việt have the lowest fee for the standard package on other terms, the riders still add on more fees.
A14: Annually Premium | B14: =D66+D72 -> 8733259.2 | C14: Not enough Information | D14: =D68+D74 -> 17659865
A16: SELECTION LIFE INSURANCE | B16: BẢO VIỆT AN BÌNH THỊNH VƯỢNG
A20: SUM INSURED CALCULATION
A22: PRESENT VALUE OF INCOME
A23: Nhi's After-Tax Income | L23: ='2. Human Capital & Pension Valu'!L17 -> 2.6234736e+08 | M23: ='2. Human Capital & Pension Valu'!M17 -> 2.5245397e+08 | N23: ='2. Human Capital & Pension Valu'!N17 -> 2.429577e+08 | O23: ='2. Human Capital & Pension Valu'!O17 -> 2.9510548e+08 | P23: ='2. Human Capital & Pension Valu'!P17 -> 2.8383262e+08 | Q23: ='2. Human Capital & Pension Valu'!Q17 -> 2.7302009e+08 | R23: ='2. Human Capital & Pension Valu'!R17 -> 2.626475e+08 | S23: ='2. Human Capital & Pension Valu'!S17 -> 2.5269543e+08 | ... AJ23: ='2. Human Capital & Pension Valu'!AJ17 -> 1.8974805e+08
A24: Husband's After-Tax Income | L24: ='2. Human Capital & Pension Valu'!L31 -> 3.3484344e+08 | M24: ='2. Human Capital & Pension Valu'!M31 -> 3.2231291e+08 | N24: ='2. Human Capital & Pension Valu'!N31 -> 3.1028009e+08 | O24: ='2. Human Capital & Pension Valu'!O31 -> 2.9872362e+08 | P24: ='2. Human Capital & Pension Valu'!P31 -> 2.8761197e+08 | Q24: ='2. Human Capital & Pension Valu'!Q31 -> 3.7310535e+08 | R24: ='2. Human Capital & Pension Valu'!R31 -> 3.5858366e+08 | S24: ='2. Human Capital & Pension Valu'!S31 -> 3.4466942e+08 | ... AJ24: ='2. Human Capital & Pension Valu'!AJ31 -> 1.7665061e+08
A25: Total Nhi's After-Tax Income | B25: =SUM(K23:AJ23) -> 6.0757664e+09
A26: Total Husband's After-Tax Income | B26: =SUM(K24:AJ24) -> 6.811972e+09
A28: PRESENT VALUE OF LIVING EXPENSES
A29: Family Expenses | L29: ='2. Consumption Needs'!L16 -> 6.0063806e+08 | M29: ='2. Consumption Needs'!M16 -> 5.8865537e+08 | N29: ='2. Consumption Needs'!N16 -> 6.0566804e+08 | O29: ='2. Consumption Needs'!O16 -> 5.9115515e+08 | P29: ='2. Consumption Needs'!P16 -> 5.7727252e+08 | Q29: ='2. Consumption Needs'!Q16 -> 5.3829624e+08 | R29: ='2. Consumption Needs'!R16 -> 5.2500699e+08 | S29: ='2. Consumption Needs'!S16 -> 5.1287499e+08 | ... AJ29: ='2. Consumption Needs'!AJ16 -> 3.2107233e+08
A30: Deduction for Nhi or Husband Expenses
A31: Living Expenses | L31: =SUM('2. Consumption Needs'!G30:G31,'2. Consumption Needs'!G39,'2. Consumption Needs'!G43:G44,'2. Consumption Needs'!G47,'2. Consumption Needs'!G55)/2+435000*12 -> 1.2751805e+08 | M31: =$L$31 -> 1.2751805e+08 | N31: =$L$31 -> 1.2751805e+08 | O31: =$L$31 -> 1.2751805e+08 | P31: =$L$31 -> 1.2751805e+08 | Q31: =$L$31 -> 1.2751805e+08 | R31: =$L$31 -> 1.2751805e+08 | S31: =$L$31 -> 1.2751805e+08 | T31: =$L$31 -> 1.2751805e+08 | ... AJ31: =$L$31 -> 1.2751805e+08
A32: Health Insurance | L32: ='4. Health and Car Insurance'!B21 -> 3008750 | M32: =$L$32 -> 3008750 | N32: =$L$32 -> 3008750 | O32: =$L$32 -> 3008750 | P32: =$L$32 -> 3008750 | Q32: =$L$32 -> 3008750 | R32: =$L$32 -> 3008750 | S32: =$L$32 -> 3008750 | T32: =$L$32 -> 3008750 | U32: ='4. Health and Car Insurance'!B22 -> 3369800 | V32: =$U$32 -> 3369800 | W32: =$U$32 -> 3369800 | X32: =$U$32 -> 3369800 | Y32: =$U$32 -> 3369800 | Z32: =$U$32 -> 3369800 | AA32: =$U$32 -> 3369800 | AB32: =$U$32 -> 3369800 | AC32: =$U$32 -> 3369800 | AD32: =$U$32 -> 3369800 | AE32: ='4. Health and Car Insurance'!B23 -> 3610500 | AF32: =$AE$32 -> 3610500 | AG32: =$AE$32 -> 3610500 | AH32: =$AE$32 -> 3610500 | AI32: =$AE$32 -> 3610500 | AJ32: =$AE$32 -> 3610500
A33: Family Expenses when Nhi or Husband die | L33: =L29-SUM(L31:L32) -> 4.7011126e+08 | M33: =M29-SUM(M31:M32) -> 4.5812857e+08 | N33: =N29-SUM(N31:N32) -> 4.7514124e+08 | O33: =O29-SUM(O31:O32) -> 4.6062835e+08 | P33: =P29-SUM(P31:P32) -> 4.4674572e+08 | Q33: =Q29-SUM(Q31:Q32) -> 4.0776944e+08 | R33: =R29-SUM(R31:R32) -> 3.9448019e+08 | S33: =S29-SUM(S31:S32) -> 3.8234819e+08 | ... AJ33: =AJ29-SUM(AJ31:AJ32) -> 1.8994378e+08
A34: Total Living Expenses Needed | B34: =SUM(K33:AJ33) -> 8.9299216e+09
A36: AMOUNT NEEDED
A37: CATEGORIES | B37: AMOUNT
A38: Present Value of Income
A39: Nhi's After-Tax Income | B39: =B25 -> 6.0757664e+09
A40: Husband's After-Tax Income | B40: =B26 -> 6.811972e+09
A41: Funeral Allowance | B41: 23400000 | C41: Funeral Allowance
A42: Emergency Fund, Savings Account, Investment Account | B42: =('3. Funding Allocation'!Q14+'3. Funding Allocation'!U14+'3. Funding Allocation'!L14)/((1+C5)*(1+D5)*(1+E5)*(1+F5)*(1+G5)*(1+H5)^5) -> 1.4846122e+09
A43: Present Value of Expenses
A44: Family Living Expenses | B44: =B34 -> 8.9299216e+09
A45: Funeral Expenses | B45: 79000000 | C45: Funeral Expenses
A46: Burital Plot (Hạc Cảnh Viên) | B46: 71000000 | C46: Burital Plot
A47: Apartment Inheritance | B47: 0 | C47: Apartment Inheritance
A48: Car Inheritance | B48: ='2. Consumption Needs'!K47*(1-22%)*12% -> 41090400 | C48: Car Inheritance
A49: Motorbike Inheritance | B49: ='2. Balance Sheet & Cashflow Sta'!B14*30%*1% -> 190771.5 | C49: Motorbike Inheritance
A50: Investment Account (Bond, Stock) Inheritance | B50: ='3. Funding Allocation'!U14/((1+C5)*(1+D5)*(1+E5)*(1+F5)*(1+G5)*(1+H5)^5)*10% -> 1.3073712e+08 | C50: Bond, Stock Inheritance
A51: Relevant Documentations | B51: 1000000
A52: Amount Needed when Nhi die | B52: =SUM(B44:B51)-SUM(B40:B42) -> 9.3295566e+08
A53: Amount Needed when Husband die | B53: =SUM(B44:B51)-(B39+B41+B42) -> 1.6691613e+09
A55: SUM INSURED NEEDED WHEN NHI DIE IN 2034 | B55: =B52*(1+$C$5)*(1+$D$5)*(1+$E$5)*(1+$F$5)*(1+$G$5)*(1+$H$5)^(K2-$H$2+1) -> 1.1998375e+09
A56: SUM INSURED NEEDED WHEN HUSBAND DIE IN 2034 | B56: =B53*(1+$C$5)*(1+$D$5)*(1+$E$5)*(1+$F$5)*(1+$G$5)*(1+$H$5)^(K2-$H$2+1) -> 2.1466427e+09
A58: LIFE INSURANCE EXPENSES
A59: Premium Payout Period (year) | B59: 25
A60: Insurance Term (year) | B60: =B59 -> 25
A61: Total Annual Premium | B61: =D66+D72 -> 8733259.2
A62: Total Received at Maturity | B62: =E66+E72 -> 6.2666315e+09 | C62: Maturity
A64: FOR NHI
A65: Package | B65: Ultimately death benefits (without any other insurance benefits) | C65: Insurance value (death benefit payout) | D65: Annually Insurance Premium | E65: Amount Received at Maturity
A66: Bảo Việt An Bình Thịnh Vượng | B66: 2 | C66: =B55/B66 -> 5.9991877e+08 | D66: =C66*97.5%/1000*133.83/B59 -> 3131198 | E66: =B55+10%*C66*(1.0365^22+1.0365^19+1.0365^16+1.0365^13+1.0365^10+1.0365^7+1.0365^4+1.0365)+B59*2%*C66 -> 2.2468203e+09
A67: AIA An Bình Ưu Việt | B67: 1.25 | C67: =B55/B67 -> 9.5987003e+08 | D67: Not enough Information
A68: Prudential Phú - Bảo An | B68: 1 | C68: =B55/B68 -> 1.1998375e+09 | D68: =C68/1000*4.95 -> 5939195.8
A70: FOR HUSBAND
A71: Package | B71: Ultimately death benefits (without any other insurance benefits) | C71: Insurance value (death benefit payout) | D71: Annually Insurance Premium | E71: Amount Received at Maturity
A72: Bảo Việt An Bình Thịnh Vượng | B72: 2 | C72: =$B$56/B72 -> 1.0733213e+09 | D72: =C72*97.5%/1000*133.83/B59 -> 5602061.2 | E72: =B56+10%*C72*(1.0365^22+1.0365^19+1.0365^16+1.0365^13+1.0365^10+1.0365^7+1.0365^4+1.0365)+B59*2%*C72 -> 4.0198112e+09
A73: AIA An Bình Ưu Việt | B73: 1.25 | C73: =$B$56/B73 -> 1.7173141e+09 | D73: Not enough Information
A74: Prudential Phú - Bảo An | B74: 1 | C74: =$B$56/B74 -> 2.1466427e+09 | D74: =C74/1000*5.46 -> 11720669
